Workbook
Name борт_2013: Ценообразование!$B$9:$D$11
Name борт_2513: Ценообразование!$B$12:$D$14
Name борт_2515: Ценообразование!$B$15:$D$17
Name борт_3015: Ценообразование!$B$18:$D$20
Name борт_3515: Ценообразование!$B$21:$D$23
Name борт_4015: Ценообразование!$B$24:$D$26
Name колесо: Ценообразование!$B$27:$D$29
Name Кузов_2013: 'Виды прицепов'!$C$4:$I$6
Name кузов_2513: 'Виды прицепов'!$C$7:$N$9
Name кузов_2515: 'Виды прицепов'!$C$10:$I$12
Name кузов_3015: 'Виды прицепов'!$C$13:$I$15
Name кузов_3515: 'Виды прицепов'!$C$16:$I$18
Name кузов_4015: 'Виды прицепов'!$C$19:$N$21
Name матрица: 'Матрица основная'!$A$4:$Q$509
Name опорное_колесо: Ценообразование!$B$33:$D$34
Name Платформа: Ценообразование!$A$2:$B$7
Name платформа2: Ценообразование!$E$4:$F$7
Name Покупатели: Покупатели!$C$1:$N$835
Name ПРИЦЕПЫ: Прицепы!$C$2:$N$1073
Name Реестр_Договоров: 'Реестр договоров'!$A$1:$D$899
Name Св_табл_ЮЛ: 'Сводная таблица ЮЛ'!$A$1:$AB$57
Name Сводная_таблица: 'Сводная таблица ЮЛ'!$A$2:$U$407
Name Сводная_таблица: 'Сводная таблица ФЛ'!$A$2:$U$899
Name ступица: Ценообразование!$B$30:$D$32
Name тент_2013: Ценообразование!$B$35:$D$38
Name тент_2513: Ценообразование!$B$39:$D$42
Name тент_2515: Ценообразование!$B$43:$D$45
Name тент_3015: Ценообразование!$B$46:$D$48
Name тент_3515: Ценообразование!$B$49:$C$51
Name тент_4015: Ценообразование!$B$52:$D$54
Name Юр_лица: 'юр лица'!$C$1:$T$38

Sheet Реестр договоров
B1: дата | C1: фамилия | D1: VIN
A2: 1161 | B2: 45447 | C2: =Покупатели!C2 -> Белоногова | D2: =VLOOKUP(C2,Покупатели!$C$2:$Q$738,15,0) -> MX4000002R0001522
A3: 1162 | B3: 45449 | C3: =Покупатели!C3 -> Рахманов | D3: =VLOOKUP(C3,Покупатели!$C$2:$Q$738,15,0) -> MX4000002R0001502
A4: 1163 | B4: 45450 | C4: =Покупатели!C6 -> Кулиева | D4: =VLOOKUP(C4,Покупатели!$C$2:$Q$738,15,0) -> MX4000002R0001511
A5: 1164 | B5: 45451 | C5: =Покупатели!C4 -> Петрик | D5: =VLOOKUP(C5,Покупатели!$C$2:$Q$738,15,0) -> MX4000002R0001518
A6: 1165 | B6: 45451 | C6: =Покупатели!C5 -> Ребенков | D6: =VLOOKUP(C6,Покупатели!$C$2:$Q$738,15,0) -> MX4000002R0001573
A7: 1166 | B7: 45451 | C7: =Покупатели!C7 -> Темирбаев | D7: =VLOOKUP(C7,Покупатели!$C$2:$Q$738,15,0) -> MX4000002R0001455
A8: 1167 | B8: 45453 | C8: =Покупатели!C8 -> Доспергенов | D8: =VLOOKUP(C8,Покупатели!$C$2:$Q$738,15,0) -> MX4000002R0001719
A9: 1168 | B9: 45451 | C9: =Покупатели!C9 -> Касымов | D9: =VLOOKUP(C9,Покупатели!$C$2:$Q$738,15,0) -> MX4000002R0001642
A10: 1169 | B10: 45455 | C10: =Покупатели!C10 -> Сулейменов 2 | D10: =VLOOKUP(C10,Покупатели!$C$2:$Q$738,15,0) -> MX4000002R0001659
A11: 1170 | B11: 45460 | C11: =Покупатели!C11 -> Курбанова | D11: =VLOOKUP(C11,Покупатели!$C$2:$Q$738,15,0) -> MX4000002R0001508
A12: 1171 | B12: 45461 | C12: =Покупатели!C12 -> Абайқызы | D12: =VLOOKUP(C12,Покупатели!$C$2:$Q$738,15,0) -> MX4000002R0001517
A13: 1172 | B13: 45461 | C13: =Покупатели!C13 -> Меньшиков | D13: =VLOOKUP(C13,Покупатели!$C$2:$Q$738,15,0) -> MX4000002R0001538
A14: 1173 | B14: 45462 | C14: =Покупатели!C14 -> Билочук | D14: =VLOOKUP(C14,Покупатели!$C$2:$Q$738,15,0) -> MX4000002R0001653
A15: 1174 | B15: 45463 | C15: =Покупатели!C15 -> Ягминас | D15: =VLOOKUP(C15,Покупатели!$C$2:$Q$738,15,0) -> MX4000002R0001654
A16: 1175 | B16: 45464 | C16: =Покупатели!C16 -> Костюков1 | D16: =VLOOKUP(C16,Покупатели!$C$2:$Q$738,15,0) -> MX4000002R0001506
A17: 1176 | B17: 45464 | C17: =Покупатели!C18 -> Байзаков | D17: =VLOOKUP(C17,Покупатели!$C$2:$Q$738,15,0) -> MX4000002R0001680
A18: 1177 | B18: 45464 | C18: =Покупатели!C17 -> Оспанова | D18: =VLOOKUP(C18,Покупатели!$C$2:$Q$738,15,0) -> MX4000002R0001497
A19: 1178 | B19: 45464 | C19: =Покупатели!C19 -> Шапарев | D19: =VLOOKUP(C19,Покупатели!$C$2:$Q$738,15,0) -> MX4000002R0001516
A20: 1179 | B20: 45464 | C20: =Покупатели!C20 -> Бикенова | D20: =VLOOKUP(C20,Покупатели!$C$2:$Q$738,15,0) -> MX4000002R0001643
A21: 1180 | B21: 45464 | C21: =Покупатели!C21 -> Боровиков | D21: =VLOOKUP(C21,Покупатели!$C$2:$Q$738,15,0) -> MX4000002R0001521
A22: 1181 | B22: 45465 | C22: =Покупатели!C22 -> Гаврилюк | D22: =VLOOKUP(C22,Покупатели!$C$2:$Q$738,15,0) -> MX4000002R0001572
A23: 1182 | B23: 45465 | C23: =Покупатели!C23 -> Каримов | D23: =VLOOKUP(C23,Покупатели!$C$2:$Q$738,15,0) -> MX4000002R0001481
A24: 1183 | B24: 45465 | C24: =Покупатели!C24 -> Базимов | D24: =VLOOKUP(C24,Покупатели!$C$2:$Q$738,15,0) -> MX4000002R0001569
A25: 1184 | B25: 45465 | C25: =Покупатели!C25 -> Жунусов1 | D25: =VLOOKUP(C25,Покупатели!$C$2:$Q$738,15,0) -> MX4000002R0001500
A26: 1185 | B26: 45465 | C26: =Покупатели!C26 -> Бирюков | D26: =VLOOKUP(C26,Покупатели!$C$2:$Q$738,15,0) -> MX4000002R0001571
A27: 1186 | B27: 45467 | C27: =Покупатели!C27 -> Сейдахмет | D27: =VLOOKUP(C27,Покупатели!$C$2:$Q$738,15,0) -> MX4000002R0001507
A28: 1187 | B28: 45467 | C28: =Покупатели!C28 -> Некерев | D28: =VLOOKUP(C28,Покупатели!$C$2:$Q$738,15,0) -> MX4000002R0001468
A29: 1188 | B29: 45467 | C29: =Покупатели!C29 -> Мещеряков | D29: =VLOOKUP(C29,Покупатели!$C$2:$Q$738,15,0) -> MX4000002R0001664
A30: 1189 | B30: 45467 | C30: =Покупатели!C30 -> Айтимов 1 | D30: =VLOOKUP(C30,Покупатели!$C$2:$Q$738,15,0) -> MX4000002R0001462
... A52: 1211 | B52: 45475 | C52: =Покупатели!C52 -> Дуйсеков | D52: =VLOOKUP(C52,Покупатели!$C$2:$Q$738,15,0) -> MX4000002R0001574
A53: 1212 | B53: 45475 | C53: =Покупатели!C54 -> Грабовский | D53: =VLOOKUP(C53,Покупатели!$C$2:$Q$738,15,0) -> MX4000002R0001663
A54: 1213 | B54: 45476 | C54: =Покупатели!C53 -> Пияшкин | D54: =VLOOKUP(C54,Покупатели!$C$2:$Q$738,15,0) -> MX4000002R0001671
A55: 1214 | B55: 45476 | C55: =Покупатели!C55 -> Жумангужина | D55: =VLOOKUP(C55,Покупатели!$C$2:$Q$738,15,0) -> MX4000002R0001657
A56: 1215 | B56: 45476 | C56: =Покупатели!C56 -> Белгибаева | D56: =VLOOKUP(C56,Покупатели!$C$2:$Q$738,15,0) -> MX4000002R0001677
A57: 1216 | B57: 45476 | C57: =Покупатели!C57 -> Харламов 1 | D57: =VLOOKUP(C57,Покупатели!$C$2:$Q$738,15,0) -> MX4000002R0001509
A58: 1217 | B58: 45477 | C58: =Покупатели!C58 -> Батяйкин | D58: =VLOOKUP(C58,Покупатели!$C$2:$Q$738,15,0) -> MX4000004R0001606
A59: 1218 | B59: 45478 | C59: =Покупатели!C60 -> Волкова | D59: =VLOOKUP(C59,Покупатели!$C$2:$Q$738,15,0) -> MX4000002R0001560
A60: 1219 | B60: 45478 | C60: =Покупатели!C61 -> Бопышев | D60: =VLOOKUP(C60,Покупатели!$C$2:$Q$738,15,0) -> MX4000002R0001647
A61: 1220 | B61: 45478 | C61: =Покупатели!C62 -> Дерюгин | D61: =VLOOKUP(C61,Покупатели!$C$2:$Q$738,15,0) -> MX4000002R0001460
A62: 1221 | B62: 45479 | C62: =Покупатели!C63 -> Туртаева | D62: =VLOOKUP(C62,Покупатели!$C$2:$Q$738,15,0) -> MX4000002R0001456
A63: 1222 | B63: 45478 | C63: ='юр лица'!C2 -> "ПК Эффект" | D63: MX4000002R0001487
A64: 1223 | B64: 45481 | C64: =Покупатели!C64 -> Ворошилов | D64: =VLOOKUP(C64,Покупатели!$C$2:$Q$738,15,0) -> MX4000002R0001484
A65: 1224 | B65: 45481 | C65: =Покупатели!C59 -> Куликова | D65: =VLOOKUP(C65,Покупатели!$C$2:$Q$738,15,0) -> MX4000002R0001578
A66: 1225 | B66: 45482 | C66: =Покупатели!C65 -> Мусаинов | D66: =VLOOKUP(C66,Покупатели!$C$2:$Q$738,15,0) -> MX4000002R0001475
A67: 1226 | B67: 45482 | C67: =Покупатели!C66 -> Кенжеахмет | D67: =VLOOKUP(C67,Покупатели!$C$2:$Q$738,15,0) -> MX4000002R0001646
A68: 1227 | B68: 45484 | C68: =Покупатели!C67 -> Сатыбаев | D68: =VLOOKUP(C68,Покупатели!$C$2:$Q$738,15,0) -> MX4000002R0001711
A69: 1228 | B69: 45484 | C69: =Покупатели!C68 -> Мускеев | D69: =VLOOKUP(C69,Покупатели!$C$2:$Q$738,15,0) -> MX4000002R0001689
A70: 1229 | B70: 45484 | C70: =Покупатели!C69 -> Жакупов | D70: =VLOOKUP(C70,Покупатели!$C$2:$Q$738,15,0) -> MX4000002R0001670
A71: 1230 | B71: 45485 | C71: =Покупатели!C70 -> Досболов | D71: =VLOOKUP(C71,Покупатели!$C$2:$Q$738,15,0) -> MX4000002R0001470
A72: 1231 | B72: 45485 | C72: =Покупатели!C71 -> Веретенников | D72: =VLOOKUP(C72,Покупатели!$C$2:$Q$738,15,0) -> MX4000002R0001472
A73: 1232 | B73: 45485 | C73: ='юр лица'!C3 -> "BASTAU QAZ" | D73: MX4000002R0001635
A74: 1233 | B74: 45488 | C74: =Покупатели!C72 -> Тимкина | D74: =VLOOKUP(C74,Покупатели!$C$2:$Q$738,15,0) -> MX4000002R0001622
A75: 1234 | B75: 45489 | C75: =Покупатели!C73 -> Джунуспеков | D75: =VLOOKUP(C75,Покупатели!$C$2:$Q$738,15,0) -> MX4000002R0001672
A76: 1235 | B76: 45489 | C76: =Покупатели!C74 -> Жакаев | D76: =VLOOKUP(C76,Покупатели!$C$2:$Q$738,15,0) -> MX4000002R0001675
A77: 1236 | B77: 45491 | C77: =Покупатели!C75 -> Казиханов | D77: =VLOOKUP(C77,Покупатели!$C$2:$Q$738,15,0) -> MX4000002R0001682
A78: 1237 | B78: 45491 | C78: =Покупатели!C76 -> Кобжасаров | D78: =VLOOKUP(C78,Покупатели!$C$2:$Q$738,15,0) -> MX4000002R0001661
A79: 1238 | B79: 45491 | C79: =Покупатели!C77 -> Токтагулов | D79: =VLOOKUP(C79,Покупатели!$C$2:$Q$738,15,0) -> MX4000002R0001467
A80: 1239 | B80: 45492 | C80: =Покупатели!C78 -> Кальтенбергер | D80: =VLOOKUP(C80,Покупатели!$C$2:$Q$738,15,0) -> MX4000002R0001667
A81: 1240 | B81: 45492 | C81: =Покупатели!C79 -> Ли | D81: =VLOOKUP(C81,Покупатели!$C$2:$Q$738,15,0) -> MX4000002R0001469
A82: 1241 | B82: 45496 | C82: =Покупатели!C80 -> Кондратьев | D82: =VLOOKUP(C82,Покупатели!$C$2:$Q$738,15,0) -> MX4000002R0001478
A83: 1242 | B83: 45496 | C83: =Покупатели!C81 -> Жаксыбаев | D83: =VLOOKUP(C83,Покупатели!$C$2:$Q$738,15,0) -> MX4000002R0001501
A84: 1243 | B84: 45496 | C84: =Покупатели!C82 -> Хомидов | D84: =VLOOKUP(C84,Покупатели!$C$2:$Q$738,15,0) -> MX4000002R0001477
A85: 1244 | B85: 45497 | C85: =Покупатели!C84 -> Зоркальцева | D85: =VLOOKUP(C85,Покупатели!$C$2:$Q$738,15,0) -> MX4000002R0001693
A86: 1245 | B86: 45497 | C86: =Покупатели!C83 -> Нусипов | D86: =VLOOKUP(C86,Покупатели!$C$2:$Q$738,15,0) -> MX4000002R0001495
A87: 1246 | B87: 45497 | C87: =Покупатели!C85 -> Мусалиев | D87: =VLOOKUP(C87,Покупатели!$C$2:$Q$738,15,0) -> MX4000002R0001674
A88: 1247 | B88: 45498 | C88: ='юр лица'!C4 -> "Akzhar mining" | D88: MX4000002R0001725
A89: 1248 | B89: 45498 | C89: =Покупатели!C86 -> Хусуров | D89: =VLOOKUP(C89,Покупатели!$C$2:$Q$738,15,0) -> MX4000002P0001412
A90: 1249 | B90: 45499 | C90: =Покупатели!C87 -> Мошков | D90: =VLOOKUP(C90,Покупатели!$C$2:$Q$738,15,0) -> MX4000002R0001662
A91: 1250 | B91: 45503 | C91: =Покупатели!C88 -> Калменова | D91: =VLOOKUP(C91,Покупатели!$C$2:$Q$738,15,0) -> MX4000002R0001660
A92: 1251 | B92: 45504 | C92: =Покупатели!C89 -> Махмутов | D92: =VLOOKUP(C92,Покупатели!$C$2:$Q$738,15,0) -> MX4000002R0001691
A93: 1252 | B93: 45504 | C93: =Покупатели!C90 -> Якубов | D93: =VLOOKUP(C93,Покупатели!$C$2:$Q$738,15,0) -> MX4000002R0001491
A94: 1253 | B94: 45504 | C94: =Покупатели!C91 -> Гусевы | D94: =VLOOKUP(C94,Покупатели!$C$2:$Q$738,15,0) -> MX4000002R0001628
A95: 1254 | B95: 45504 | C95: =Покупатели!C92 -> Сейдеметов1 | D95: =VLOOKUP(C95,Покупатели!$C$2:$Q$738,15,0) -> MX4000002R0001582
A96: 1255 | B96: 45509 | C96: =Покупатели!C93 -> Бабенков | D96: =VLOOKUP(C96,Покупатели!$C$2:$Q$738,15,0) -> MX4000002R0001710
A97: 1256 | B97: 45510 | C97: =Покупатели!C94 -> Ахатов | D97: =VLOOKUP(C97,Покупатели!$C$2:$Q$738,15,0) -> MX4000002R0001490
A98: 1257 | B98: 45510 | C98: =Покупатели!C95 -> Легеза | D98: =VLOOKUP(C98,Покупатели!$C$2:$Q$738,15,0) -> MX4000002R0001696
A99: 1258 | B99: 45511 | C99: =Покупатели!C96 -> Коптлеуов 1 | D99: =VLOOKUP(C99,Покупатели!$C$2:$Q$738,15,0) -> MX4000002R0001552
A100: 1259 | B100: 45514 | C100: =Покупатели!C97 -> Егорова | D100: =VLOOKUP(C100,Покупатели!$C$2:$Q$738,15,0) -> MX4000002R0001453
... A125: 1284 | B125: 45532 | C125: =Покупатели!C122 -> Нурабаев | D125: =VLOOKUP(C125,Покупатели!$C$2:$Q$738,15,0) -> MX4000002R0001447
A126: 1285 | B126: 45532 | C126: "Sky Industrial Group" | D126: MX4000002R0001621
A127: 1286 | B127: 45532 | C127: =Покупатели!C123 -> Жұманғазы | D127: =VLOOKUP(C127,Покупатели!$C$2:$Q$738,15,0) -> MX4000002R0001736
A128: 1287 | B128: 45533 | C128: =Покупатели!C124 -> Омарова | D128: =VLOOKUP(C128,Покупатели!$C$2:$Q$738,15,0) -> MX4000002R0001731
A129: 1288 | B129: 45537 | C129: =Покупатели!C125 -> Гильмизянов | D129: =VLOOKUP(C129,Покупатели!$C$2:$Q$738,15,0) -> MX4000002R0001762
A130: 1290 | B130: 45537 | C130: =Покупатели!C126 -> Уристемов | D130: =VLOOKUP(C130,Покупатели!$C$2:$Q$738,15,0) -> MX4000002R0001760
A131: 1291 | B131: 45538 | C131: =Покупатели!C127 -> Нүкен | D131: =VLOOKUP(C131,Покупатели!$C$2:$Q$738,15,0) -> MX4000002R0001723
A132: 1292 | B132: 45539 | C132: =Покупатели!C128 -> Тасенов | D132: =VLOOKUP(C132,Покупатели!$C$2:$Q$738,15,0) -> MX4000002N0000672
A133: 1293 | B133: 45538 | C133: =Покупатели!C129 -> Волков | D133: =VLOOKUP(C133,Покупатели!$C$2:$Q$738,15,0) -> MX4000002R0001655
A134: 1294 | B134: 45539 | C134: =Покупатели!C130 -> Щербаков | D134: =VLOOKUP(C134,Покупатели!$C$2:$Q$738,15,0) -> MX4000002R0001761
A135: 1295 | B135: 45540 | C135: =Покупатели!C131 -> Губайдуллин | D135: =VLOOKUP(C135,Покупатели!$C$2:$Q$738,15,0) -> MX4000004R0001756
A136: 1296 | B136: 45540 | C136: =Покупатели!C132 -> Юрчук | D136: =VLOOKUP(C136,Покупатели!$C$2:$Q$738,15,0) -> MX4000002R0001765
A137: 1297 | B137: 45541 | C137: =Покупатели!C133 -> Абдукадырова | D137: =VLOOKUP(C137,Покупатели!$C$2:$Q$738,15,0) -> MX4000002R0001583
A138: 1298 | B138: 45541 | C138: =Покупатели!C134 -> Данегулов | D138: =VLOOKUP(C138,Покупатели!$C$2:$Q$738,15,0) -> MX4000002R0001766
... A141: 1301 | B141: 45544 | C141: =Покупатели!C137 -> Кожахметова | D141: =VLOOKUP(C141,Покупатели!$C$2:$Q$738,15,0) -> MX4000002R0001701
A142: 1302 | B142: 45544 | C142: =Покупатели!C737 -> Сейдеметов2 | D142: =VLOOKUP(C142,Покупатели!$C$2:$Q$738,15,0) -> MX4000002R0001730
A143: 1303 | B143: 45544 | C143: =Покупатели!C738 -> Сейдеметов | D143: =VLOOKUP(C143,Покупатели!$C$2:$Q$738,15,0) -> MX4000002R0001734
A144: 1304 | B144: 45544 | C144: =Покупатели!C138 -> Калмамбетов | D144: =VLOOKUP(C144,Покупатели!$C$2:$Q$738,15,0) -> MX4000004R0001755
A145: 1305 | B145: 45545 | C145: =Покупатели!C139 -> Камаев | D145: =VLOOKUP(C145,Покупатели!$C$2:$Q$738,15,0) -> MX4000002R0001758
A146: 1306 | B146: 45545 | C146: =Покупатели!C140 -> Грачев | D146: =VLOOKUP(C146,Покупатели!$C$2:$Q$738,15,0) -> MX4000002R0001733
A147: 1307 | B147: 45545 | C147: =Покупатели!C141 -> Батолин | D147: =VLOOKUP(C147,Покупатели!$C$2:$Q$738,15,0) -> MX4000002R0001602
...

Sheet Прицепы
A1: Отметка времени | C1: VIN код | D1: Прицеп | E1: Борт | F1: Колесо | G1: Ступица | H1: Тент-каркас | I1: Дата выпуска | J1: Откатное колесо | K1: Склад | L1: Количество осей | M1: Артикул | N1: Статус
A2: 45520.74 | C2: MX4000003R0001752 | D2: Прицеп 2,0*1,25 м (до 750 кг.) | E2: нет | F2: нет | G2: R13 | H2: нет | I2: 45520 | J2: есть | K2: Кокшетау | L2: 1 ось | M2: =IFERROR(__xludf.DUMMYFUNCTION("JOIN("""",VLOOKUP(D2,'для артикула'!$A$2:$B$7,2,0),VLOOKUP(G2,'для артикула'!$A$13:$B$14,2,0),VLOOKUP(E2,'для артикула'!$A$9:$B$11,2,0),VLOOKUP(F2,'для артикула'!$A$17:$B$19,2,0),VLOOKUP(J2,'для артикула'!$A$22:$B$23,2,0),VLOOKUP(H2,'для артикула'!$A$26:$"&"B$30,2,0))"),"002-2013-OK") -> 002-2013-OK | N2: =IF(ISNUMBER(MATCH(C2, 'Реестр договоров'!$D$2:$D$900, 0)), "Продано", "В наличии") -> Продано
A3: 45632.55 | C3: MX4000002R0001856 | D3: Прицеп 2,0*1,25 м (до 750 кг.) | E3: 50 | F3: R13 | G3: R13 | H3: нет | I3: 45628 | J3: есть | K3: Алматы | L3: 1 ось | M3: =IFERROR(__xludf.DUMMYFUNCTION("JOIN("""",VLOOKUP(D3,'для артикула'!$A$2:$B$7,2,0),VLOOKUP(G3,'для артикула'!$A$13:$B$14,2,0),VLOOKUP(E3,'для артикула'!$A$9:$B$11,2,0),VLOOKUP(F3,'для артикула'!$A$17:$B$19,2,0),VLOOKUP(J3,'для артикула'!$A$22:$B$23,2,0),VLOOKUP(H3,'для артикула'!$A$26:$"&"B$30,2,0))"),"002-2013E50Q13-OK") -> 002-2013E50Q13-OK | N3: =IF(ISNUMBER(MATCH(C3, 'Реестр договоров'!$D$2:$D$900, 0)), "Продано", "В наличии") -> Продано
A4: 45646.439 | C4: MX4000002R0001852 | D4: Прицеп 2,0*1,25 м (до 750 кг.) | E4: 50 | F4: R13 | G4: R13 | H4: нет | I4: 45641 | J4: есть | K4: Алматы | L4: 1 ось | M4: =IFERROR(__xludf.DUMMYFUNCTION("JOIN("""",VLOOKUP(D4,'для артикула'!$A$2:$B$7,2,0),VLOOKUP(G4,'для артикула'!$A$13:$B$14,2,0),VLOOKUP(E4,'для артикула'!$A$9:$B$11,2,0),VLOOKUP(F4,'для артикула'!$A$17:$B$19,2,0),VLOOKUP(J4,'для артикула'!$A$22:$B$23,2,0),VLOOKUP(H4,'для артикула'!$A$26:$"&"B$30,2,0))"),"002-2013E50Q13-OK") -> 002-2013E50Q13-OK | N4: =IF(ISNUMBER(MATCH(C4, 'Реестр договоров'!$D$2:$D$900, 0)), "Продано", "В наличии") -> Продано
A5: 45617.566 | C5: MX4000002R0001849 | D5: Прицеп 2,0*1,25 м (до 750 кг.) | E5: 50 | F5: R13 | G5: R13 | H5: нет | I5: 45617 | J5: есть | K5: Алматы | L5: 1 ось | M5: =IFERROR(__xludf.DUMMYFUNCTION("JOIN("""",VLOOKUP(D5,'для артикула'!$A$2:$B$7,2,0),VLOOKUP(G5,'для артикула'!$A$13:$B$14,2,0),VLOOKUP(E5,'для артикула'!$A$9:$B$11,2,0),VLOOKUP(F5,'для артикула'!$A$17:$B$19,2,0),VLOOKUP(J5,'для артикула'!$A$22:$B$23,2,0),VLOOKUP(H5,'для артикула'!$A$26:$"&"B$30,2,0))"),"002-2013E50Q13-OK") -> 002-2013E50Q13-OK | N5: =IF(ISNUMBER(MATCH(C5, 'Реестр договоров'!$D$2:$D$900, 0)), "Продано", "В наличии") -> Продано
A6: 45617.529 | C6: MX4000002R0001848 | D6: Прицеп 2,0*1,25 м (до 750 кг.) | E6: 50 | F6: R13 | G6: R13 | H6: нет | I6: 45617 | J6: есть | K6: Алматы | L6: 1 ось | M6: =IFERROR(__xludf.DUMMYFUNCTION("JOIN("""",VLOOKUP(D6,'для артикула'!$A$2:$B$7,2,0),VLOOKUP(G6,'для артикула'!$A$13:$B$14,2,0),VLOOKUP(E6,'для артикула'!$A$9:$B$11,2,0),VLOOKUP(F6,'для артикула'!$A$17:$B$19,2,0),VLOOKUP(J6,'для артикула'!$A$22:$B$23,2,0),VLOOKUP(H6,'для артикула'!$A$26:$"&"B$30,2,0))"),"002-2013E50Q13-OK") -> 002-2013E50Q13-OK | N6: =IF(ISNUMBER(MATCH(C6, 'Реестр договоров'!$D$2:$D$900, 0)), "Продано", "В наличии") -> Продано
A7: 45617.528 | C7: MX4000002R0001847 | D7: Прицеп 2,0*1,25 м (до 750 кг.) | E7: 50 | F7: R13 | G7: R13 | H7: нет | I7: 45617 | J7: есть | K7: Алматы | L7: 1 ось | M7: =IFERROR(__xludf.DUMMYFUNCTION("JOIN("""",VLOOKUP(D7,'для артикула'!$A$2:$B$7,2,0),VLOOKUP(G7,'для артикула'!$A$13:$B$14,2,0),VLOOKUP(E7,'для артикула'!$A$9:$B$11,2,0),VLOOKUP(F7,'для артикула'!$A$17:$B$19,2,0),VLOOKUP(J7,'для артикула'!$A$22:$B$23,2,0),VLOOKUP(H7,'для артикула'!$A$26:$"&"B$30,2,0))"),"002-2013E50Q13-OK") -> 002-2013E50Q13-OK | N7: =IF(ISNUMBER(MATCH(C7, 'Реестр договоров'!$D$2:$D$900, 0)), "Продано", "В наличии") -> Продано
A8: 45617.528 | C8: MX4000002R0001846 | D8: Прицеп 2,0*1,25 м (до 750 кг.) | E8: 50 | F8: R13 | G8: R13 | H8: нет | I8: 45617 | J8: есть | K8: Алматы | L8: 1 ось | M8: =IFERROR(__xludf.DUMMYFUNCTION("JOIN("""",VLOOKUP(D8,'для артикула'!$A$2:$B$7,2,0),VLOOKUP(G8,'для артикула'!$A$13:$B$14,2,0),VLOOKUP(E8,'для артикула'!$A$9:$B$11,2,0),VLOOKUP(F8,'для артикула'!$A$17:$B$19,2,0),VLOOKUP(J8,'для артикула'!$A$22:$B$23,2,0),VLOOKUP(H8,'для артикула'!$A$26:$"&"B$30,2,0))"),"002-2013E50Q13-OK") -> 002-2013E50Q13-OK | N8: =IF(ISNUMBER(MATCH(C8, 'Реестр договоров'!$D$2:$D$900, 0)), "Продано", "В наличии") -> Продано
A9: 45637.773 | C9: MX4000002R0001838 | D9: Прицеп 2,0*1,25 м (до 750 кг.) | E9: 50 | F9: R13 | G9: R13 | H9: нет | I9: 45637 | J9: есть | K9: Астана | L9: 1 ось | M9: =IFERROR(__xludf.DUMMYFUNCTION("JOIN("""",VLOOKUP(D9,'для артикула'!$A$2:$B$7,2,0),VLOOKUP(G9,'для артикула'!$A$13:$B$14,2,0),VLOOKUP(E9,'для артикула'!$A$9:$B$11,2,0),VLOOKUP(F9,'для артикула'!$A$17:$B$19,2,0),VLOOKUP(J9,'для артикула'!$A$22:$B$23,2,0),VLOOKUP(H9,'для артикула'!$A$26:$"&"B$30,2,0))"),"002-2013E50Q13-OK") -> 002-2013E50Q13-OK | N9: =IF(ISNUMBER(MATCH(C9, 'Реестр договоров'!$D$2:$D$900, 0)), "Продано", "В наличии") -> Продано
A10: 45610.653 | C10: MX4000002R0001837 | D10: Прицеп 2,0*1,25 м (до 750 кг.) | E10: 50 | F10: R13 | G10: R13 | H10: 30 | I10: 45610 | J10: есть | K10: Кокшетау | L10: 1 ось | M10: =IFERROR(__xludf.DUMMYFUNCTION("JOIN("""",VLOOKUP(D10,'для артикула'!$A$2:$B$7,2,0),VLOOKUP(G10,'для артикула'!$A$13:$B$14,2,0),VLOOKUP(E10,'для артикула'!$A$9:$B$11,2,0),VLOOKUP(F10,'для артикула'!$A$17:$B$19,2,0),VLOOKUP(J10,'для артикула'!$A$22:$B$23,2,0),VLOOKUP(H10,'для артикула'!$"&"A$26:$B$30,2,0))"),"002-2013E50Q13-OK30") -> 002-2013E50Q13-OK30 | N10: =IF(ISNUMBER(MATCH(C10, 'Реестр договоров'!$D$2:$D$900, 0)), "Продано", "В наличии") -> Продано
A11: 45604.421 | C11: MX4000002R0001836 | D11: Прицеп 2,0*1,25 м (до 750 кг.) | E11: 50 | F11: R13 | G11: R13 | H11: нет | I11: 45604 | J11: есть | K11: Кокшетау | L11: 1 ось | M11: =IFERROR(__xludf.DUMMYFUNCTION("JOIN("""",VLOOKUP(D11,'для артикула'!$A$2:$B$7,2,0),VLOOKUP(G11,'для артикула'!$A$13:$B$14,2,0),VLOOKUP(E11,'для артикула'!$A$9:$B$11,2,0),VLOOKUP(F11,'для артикула'!$A$17:$B$19,2,0),VLOOKUP(J11,'для артикула'!$A$22:$B$23,2,0),VLOOKUP(H11,'для артикула'!$"&"A$26:$B$30,2,0))"),"002-2013E50Q13-OK") -> 002-2013E50Q13-OK | N11: =IF(ISNUMBER(MATCH(C11, 'Реестр договоров'!$D$2:$D$900, 0)), "Продано", "В наличии") -> Продано
A12: 45637.812 | C12: MX4000002R0001831 | D12: Прицеп 2,0*1,25 м (до 750 кг.) | E12: 30 | F12: R13 | G12: R13 | H12: нет | I12: 45637 | J12: есть | K12: Астана | L12: 1 ось | M12: =IFERROR(__xludf.DUMMYFUNCTION("JOIN("""",VLOOKUP(D12,'для артикула'!$A$2:$B$7,2,0),VLOOKUP(G12,'для артикула'!$A$13:$B$14,2,0),VLOOKUP(E12,'для артикула'!$A$9:$B$11,2,0),VLOOKUP(F12,'для артикула'!$A$17:$B$19,2,0),VLOOKUP(J12,'для артикула'!$A$22:$B$23,2,0),VLOOKUP(H12,'для артикула'!$"&"A$26:$B$30,2,0))"),"002-2013E30Q13-OK") -> 002-2013E30Q13-OK | N12: =IF(ISNUMBER(MATCH(C12, 'Реестр договоров'!$D$2:$D$900, 0)), "Продано", "В наличии") -> Продано
A13: 45635.505 | C13: MX4000002R0001830 | D13: Прицеп 2,0*1,25 м (до 750 кг.) | E13: 50 | F13: R13 | G13: R13 | H13: нет | I13: 45628 | J13: есть | K13: Астана | L13: 1 ось | M13: =IFERROR(__xludf.DUMMYFUNCTION("JOIN("""",VLOOKUP(D13,'для артикула'!$A$2:$B$7,2,0),VLOOKUP(G13,'для артикула'!$A$13:$B$14,2,0),VLOOKUP(E13,'для артикула'!$A$9:$B$11,2,0),VLOOKUP(F13,'для артикула'!$A$17:$B$19,2,0),VLOOKUP(J13,'для артикула'!$A$22:$B$23,2,0),VLOOKUP(H13,'для артикула'!$"&"A$26:$B$30,2,0))"),"002-2013E50Q13-OK") -> 002-2013E50Q13-OK | N13: =IF(ISNUMBER(MATCH(C13, 'Реестр договоров'!$D$2:$D$900, 0)), "Продано", "В наличии") -> Продано
A14: 45629.598 | C14: MX4000002R0001827 | D14: Прицеп 2,0*1,25 м (до 750 кг.) | E14: 50 | F14: R13 | G14: R13 | H14: нет | I14: 45629 | J14: есть | K14: Алматы | L14: 1 ось | M14: =IFERROR(__xludf.DUMMYFUNCTION("JOIN("""",VLOOKUP(D14,'для артикула'!$A$2:$B$7,2,0),VLOOKUP(G14,'для артикула'!$A$13:$B$14,2,0),VLOOKUP(E14,'для артикула'!$A$9:$B$11,2,0),VLOOKUP(F14,'для артикула'!$A$17:$B$19,2,0),VLOOKUP(J14,'для артикула'!$A$22:$B$23,2,0),VLOOKUP(H14,'для артикула'!$"&"A$26:$B$30,2,0))"),"002-2013E50Q13-OK") -> 002-2013E50Q13-OK | N14: =IF(ISNUMBER(MATCH(C14, 'Реестр договоров'!$D$2:$D$900, 0)), "Продано", "В наличии") -> Продано
A15: 45617.528 | C15: MX4000002R0001826 | D15: Прицеп 2,0*1,25 м (до 750 кг.) | E15: 50 | F15: R13 | G15: R13 | H15: нет | I15: 45617 | J15: есть | K15: Алматы | L15: 1 ось | M15: =IFERROR(__xludf.DUMMYFUNCTION("JOIN("""",VLOOKUP(D15,'для артикула'!$A$2:$B$7,2,0),VLOOKUP(G15,'для артикула'!$A$13:$B$14,2,0),VLOOKUP(E15,'для артикула'!$A$9:$B$11,2,0),VLOOKUP(F15,'для артикула'!$A$17:$B$19,2,0),VLOOKUP(J15,'для артикула'!$A$22:$B$23,2,0),VLOOKUP(H15,'для артикула'!$"&"A$26:$B$30,2,0))"),"002-2013E50Q13-OK") -> 002-2013E50Q13-OK | N15: =IF(ISNUMBER(MATCH(C15, 'Реестр договоров'!$D$2:$D$900, 0)), "Продано", "В наличии") -> Продано
A16: 45617.601 | C16: MX4000002R0001825 | D16: Прицеп 2,0*1,25 м (до 750 кг.) | E16: 30 | F16: R13 | G16: R13 | H16: нет | I16: 45617 | J16: есть | K16: Алматы | L16: 1 ось | M16: =IFERROR(__xludf.DUMMYFUNCTION("JOIN("""",VLOOKUP(D16,'для артикула'!$A$2:$B$7,2,0),VLOOKUP(G16,'для артикула'!$A$13:$B$14,2,0),VLOOKUP(E16,'для артикула'!$A$9:$B$11,2,0),VLOOKUP(F16,'для артикула'!$A$17:$B$19,2,0),VLOOKUP(J16,'для артикула'!$A$22:$B$23,2,0),VLOOKUP(H16,'для артикула'!$"&"A$26:$B$30,2,0))"),"002-2013E30Q13-OK") -> 002-2013E30Q13-OK | N16: =IF(ISNUMBER(MATCH(C16, 'Реестр договоров'!$D$2:$D$900, 0)), "Продано", "В наличии") -> Продано
A17: 45617.527 | C17: MX4000002R0001824 | D17: Прицеп 2,0*1,25 м (до 750 кг.) | E17: 50 | F17: R13 | G17: R13 | H17: нет | I17: 45617 | J17: есть | K17: Алматы | L17: 1 ось | M17: =IFERROR(__xludf.DUMMYFUNCTION("JOIN("""",VLOOKUP(D17,'для артикула'!$A$2:$B$7,2,0),VLOOKUP(G17,'для артикула'!$A$13:$B$14,2,0),VLOOKUP(E17,'для артикула'!$A$9:$B$11,2,0),VLOOKUP(F17,'для артикула'!$A$17:$B$19,2,0),VLOOKUP(J17,'для артикула'!$A$22:$B$23,2,0),VLOOKUP(H17,'для артикула'!$"&"A$26:$B$30,2,0))"),"002-2013E50Q13-OK") -> 002-2013E50Q13-OK | N17: =IF(ISNUMBER(MATCH(C17, 'Реестр договоров'!$D$2:$D$900, 0)), "Продано", "В наличии") -> Продано
A18: 45652.487 | C18: MX4000002R0001823 | D18: Прицеп 2,0*1,25 м (до 750 кг.) | E18: 30 | F18: R13 | G18: R13 | H18: нет | I18: 45652 | J18: есть | K18: Алматы | L18: 1 ось | M18: =IFERROR(__xludf.DUMMYFUNCTION("JOIN("""",VLOOKUP(D18,'для артикула'!$A$2:$B$7,2,0),VLOOKUP(G18,'для артикула'!$A$13:$B$14,2,0),VLOOKUP(E18,'для артикула'!$A$9:$B$11,2,0),VLOOKUP(F18,'для артикула'!$A$17:$B$19,2,0),VLOOKUP(J18,'для артикула'!$A$22:$B$23,2,0),VLOOKUP(H18,'для артикула'!$"&"A$26:$B$30,2,0))"),"002-2013E30Q13-OK") -> 002-2013E30Q13-OK | N18: =IF(ISNUMBER(MATCH(C18, 'Реестр договоров'!$D$2:$D$900, 0)), "Продано", "В наличии") -> Продано
A19: 45644.555 | C19: MX4000002R0001822 | D19: Прицеп 2,0*1,25 м (до 750 кг.) | E19: 50 | F19: R13 | G19: R13 | H19: нет | I19: 45629 | J19: есть | K19: Алматы | L19: 1 ось | M19: =IFERROR(__xludf.DUMMYFUNCTION("JOIN("""",VLOOKUP(D19,'для артикула'!$A$2:$B$7,2,0),VLOOKUP(G19,'для артикула'!$A$13:$B$14,2,0),VLOOKUP(E19,'для артикула'!$A$9:$B$11,2,0),VLOOKUP(F19,'для артикула'!$A$17:$B$19,2,0),VLOOKUP(J19,'для артикула'!$A$22:$B$23,2,0),VLOOKUP(H19,'для артикула'!$"&"A$26:$B$30,2,0))"),"002-2013E50Q13-OK") -> 002-2013E50Q13-OK | N19: =IF(ISNUMBER(MATCH(C19, 'Реестр договоров'!$D$2:$D$900, 0)), "Продано", "В наличии") -> Продано
A20: 45617.527 | C20: MX4000002R0001821 | D20: Прицеп 2,0*1,25 м (до 750 кг.) | E20: 50 | F20: R13 | G20: R13 | H20: нет | I20: 45617 | J20: есть | K20: Алматы | L20: 1 ось | M20: =IFERROR(__xludf.DUMMYFUNCTION("JOIN("""",VLOOKUP(D20,'для артикула'!$A$2:$B$7,2,0),VLOOKUP(G20,'для артикула'!$A$13:$B$14,2,0),VLOOKUP(E20,'для артикула'!$A$9:$B$11,2,0),VLOOKUP(F20,'для артикула'!$A$17:$B$19,2,0),VLOOKUP(J20,'для артикула'!$A$22:$B$23,2,0),VLOOKUP(H20,'для артикула'!$"&"A$26:$B$30,2,0))"),"002-2013E50Q13-OK") -> 002-2013E50Q13-OK | N20: =IF(ISNUMBER(MATCH(C20, 'Реестр договоров'!$D$2:$D$900, 0)), "Продано", "В наличии") -> Продано
A21: 45609.514 | C21: MX4000002R0001820 | D21: Прицеп 2,0*1,25 м (до 750 кг.) | E21: 50 | F21: R13 | G21: R13 | H21: нет | I21: 45609 | J21: есть | K21: Алматы | L21: 1 ось | M21: =IFERROR(__xludf.DUMMYFUNCTION("JOIN("""",VLOOKUP(D21,'для артикула'!$A$2:$B$7,2,0),VLOOKUP(G21,'для артикула'!$A$13:$B$14,2,0),VLOOKUP(E21,'для артикула'!$A$9:$B$11,2,0),VLOOKUP(F21,'для артикула'!$A$17:$B$19,2,0),VLOOKUP(J21,'для артикула'!$A$22:$B$23,2,0),VLOOKUP(H21,'для артикула'!$"&"A$26:$B$30,2,0))"),"002-2013E50Q13-OK") -> 002-2013E50Q13-OK | N21: =IF(ISNUMBER(MATCH(C21, 'Реестр договоров'!$D$2:$D$900, 0)), "Продано", "В наличии") -> Продано
A22: 45588.5 | C22: MX4000002R0001817 | D22: Прицеп 2,0*1,25 м (до 750 кг.) | E22: 50 | F22: R13 | G22: R13 | H22: 30 | I22: 45588 | J22: есть | K22: Кокшетау | L22: 1 ось | M22: =IFERROR(__xludf.DUMMYFUNCTION("JOIN("""",VLOOKUP(D22,'для артикула'!$A$2:$B$7,2,0),VLOOKUP(G22,'для артикула'!$A$13:$B$14,2,0),VLOOKUP(E22,'для артикула'!$A$9:$B$11,2,0),VLOOKUP(F22,'для артикула'!$A$17:$B$19,2,0),VLOOKUP(J22,'для артикула'!$A$22:$B$23,2,0),VLOOKUP(H22,'для артикула'!$"&"A$26:$B$30,2,0))"),"002-2013E50Q13-OK30") -> 002-2013E50Q13-OK30 | N22: =IF(ISNUMBER(MATCH(C22, 'Реестр договоров'!$D$2:$D$900, 0)), "Продано", "В наличии") -> Продано
A23: 45583.611 | C23: MX4000002R0001816 | D23: Прицеп 2,0*1,25 м (до 750 кг.) | E23: 50 | F23: R13 | G23: R13 | H23: 30 | I23: 45583 | J23: есть | K23: Астана | L23: 1 ось | M23: =IFERROR(__xludf.DUMMYFUNCTION("JOIN("""",VLOOKUP(D23,'для артикула'!$A$2:$B$7,2,0),VLOOKUP(G23,'для артикула'!$A$13:$B$14,2,0),VLOOKUP(E23,'для артикула'!$A$9:$B$11,2,0),VLOOKUP(F23,'для артикула'!$A$17:$B$19,2,0),VLOOKUP(J23,'для артикула'!$A$22:$B$23,2,0),VLOOKUP(H23,'для артикула'!$"&"A$26:$B$30,2,0))"),"002-2013E50Q13-OK30") -> 002-2013E50Q13-OK30 | N23: =IF(ISNUMBER(MATCH(C23, 'Реестр договоров'!$D$2:$D$900, 0)), "Продано", "В наличии") -> Продано
A24: 45583.608 | C24: MX4000002R0001815 | D24: Прицеп 2,0*1,25 м (до 750 кг.) | E24: 30 | F24: R13 | G24: R13 | H24: 60 | I24: 45583 | J24: есть | K24: Астана | L24: 1 ось | M24: =IFERROR(__xludf.DUMMYFUNCTION("JOIN("""",VLOOKUP(D24,'для артикула'!$A$2:$B$7,2,0),VLOOKUP(G24,'для артикула'!$A$13:$B$14,2,0),VLOOKUP(E24,'для артикула'!$A$9:$B$11,2,0),VLOOKUP(F24,'для артикула'!$A$17:$B$19,2,0),VLOOKUP(J24,'для артикула'!$A$22:$B$23,2,0),VLOOKUP(H24,'для артикула'!$"&"A$26:$B$30,2,0))"),"002-2013E30Q13-OK60") -> 002-2013E30Q13-OK60 | N24: =IF(ISNUMBER(MATCH(C24, 'Реестр договоров'!$D$2:$D$900, 0)), "Продано", "В наличии") -> Продано
A25: 45579.735 | C25: MX4000002R0001813 | D25: Прицеп 2,0*1,25 м (до 750 кг.) | E25: 30 | F25: R13 | G25: R13 | H25: нет | I25: 45579 | J25: есть | K25: Астана | L25: 1 ось | M25: =IFERROR(__xludf.DUMMYFUNCTION("JOIN("""",VLOOKUP(D25,'для артикула'!$A$2:$B$7,2,0),VLOOKUP(G25,'для артикула'!$A$13:$B$14,2,0),VLOOKUP(E25,'для артикула'!$A$9:$B$11,2,0),VLOOKUP(F25,'для артикула'!$A$17:$B$19,2,0),VLOOKUP(J25,'для артикула'!$A$22:$B$23,2,0),VLOOKUP(H25,'для артикула'!$"&"A$26:$B$30,2,0))"),"002-2013E30Q13-OK") -> 002-2013E30Q13-OK | N25: =IF(ISNUMBER(MATCH(C25, 'Реестр договоров'!$D$2:$D$900, 0)), "Продано", "В наличии") -> Продано
A26: 45579.734 | C26: MX4000002R0001812 | D26: Прицеп 2,0*1,25 м (до 750 кг.) | E26: 50 | F26: R13 | G26: R13 | H26: нет | I26: 45579 | J26: есть | K26: Астана | L26: 1 ось | M26: =IFERROR(__xludf.DUMMYFUNCTION("JOIN("""",VLOOKUP(D26,'для артикула'!$A$2:$B$7,2,0),VLOOKUP(G26,'для артикула'!$A$13:$B$14,2,0),VLOOKUP(E26,'для артикула'!$A$9:$B$11,2,0),VLOOKUP(F26,'для артикула'!$A$17:$B$19,2,0),VLOOKUP(J26,'для артикула'!$A$22:$B$23,2,0),VLOOKUP(H26,'для артикула'!$"&"A$26:$B$30,2,0))"),"002-2013E50Q13-OK") -> 002-2013E50Q13-OK | N26: =IF(ISNUMBER(MATCH(C26, 'Реестр договоров'!$D$2:$D$900, 0)), "Продано", "В наличии") -> Продано
A27: 45575.703 | C27: MX4000002R0001811 | D27: Прицеп 2,0*1,25 м (до 750 кг.) | E27: 50 | F27: R13 | G27: R13 | H27: нет | I27: 45575 | J27: есть | K27: Кокшетау | L27: 1 ось | M27: =IFERROR(__xludf.DUMMYFUNCTION("JOIN("""",VLOOKUP(D27,'для артикула'!$A$2:$B$7,2,0),VLOOKUP(G27,'для артикула'!$A$13:$B$14,2,0),VLOOKUP(E27,'для артикула'!$A$9:$B$11,2,0),VLOOKUP(F27,'для артикула'!$A$17:$B$19,2,0),VLOOKUP(J27,'для артикула'!$A$22:$B$23,2,0),VLOOKUP(H27,'для артикула'!$"&"A$26:$B$30,2,0))"),"002-2013E50Q13-OK") -> 002-2013E50Q13-OK | N27: =IF(ISNUMBER(MATCH(C27, 'Реестр договоров'!$D$2:$D$900, 0)), "Продано", "В наличии") -> Продано
A28: 45579.751 | C28: MX4000002R0001804 | D28: Прицеп 2,0*1,25 м (до 750 кг.) | E28: 50 | F28: R13 | G28: R13 | H28: нет | I28: 45579 | J28: есть | K28: Астана | L28: 1 ось | M28: =IFERROR(__xludf.DUMMYFUNCTION("JOIN("""",VLOOKUP(D28,'для артикула'!$A$2:$B$7,2,0),VLOOKUP(G28,'для артикула'!$A$13:$B$14,2,0),VLOOKUP(E28,'для артикула'!$A$9:$B$11,2,0),VLOOKUP(F28,'для артикула'!$A$17:$B$19,2,0),VLOOKUP(J28,'для артикула'!$A$22:$B$23,2,0),VLOOKUP(H28,'для артикула'!$"&"A$26:$B$30,2,0))"),"002-2013E50Q13-OK") -> 002-2013E50Q13-OK | N28: =IF(ISNUMBER(MATCH(C28, 'Реестр договоров'!$D$2:$D$900, 0)), "Продано", "В наличии") -> Продано
A29: 45579.752 | C29: MX4000002R0001803 | D29: Прицеп 2,0*1,25 м (до 750 кг.) | E29: 30 | F29: R13 | G29: R13 | H29: 60 | I29: 45579 | J29: есть | K29: Астана | L29: 1 ось | M29: =IFERROR(__xludf.DUMMYFUNCTION("JOIN("""",VLOOKUP(D29,'для артикула'!$A$2:$B$7,2,0),VLOOKUP(G29,'для артикула'!$A$13:$B$14,2,0),VLOOKUP(E29,'для артикула'!$A$9:$B$11,2,0),VLOOKUP(F29,'для артикула'!$A$17:$B$19,2,0),VLOOKUP(J29,'для артикула'!$A$22:$B$23,2,0),VLOOKUP(H29,'для артикула'!$"&"A$26:$B$30,2,0))"),"002-2013E30Q13-OK60") -> 002-2013E30Q13-OK60 | N29: =IF(ISNUMBER(MATCH(C29, 'Реестр договоров'!$D$2:$D$900, 0)), "Продано", "В наличии") -> Продано
A30: 45568.481 | C30: MX4000002R0001802 | D30: Прицеп 2,0*1,25 м (до 750 кг.) | E30: 50 | F30: R13 | G30: R13 | H30: 30 | I30: 45568 | J30: есть | K30: Кокшетау | L30: 1 ось | M30: =IFERROR(__xludf.DUMMYFUNCTION("JOIN("""",VLOOKUP(D30,'для артикула'!$A$2:$B$7,2,0),VLOOKUP(G30,'для артикула'!$A$13:$B$14,2,0),VLOOKUP(E30,'для артикула'!$A$9:$B$11,2,0),VLOOKUP(F30,'для артикула'!$A$17:$B$19,2,0),VLOOKUP(J30,'для артикула'!$A$22:$B$23,2,0),VLOOKUP(H30,'для артикула'!$"&"A$26:$B$30,2,0))"),"002-2013E50Q13-OK30") -> 002-2013E50Q13-OK30 | N30: =IF(ISNUMBER(MATCH(C30, 'Реестр договоров'!$D$2:$D$900, 0)), "Продано", "В наличии") -> Продано
A31: 45579.746 | C31: MX4000002R0001801 | D31: Прицеп 2,0*1,25 м (до 750 кг.) | E31: 50 | F31: R13 | G31: R13 | H31: 30 | I31: 45579 | J31: есть | K31: Астана | L31: 1 ось | M31: =IFERROR(__xludf.DUMMYFUNCTION("JOIN("""",VLOOKUP(D31,'для артикула'!$A$2:$B$7,2,0),VLOOKUP(G31,'для артикула'!$A$13:$B$14,2,0),VLOOKUP(E31,'для артикула'!$A$9:$B$11,2,0),VLOOKUP(F31,'для артикула'!$A$17:$B$19,2,0),VLOOKUP(J31,'для артикула'!$A$22:$B$23,2,0),VLOOKUP(H31,'для артикула'!$"&"A$26:$B$30,2,0))"),"002-2013E50Q13-OK30") -> 002-2013E50Q13-OK30 | N31: =IF(ISNUMBER(MATCH(C31, 'Реестр договоров'!$D$2:$D$900, 0)), "Продано", "В наличии") -> Продано
A32: 45579.747 | C32: MX4000002R0001800 | D32: Прицеп 2,0*1,25 м (до 750 кг.) | E32: 50 | F32: R15 | G32: R15 | H32: 30 | I32: 45579 | J32: есть | K32: Астана | L32: 1 ось | M32: =IFERROR(__xludf.DUMMYFUNCTION("JOIN("""",VLOOKUP(D32,'для артикула'!$A$2:$B$7,2,0),VLOOKUP(G32,'для артикула'!$A$13:$B$14,2,0),VLOOKUP(E32,'для артикула'!$A$9:$B$11,2,0),VLOOKUP(F32,'для артикула'!$A$17:$B$19,2,0),VLOOKUP(J32,'для артикула'!$A$22:$B$23,2,0),VLOOKUP(H32,'для артикула'!$"&"A$26:$B$30,2,0))"),"002-2013E50Q15-OK30") -> 002-2013E50Q15-OK30 | N32: =IF(ISNUMBER(MATCH(C32, 'Реестр договоров'!$D$2:$D$900, 0)), "Продано", "В наличии") -> Продано
A33: 45612.467 | C33: MX4000002R0001790 | D33: Прицеп 2,0*1,25 м (до 750 кг.) | E33: 50 | F33: R13 | G33: R13 | H33: нет | I33: 45612 | J33: есть | K33: Алматы | L33: 1 ось | M33: =IFERROR(__xludf.DUMMYFUNCTION("JOIN("""",VLOOKUP(D33,'для артикула'!$A$2:$B$7,2,0),VLOOKUP(G33,'для артикула'!$A$13:$B$14,2,0),VLOOKUP(E33,'для артикула'!$A$9:$B$11,2,0),VLOOKUP(F33,'для артикула'!$A$17:$B$19,2,0),VLOOKUP(J33,'для артикула'!$A$22:$B$23,2,0),VLOOKUP(H33,'для артикула'!$"&"A$26:$B$30,2,0))"),"002-2013E50Q13-OK") -> 002-2013E50Q13-OK | N33: =IF(ISNUMBER(MATCH(C33, 'Реестр договоров'!$D$2:$D$900, 0)), "Продано", "В наличии") -> Продано
A34: 45609.45 | C34: MX4000002R0001789 | D34: Прицеп 2,0*1,25 м (до 750 кг.) | E34: 50 | F34: R13 | G34: R13 | H34: нет | I34: 45609 | J34: есть | K34: Алматы | L34: 1 ось | M34: =IFERROR(__xludf.DUMMYFUNCTION("JOIN("""",VLOOKUP(D34,'для артикула'!$A$2:$B$7,2,0),VLOOKUP(G34,'для артикула'!$A$13:$B$14,2,0),VLOOKUP(E34,'для артикула'!$A$9:$B$11,2,0),VLOOKUP(F34,'для артикула'!$A$17:$B$19,2,0),VLOOKUP(J34,'для артикула'!$A$22:$B$23,2,0),VLOOKUP(H34,'для артикула'!$"&"A$26:$B$30,2,0))"),"002-2013E50Q13-OK") -> 002-2013E50Q13-OK | N34: =IF(ISNUMBER(MATCH(C34, 'Реестр договоров'!$D$2:$D$900, 0)), "Продано", "В наличии") -> Продано
A35: 45606.532 | C35: MX4000002R0001788 | D35: Прицеп 2,0*1,25 м (до 750 кг.) | E35: 30 | F35: R13 | G35: R13 | H35: нет | I35: 45606 | J35: есть | K35: Алматы | L35: 1 ось | M35: =IFERROR(__xludf.DUMMYFUNCTION("JOIN("""",VLOOKUP(D35,'для артикула'!$A$2:$B$7,2,0),VLOOKUP(G35,'для артикула'!$A$13:$B$14,2,0),VLOOKUP(E35,'для артикула'!$A$9:$B$11,2,0),VLOOKUP(F35,'для артикула'!$A$17:$B$19,2,0),VLOOKUP(J35,'для артикула'!$A$22:$B$23,2,0),VLOOKUP(H35,'для артикула'!$"&"A$26:$B$30,2,0))"),"002-2013E30Q13-OK") -> 002-2013E30Q13-OK | N35: =IF(ISNUMBER(MATCH(C35, 'Реестр договоров'!$D$2:$D$900, 0)), "Продано", "В наличии") -> Продано
A36: 45576.64 | C36: MX4000002R0001787 | D36: Прицеп 2,0*1,25 м (до 750 кг.) | E36: 50 | F36: R13 | G36: R13 | H36: нет | I36: 45576 | J36: есть | K36: Алматы | L36: 1 ось | M36: =IFERROR(__xludf.DUMMYFUNCTION("JOIN("""",VLOOKUP(D36,'для артикула'!$A$2:$B$7,2,0),VLOOKUP(G36,'для артикула'!$A$13:$B$14,2,0),VLOOKUP(E36,'для артикула'!$A$9:$B$11,2,0),VLOOKUP(F36,'для артикула'!$A$17:$B$19,2,0),VLOOKUP(J36,'для артикула'!$A$22:$B$23,2,0),VLOOKUP(H36,'для артикула'!$"&"A$26:$B$30,2,0))"),"002-2013E50Q13-OK") -> 002-2013E50Q13-OK | N36: =IF(ISNUMBER(MATCH(C36, 'Реестр договоров'!$D$2:$D$900, 0)), "Продано", "В наличии") -> Продано
A37: 45600.584 | C37: MX4000002R0001786 | D37: Прицеп 2,0*1,25 м (до 750 кг.) | E37: 50 | F37: R13 | G37: R13 | H37: нет | I37: 45600 | J37: есть | K37: Алматы | L37: 1 ось | M37: =IFERROR(__xludf.DUMMYFUNCTION("JOIN("""",VLOOKUP(D37,'для артикула'!$A$2:$B$7,2,0),VLOOKUP(G37,'для артикула'!$A$13:$B$14,2,0),VLOOKUP(E37,'для артикула'!$A$9:$B$11,2,0),VLOOKUP(F37,'для артикула'!$A$17:$B$19,2,0),VLOOKUP(J37,'для артикула'!$A$22:$B$23,2,0),VLOOKUP(H37,'для артикула'!$"&"A$26:$B$30,2,0))"),"002-2013E50Q13-OK") -> 002-2013E50Q13-OK | N37: =IF(ISNUMBER(MATCH(C37, 'Реестр договоров'!$D$2:$D$900, 0)), "Продано", "В наличии") -> Продано
A38: 45601.76 | C38: MX4000002R0001785 | D38: Прицеп 2,0*1,25 м (до 750 кг.) | E38: 50 | F38: R13 | G38: R13 | H38: нет | I38: 45600 | J38: есть | K38: Алматы | L38: 1 ось | M38: =IFERROR(__xludf.DUMMYFUNCTION("JOIN("""",VLOOKUP(D38,'для артикула'!$A$2:$B$7,2,0),VLOOKUP(G38,'для артикула'!$A$13:$B$14,2,0),VLOOKUP(E38,'для артикула'!$A$9:$B$11,2,0),VLOOKUP(F38,'для артикула'!$A$17:$B$19,2,0),VLOOKUP(J38,'для артикула'!$A$22:$B$23,2,0),VLOOKUP(H38,'для артикула'!$"&"A$26:$B$30,2,0))"),"002-2013E50Q13-OK") -> 002-2013E50Q13-OK | N38: =IF(ISNUMBER(MATCH(C38, 'Реестр договоров'!$D$2:$D$900, 0)), "Продано", "В наличии") -> Продано
A39: 45606.499 | C39: MX4000002R0001784 | D39: Прицеп 2,0*1,25 м (до 750 кг.) | E39: 30 | F39: R13 | G39: R13 | H39: нет | I39: 45606 | J39: есть | K39: Алматы | L39: 1 ось | M39: =IFERROR(__xludf.DUMMYFUNCTION("JOIN("""",VLOOKUP(D39,'для артикула'!$A$2:$B$7,2,0),VLOOKUP(G39,'для артикула'!$A$13:$B$14,2,0),VLOOKUP(E39,'для артикула'!$A$9:$B$11,2,0),VLOOKUP(F39,'для артикула'!$A$17:$B$19,2,0),VLOOKUP(J39,'для артикула'!$A$22:$B$23,2,0),VLOOKUP(H39,'для артикула'!$"&"A$26:$B$30,2,0))"),"002-2013E30Q13-OK") -> 002-2013E30Q13-OK | N39: =IF(ISNUMBER(MATCH(C39, 'Реестр договоров'!$D$2:$D$900, 0)), "Продано", "В наличии") -> Продано
A40: 45583.709 | C40: MX4000002R0001783 | D40: Прицеп 2,0*1,25 м (до 750 кг.) | E40: 50 | F40: R13 | G40: R13 | H40: нет | I40: 45583 | J40: есть | K40: Алматы | L40: 1 ось | M40: =IFERROR(__xludf.DUMMYFUNCTION("JOIN("""",VLOOKUP(D40,'для артикула'!$A$2:$B$7,2,0),VLOOKUP(G40,'для артикула'!$A$13:$B$14,2,0),VLOOKUP(E40,'для артикула'!$A$9:$B$11,2,0),VLOOKUP(F40,'для артикула'!$A$17:$B$19,2,0),VLOOKUP(J40,'для артикула'!$A$22:$B$23,2,0),VLOOKUP(H40,'для артикула'!$"&"A$26:$B$30,2,0))"),"002-2013E50Q13-OK") -> 002-2013E50Q13-OK | N40: =IF(ISNUMBER(MATCH(C40, 'Реестр договоров'!$D$2:$D$900, 0)), "Продано", "В наличии") -> Продано
A41: 45605.556 | C41: MX4000002R0001782 | D41: Прицеп 2,0*1,25 м (до 750 кг.) | E41: 50 | F41: R13 | G41: R13 | H41: нет | I41: 45605 | J41: есть | K41: Алматы | L41: 1 ось | M41: =IFERROR(__xludf.DUMMYFUNCTION("JOIN("""",VLOOKUP(D41,'для артикула'!$A$2:$B$7,2,0),VLOOKUP(G41,'для артикула'!$A$13:$B$14,2,0),VLOOKUP(E41,'для артикула'!$A$9:$B$11,2,0),VLOOKUP(F41,'для артикула'!$A$17:$B$19,2,0),VLOOKUP(J41,'для артикула'!$A$22:$B$23,2,0),VLOOKUP(H41,'для артикула'!$"&"A$26:$B$30,2,0))"),"002-2013E50Q13-OK") -> 002-2013E50Q13-OK | N41: =IF(ISNUMBER(MATCH(C41, 'Реестр договоров'!$D$2:$D$900, 0)), "Продано", "В наличии") -> Продано
A42: 45582.527 | C42: MX4000002R0001781 | D42: Прицеп 2,0*1,25 м (до 750 кг.) | E42: 50 | F42: R13 | G42: R13 | H42: нет | I42: 45582 | J42: есть | K42: Кокшетау | L42: 1 ось | M42: =IFERROR(__xludf.DUMMYFUNCTION("JOIN("""",VLOOKUP(D42,'для артикула'!$A$2:$B$7,2,0),VLOOKUP(G42,'для артикула'!$A$13:$B$14,2,0),VLOOKUP(E42,'для артикула'!$A$9:$B$11,2,0),VLOOKUP(F42,'для артикула'!$A$17:$B$19,2,0),VLOOKUP(J42,'для артикула'!$A$22:$B$23,2,0),VLOOKUP(H42,'для артикула'!$"&"A$26:$B$30,2,0))"),"002-2013E50Q13-OK") -> 002-2013E50Q13-OK | N42: =IF(ISNUMBER(MATCH(C42, 'Реестр договоров'!$D$2:$D$900, 0)), "Продано", "В наличии") -> Продано
A43: 45560.526 | C43: MX4000002R0001779 | D43: Прицеп 2,0*1,25 м (до 750 кг.) | E43: 50 | F43: R13 | G43: R13 | H43: нет | I43: 45560 | J43: есть | K43: Кокшетау | L43: 1 ось | M43: =IFERROR(__xludf.DUMMYFUNCTION("JOIN("""",VLOOKUP(D43,'для артикула'!$A$2:$B$7,2,0),VLOOKUP(G43,'для артикула'!$A$13:$B$14,2,0),VLOOKUP(E43,'для артикула'!$A$9:$B$11,2,0),VLOOKUP(F43,'для артикула'!$A$17:$B$19,2,0),VLOOKUP(J43,'для артикула'!$A$22:$B$23,2,0),VLOOKUP(H43,'для артикула'!$"&"A$26:$B$30,2,0))"),"002-2013E50Q13-OK") -> 002-2013E50Q13-OK | N43: =IF(ISNUMBER(MATCH(C43, 'Реестр договоров'!$D$2:$D$900, 0)), "Продано", "В наличии") -> Продано
A44: 45559.753 | C44: MX4000002R0001778 | D44: Прицеп 2,0*1,25 м (до 750 кг.) | E44: 50 | F44: R13 | G44: R13 | H44: нет | I44: 45559 | J44: есть | K44: Астана | L44: 1 ось | M44: =IFERROR(__xludf.DUMMYFUNCTION("JOIN("""",VLOOKUP(D44,'для артикула'!$A$2:$B$7,2,0),VLOOKUP(G44,'для артикула'!$A$13:$B$14,2,0),VLOOKUP(E44,'для артикула'!$A$9:$B$11,2,0),VLOOKUP(F44,'для артикула'!$A$17:$B$19,2,0),VLOOKUP(J44,'для артикула'!$A$22:$B$23,2,0),VLOOKUP(H44,'для артикула'!$"&"A$26:$B$30,2,0))"),"002-2013E50Q13-OK") -> 002-2013E50Q13-OK | N44: =IF(ISNUMBER(MATCH(C44, 'Реестр договоров'!$D$2:$D$900, 0)), "Продано", "В наличии") -> Продано
A45: 45558.754 | C45: MX4000002R0001777 | D45: Прицеп 2,0*1,25 м (до 750 кг.) | E45: 50 | F45: R13 | G45: R13 | H45: 60 | I45: 45558 | J45: есть | K45: Астана | L45: 1 ось | M45: =IFERROR(__xludf.DUMMYFUNCTION("JOIN("""",VLOOKUP(D45,'для артикула'!$A$2:$B$7,2,0),VLOOKUP(G45,'для артикула'!$A$13:$B$14,2,0),VLOOKUP(E45,'для артикула'!$A$9:$B$11,2,0),VLOOKUP(F45,'для артикула'!$A$17:$B$19,2,0),VLOOKUP(J45,'для артикула'!$A$22:$B$23,2,0),VLOOKUP(H45,'для артикула'!$"&"A$26:$B$30,2,0))"),"002-2013E50Q13-OK60") -> 002-2013E50Q13-OK60 | N45: =IF(ISNUMBER(MATCH(C45, 'Реестр договоров'!$D$2:$D$900, 0)), "Продано", "В наличии") -> Продано
A46: 45558.678 | C46: MX4000002R0001776 | D46: Прицеп 2,0*1,25 м (до 750 кг.) | E46: 50 | F46: R13 | G46: R13 | H46: 60 | I46: 45558 | J46: есть | K46: Астана | L46: 1 ось | M46: =IFERROR(__xludf.DUMMYFUNCTION("JOIN("""",VLOOKUP(D46,'для артикула'!$A$2:$B$7,2,0),VLOOKUP(G46,'для артикула'!$A$13:$B$14,2,0),VLOOKUP(E46,'для артикула'!$A$9:$B$11,2,0),VLOOKUP(F46,'для артикула'!$A$17:$B$19,2,0),VLOOKUP(J46,'для артикула'!$A$22:$B$23,2,0),VLOOKUP(H46,'для артикула'!$"&"A$26:$B$30,2,0))"),"002-2013E50Q13-OK60") -> 002-2013E50Q13-OK60 | N46: =IF(ISNUMBER(MATCH(C46, 'Реестр договоров'!$D$2:$D$900, 0)), "Продано", "В наличии") -> Продано
A47: 45557.705 | C47: MX4000002R0001775 | D47: Прицеп 2,0*1,25 м (до 750 кг.) | E47: 50 | F47: R13 | G47: R13 | H47: 30 | I47: 45557 | J47: есть | K47: Астана | L47: 1 ось | M47: =IFERROR(__xludf.DUMMYFUNCTION("JOIN("""",VLOOKUP(D47,'для артикула'!$A$2:$B$7,2,0),VLOOKUP(G47,'для артикула'!$A$13:$B$14,2,0),VLOOKUP(E47,'для артикула'!$A$9:$B$11,2,0),VLOOKUP(F47,'для артикула'!$A$17:$B$19,2,0),VLOOKUP(J47,'для артикула'!$A$22:$B$23,2,0),VLOOKUP(H47,'для артикула'!$"&"A$26:$B$30,2,0))"),"002-2013E50Q13-OK30") -> 002-2013E50Q13-OK30 | N47: =IF(ISNUMBER(MATCH(C47, 'Реестр договоров'!$D$2:$D$900, 0)), "Продано", "В наличии") -> Продано
A48: 45601.503 | C48: MX4000002R0001774 | D48: Прицеп 2,0*1,25 м (до 750 кг.) | E48: 30 | F48: R13 | G48: R13 | H48: нет | I48: 45600 | J48: есть | K48: Астана | L48: 1 ось | M48: =IFERROR(__xludf.DUMMYFUNCTION("JOIN("""",VLOOKUP(D48,'для артикула'!$A$2:$B$7,2,0),VLOOKUP(G48,'для артикула'!$A$13:$B$14,2,0),VLOOKUP(E48,'для артикула'!$A$9:$B$11,2,0),VLOOKUP(F48,'для артикула'!$A$17:$B$19,2,0),VLOOKUP(J48,'для артикула'!$A$22:$B$23,2,0),VLOOKUP(H48,'для артикула'!$"&"A$26:$B$30,2,0))"),"002-2013E30Q13-OK") -> 002-2013E30Q13-OK | N48: =IF(ISNUMBER(MATCH(C48, 'Реестр договоров'!$D$2:$D$900, 0)), "Продано", "В наличии") -> Продано
A49: 45552.772 | C49: MX4000002R0001773 | D49: Прицеп 2,0*1,25 м (до 750 кг.) | E49: 30 | F49: R13 | G49: R13 | H49: нет | I49: 45552 | J49: есть | K49: Кокшетау | L49: 1 ось | M49: =IFERROR(__xludf.DUMMYFUNCTION("JOIN("""",VLOOKUP(D49,'для артикула'!$A$2:$B$7,2,0),VLOOKUP(G49,'для артикула'!$A$13:$B$14,2,0),VLOOKUP(E49,'для артикула'!$A$9:$B$11,2,0),VLOOKUP(F49,'для артикула'!$A$17:$B$19,2,0),VLOOKUP(J49,'для артикула'!$A$22:$B$23,2,0),VLOOKUP(H49,'для артикула'!$"&"A$26:$B$30,2,0))"),"002-2013E30Q13-OK") -> 002-2013E30Q13-OK | N49: =IF(ISNUMBER(MATCH(C49, 'Реестр договоров'!$D$2:$D$900, 0)), "Продано", "В наличии") -> Продано
A50: 45552.555 | C50: MX4000002R0001772 | D50: Прицеп 2,0*1,25 м (до 750 кг.) | E50: 30 | F50: R13 | G50: R13 | H50: 30 | I50: 45552 | J50: есть | K50: Кокшетау | L50: 1 ось | M50: =IFERROR(__xludf.DUMMYFUNCTION("JOIN("""",VLOOKUP(D50,'для артикула'!$A$2:$B$7,2,0),VLOOKUP(G50,'для артикула'!$A$13:$B$14,2,0),VLOOKUP(E50,'для артикула'!$A$9:$B$11,2,0),VLOOKUP(F50,'для артикула'!$A$17:$B$19,2,0),VLOOKUP(J50,'для артикула'!$A$22:$B$23,2,0),VLOOKUP(H50,'для артикула'!$"&"A$26:$B$30,2,0))"),"002-2013E30Q13-OK30") -> 002-2013E30Q13-OK30 | N50: =IF(ISNUMBER(MATCH(C50, 'Реестр договоров'!$D$2:$D$900, 0)), "Продано", "В наличии") -> Продано
A51: 45552.472 | C51: MX4000002R0001770 | D51: Прицеп 2,0*1,25 м (до 750 кг.) | E51: 50 | F51: R13 | G51: R13 | H51: нет | I51: 45552 | J51: есть | K51: Астана | L51: 1 ось | M51: =IFERROR(__xludf.DUMMYFUNCTION("JOIN("""",VLOOKUP(D51,'для артикула'!$A$2:$B$7,2,0),VLOOKUP(G51,'для артикула'!$A$13:$B$14,2,0),VLOOKUP(E51,'для артикула'!$A$9:$B$11,2,0),VLOOKUP(F51,'для артикула'!$A$17:$B$19,2,0),VLOOKUP(J51,'для артикула'!$A$22:$B$23,2,0),VLOOKUP(H51,'для артикула'!$"&"A$26:$B$30,2,0))"),"002-2013E50Q13-OK") -> 002-2013E50Q13-OK | N51: =IF(ISNUMBER(MATCH(C51, 'Реестр договоров'!$D$2:$D$900, 0)), "Продано", "В наличии") -> Продано
A52: 45544.466 | C52: MX4000002R0001768 | D52: Прицеп 2,0*1,25 м (до 750 кг.) | E52: 30 | F52: R13 | G52: R13 | H52: нет | I52: 45544 | J52: есть | K52: Астана | L52: 1 ось | M52: =IFERROR(__xludf.DUMMYFUNCTION("JOIN("""",VLOOKUP(D52,'для артикула'!$A$2:$B$7,2,0),VLOOKUP(G52,'для артикула'!$A$13:$B$14,2,0),VLOOKUP(E52,'для артикула'!$A$9:$B$11,2,0),VLOOKUP(F52,'для артикула'!$A$17:$B$19,2,0),VLOOKUP(J52,'для артикула'!$A$22:$B$23,2,0),VLOOKUP(H52,'для артикула'!$"&"A$26:$B$30,2,0))"),"002-2013E30Q13-OK") -> 002-2013E30Q13-OK | N52: =IF(ISNUMBER(MATCH(C52, 'Реестр договоров'!$D$2:$D$900, 0)), "Продано", "В наличии") -> Продано
A53: 45544.467 | C53: MX4000002R0001767 | D53: Прицеп 2,0*1,25 м (до 750 кг.) | E53: 50 | F53: R13 | G53: R13 | H53: 30 | I53: 45544 | J53: есть | K53: Астана | L53: 1 ось | M53: =IFERROR(__xludf.DUMMYFUNCTION("JOIN("""",VLOOKUP(D53,'для артикула'!$A$2:$B$7,2,0),VLOOKUP(G53,'для артикула'!$A$13:$B$14,2,0),VLOOKUP(E53,'для артикула'!$A$9:$B$11,2,0),VLOOKUP(F53,'для артикула'!$A$17:$B$19,2,0),VLOOKUP(J53,'для артикула'!$A$22:$B$23,2,0),VLOOKUP(H53,'для артикула'!$"&"A$26:$B$30,2,0))"),"002-2013E50Q13-OK30") -> 002-2013E50Q13-OK30 | N53: =IF(ISNUMBER(MATCH(C53, 'Реестр договоров'!$D$2:$D$900, 0)), "Продано", "В наличии") -> Продано
A54: 45540.446 | C54: MX4000002R0001765 | D54: Прицеп 2,0*1,25 м (до 750 кг.) | E54: 50 | F54: R13 | G54: R13 | H54: нет | I54: 45540 | J54: есть | K54: Кокшетау | L54: 1 ось | M54: =IFERROR(__xludf.DUMMYFUNCTION("JOIN("""",VLOOKUP(D54,'для артикула'!$A$2:$B$7,2,0),VLOOKUP(G54,'для артикула'!$A$13:$B$14,2,0),VLOOKUP(E54,'для артикула'!$A$9:$B$11,2,0),VLOOKUP(F54,'для артикула'!$A$17:$B$19,2,0),VLOOKUP(J54,'для артикула'!$A$22:$B$23,2,0),VLOOKUP(H54,'для артикула'!$"&"A$26:$B$30,2,0))"),"002-2013E50Q13-OK") -> 002-2013E50Q13-OK | N54: =IF(ISNUMBER(MATCH(C54, 'Реестр договоров'!$D$2:$D$900, 0)), "Продано", "В наличии") -> Продано
A55: 45541.494 | C55: MX4000002R0001764 | D55: Прицеп 2,0*1,25 м (до 750 кг.) | E55: 50 | F55: R13 | G55: R13 | H55: нет | I55: 45541 | J55: есть | K55: Астана | L55: 1 ось | M55: =IFERROR(__xludf.DUMMYFUNCTION("JOIN("""",VLOOKUP(D55,'для артикула'!$A$2:$B$7,2,0),VLOOKUP(G55,'для артикула'!$A$13:$B$14,2,0),VLOOKUP(E55,'для артикула'!$A$9:$B$11,2,0),VLOOKUP(F55,'для артикула'!$A$17:$B$19,2,0),VLOOKUP(J55,'для артикула'!$A$22:$B$23,2,0),VLOOKUP(H55,'для артикула'!$"&"A$26:$B$30,2,0))"),"002-2013E50Q13-OK") -> 002-2013E50Q13-OK | N55: =IF(ISNUMBER(MATCH(C55, 'Реестр договоров'!$D$2:$D$900, 0)), "Продано", "В наличии") -> Продано
A56: 45544.462 | C56: MX4000002R0001763 | D56: Прицеп 2,0*1,25 м (до 750 кг.) | E56: 50 | F56: R13 | G56: R13 | H56: нет | I56: 45544 | J56: есть | K56: Астана | L56: 1 ось | M56: =IFERROR(__xludf.DUMMYFUNCTION("JOIN("""",VLOOKUP(D56,'для артикула'!$A$2:$B$7,2,0),VLOOKUP(G56,'для артикула'!$A$13:$B$14,2,0),VLOOKUP(E56,'для артикула'!$A$9:$B$11,2,0),VLOOKUP(F56,'для артикула'!$A$17:$B$19,2,0),VLOOKUP(J56,'для артикула'!$A$22:$B$23,2,0),VLOOKUP(H56,'для артикула'!$"&"A$26:$B$30,2,0))"),"002-2013E50Q13-OK") -> 002-2013E50Q13-OK | N56: =IF(ISNUMBER(MATCH(C56, 'Реестр договоров'!$D$2:$D$900, 0)), "Продано", "В наличии") -> Продано
A57: 45537.452 | C57: MX4000002R0001762 | D57: Прицеп 2,0*1,25 м (до 750 кг.) | E57: 50 | F57: R13 | G57: R13 | H57: нет | I57: 45537 | J57: есть | K57: Кокшетау | L57: 1 ось | M57: =IFERROR(__xludf.DUMMYFUNCTION("JOIN("""",VLOOKUP(D57,'для артикула'!$A$2:$B$7,2,0),VLOOKUP(G57,'для артикула'!$A$13:$B$14,2,0),VLOOKUP(E57,'для артикула'!$A$9:$B$11,2,0),VLOOKUP(F57,'для артикула'!$A$17:$B$19,2,0),VLOOKUP(J57,'для артикула'!$A$22:$B$23,2,0),VLOOKUP(H57,'для артикула'!$"&"A$26:$B$30,2,0))"),"002-2013E50Q13-OK") -> 002-2013E50Q13-OK | N57: =IF(ISNUMBER(MATCH(C57, 'Реестр договоров'!$D$2:$D$900, 0)), "Продано", "В наличии") -> Продано
A58: 45533.491 | C58: MX4000002R0001761 | D58: Прицеп 2,0*1,25 м (до 750 кг.) | E58: 50 | F58: R13 | G58: R13 | H58: 30 | I58: 45533 | J58: есть | K58: Астана | L58: 1 ось | M58: =IFERROR(__xludf.DUMMYFUNCTION("JOIN("""",VLOOKUP(D58,'для артикула'!$A$2:$B$7,2,0),VLOOKUP(G58,'для артикула'!$A$13:$B$14,2,0),VLOOKUP(E58,'для артикула'!$A$9:$B$11,2,0),VLOOKUP(F58,'для артикула'!$A$17:$B$19,2,0),VLOOKUP(J58,'для артикула'!$A$22:$B$23,2,0),VLOOKUP(H58,'для артикула'!$"&"A$26:$B$30,2,0))"),"002-2013E50Q13-OK30") -> 002-2013E50Q13-OK30 | N58: =IF(ISNUMBER(MATCH(C58, 'Реестр договоров'!$D$2:$D$900, 0)), "Продано", "В наличии") -> Продано
A59: 45533.491 | C59: MX4000002R0001760 | D59: Прицеп 2,0*1,25 м (до 750 кг.) | E59: 50 | F59: R13 | G59: R13 | H59: 30 | I59: 45533 | J59: есть | K59: Астана | L59: 1 ось | M59: =IFERROR(__xludf.DUMMYFUNCTION("JOIN("""",VLOOKUP(D59,'для артикула'!$A$2:$B$7,2,0),VLOOKUP(G59,'для артикула'!$A$13:$B$14,2,0),VLOOKUP(E59,'для артикула'!$A$9:$B$11,2,0),VLOOKUP(F59,'для артикула'!$A$17:$B$19,2,0),VLOOKUP(J59,'для артикула'!$A$22:$B$23,2,0),VLOOKUP(H59,'для артикула'!$"&"A$26:$B$30,2,0))"),"002-2013E50Q13-OK30") -> 002-2013E50Q13-OK30 | N59: =IF(ISNUMBER(MATCH(C59, 'Реестр договоров'!$D$2:$D$900, 0)), "Продано", "В наличии") -> Продано
A60: 45530.739 | C60: MX4000002R0001759 | D60: Прицеп 2,0*1,25 м (до 750 кг.) | E60: 50 | F60: R13 | G60: R13 | H60: 30 | I60: 45530 | J60: есть | K60: Астана | L60: 1 ось | M60: =IFERROR(__xludf.DUMMYFUNCTION("JOIN("""",VLOOKUP(D60,'для артикула'!$A$2:$B$7,2,0),VLOOKUP(G60,'для артикула'!$A$13:$B$14,2,0),VLOOKUP(E60,'для артикула'!$A$9:$B$11,2,0),VLOOKUP(F60,'для артикула'!$A$17:$B$19,2,0),VLOOKUP(J60,'для артикула'!$A$22:$B$23,2,0),VLOOKUP(H60,'для артикула'!$"&"A$26:$B$30,2,0))"),"002-2013E50Q13-OK30") -> 002-2013E50Q13-OK30 | N60: =IF(ISNUMBER(MATCH(C60, 'Реестр договоров'!$D$2:$D$900, 0)), "Продано", "В наличии") -> Продано
A61: 45531.458 | C61: MX4000002R0001758 | D61: Прицеп 2,0*1,25 м (до 750 кг.) | E61: 30 | F61: R13 | G61: R13 | H61: нет | I61: 45531 | J61: есть | K61: Астана | L61: 1 ось | M61: =IFERROR(__xludf.DUMMYFUNCTION("JOIN("""",VLOOKUP(D61,'для артикула'!$A$2:$B$7,2,0),VLOOKUP(G61,'для артикула'!$A$13:$B$14,2,0),VLOOKUP(E61,'для артикула'!$A$9:$B$11,2,0),VLOOKUP(F61,'для артикула'!$A$17:$B$19,2,0),VLOOKUP(J61,'для артикула'!$A$22:$B$23,2,0),VLOOKUP(H61,'для артикула'!$"&"A$26:$B$30,2,0))"),"002-2013E30Q13-OK") -> 002-2013E30Q13-OK | N61: =IF(ISNUMBER(MATCH(C61, 'Реестр договоров'!$D$2:$D$900, 0)), "Продано", "В наличии") -> Продано
A62: 45524.685 | C62: MX4000002R0001757 | D62: Прицеп 2,0*1,25 м (до 750 кг.) | E62: 50 | F62: R13 | G62: R13 | H62: нет | I62: 45524 | J62: есть | K62: Кокшетау | L62: 1 ось | M62: =IFERROR(__xludf.DUMMYFUNCTION("JOIN("""",VLOOKUP(D62,'для артикула'!$A$2:$B$7,2,0),VLOOKUP(G62,'для артикула'!$A$13:$B$14,2,0),VLOOKUP(E62,'для артикула'!$A$9:$B$11,2,0),VLOOKUP(F62,'для артикула'!$A$17:$B$19,2,0),VLOOKUP(J62,'для артикула'!$A$22:$B$23,2,0),VLOOKUP(H62,'для артикула'!$"&"A$26:$B$30,2,0))"),"002-2013E50Q13-OK") -> 002-2013E50Q13-OK | N62: =IF(ISNUMBER(MATCH(C62, 'Реестр договоров'!$D$2:$D$900, 0)), "Продано", "В наличии") -> Продано
A63: 45525.507 | C63: MX4000002R0001751 | D63: Прицеп 2,0*1,25 м (до 750 кг.) | E63: 30 | F63: R13 | G63: R13 | H63: нет | I63: 45525 | J63: есть | K63: Астана | L63: 1 ось | M63: =IFERROR(__xludf.DUMMYFUNCTION("JOIN("""",VLOOKUP(D63,'для артикула'!$A$2:$B$7,2,0),VLOOKUP(G63,'для артикула'!$A$13:$B$14,2,0),VLOOKUP(E63,'для артикула'!$A$9:$B$11,2,0),VLOOKUP(F63,'для артикула'!$A$17:$B$19,2,0),VLOOKUP(J63,'для артикула'!$A$22:$B$23,2,0),VLOOKUP(H63,'для артикула'!$"&"A$26:$B$30,2,0))"),"002-2013E30Q13-OK") -> 002-2013E30Q13-OK | N63: =IF(ISNUMBER(MATCH(C63, 'Реестр договоров'!$D$2:$D$900, 0)), "Продано", "В наличии") -> Продано
A64: 45523.532 | C64: MX4000002R0001750 | D64: Прицеп 2,0*1,25 м (до 750 кг.) | E64: 30 | F64: R13 | G64: R13 | H64: нет | I64: 45523 | J64: есть | K64: Астана | L64: 1 ось | M64: =IFERROR(__xludf.DUMMYFUNCTION("JOIN("""",VLOOKUP(D64,'для артикула'!$A$2:$B$7,2,0),VLOOKUP(G64,'для артикула'!$A$13:$B$14,2,0),VLOOKUP(E64,'для артикула'!$A$9:$B$11,2,0),VLOOKUP(F64,'для артикула'!$A$17:$B$19,2,0),VLOOKUP(J64,'для артикула'!$A$22:$B$23,2,0),VLOOKUP(H64,'для артикула'!$"&"A$26:$B$30,2,0))"),"002-2013E30Q13-OK") -> 002-2013E30Q13-OK | N64: =IF(ISNUMBER(MATCH(C64, 'Реестр договоров'!$D$2:$D$900, 0)), "Продано", "В наличии") -> Продано
A65: 45520.499 | C65: MX4000002R0001749 | D65: Прицеп 2,0*1,25 м (до 750 кг.) | E65: 30 | F65: R13 | G65: R13 | H65: нет | I65: 45520 | J65: есть | K65: Астана | L65: 1 ось | M65: =IFERROR(__xludf.DUMMYFUNCTION("JOIN("""",VLOOKUP(D65,'для артикула'!$A$2:$B$7,2,0),VLOOKUP(G65,'для артикула'!$A$13:$B$14,2,0),VLOOKUP(E65,'для артикула'!$A$9:$B$11,2,0),VLOOKUP(F65,'для артикула'!$A$17:$B$19,2,0),VLOOKUP(J65,'для артикула'!$A$22:$B$23,2,0),VLOOKUP(H65,'для артикула'!$"&"A$26:$B$30,2,0))"),"002-2013E30Q13-OK") -> 002-2013E30Q13-OK | N65: =IF(ISNUMBER(MATCH(C65, 'Реестр договоров'!$D$2:$D$900, 0)), "Продано", "В наличии") -> Продано
A66: 45541.606 | C66: MX4000002R0001747 | D66: Прицеп 2,0*1,25 м (до 750 кг.) | E66: 50 | F66: R13 | G66: R13 | H66: нет | I66: 45541 | J66: есть | K66: Алматы | L66: 1 ось | M66: =IFERROR(__xludf.DUMMYFUNCTION("JOIN("""",VLOOKUP(D66,'для артикула'!$A$2:$B$7,2,0),VLOOKUP(G66,'для артикула'!$A$13:$B$14,2,0),VLOOKUP(E66,'для артикула'!$A$9:$B$11,2,0),VLOOKUP(F66,'для артикула'!$A$17:$B$19,2,0),VLOOKUP(J66,'для артикула'!$A$22:$B$23,2,0),VLOOKUP(H66,'для артикула'!$"&"A$26:$B$30,2,0))"),"002-2013E50Q13-OK") -> 002-2013E50Q13-OK | N66: =IF(ISNUMBER(MATCH(C66, 'Реестр договоров'!$D$2:$D$900, 0)), "Продано", "В наличии") -> Продано
A67: 45546.497 | C67: MX4000002R0001746 | D67: Прицеп 2,0*1,25 м (до 750 кг.) | E67: 50 | F67: R13 | G67: R13 | H67: нет | I67: 45546 | J67: есть | K67: Алматы | L67: 1 ось | M67: =IFERROR(__xludf.DUMMYFUNCTION("JOIN("""",VLOOKUP(D67,'для артикула'!$A$2:$B$7,2,0),VLOOKUP(G67,'для артикула'!$A$13:$B$14,2,0),VLOOKUP(E67,'для артикула'!$A$9:$B$11,2,0),VLOOKUP(F67,'для артикула'!$A$17:$B$19,2,0),VLOOKUP(J67,'для артикула'!$A$22:$B$23,2,0),VLOOKUP(H67,'для артикула'!$"&"A$26:$B$30,2,0))"),"002-2013E50Q13-OK") -> 002-2013E50Q13-OK | N67: =IF(ISNUMBER(MATCH(C67, 'Реестр договоров'!$D$2:$D$900, 0)), "Продано", "В наличии") -> Продано
A68: 45520.494 | C68: MX4000002R0001745 | D68: Прицеп 2,0*1,25 м (до 750 кг.) | E68: 30 | F68: R13 | G68: R13 | H68: нет | I68: 45516 | J68: есть | K68: Кокшетау | L68: 1 ось | M68: =IFERROR(__xludf.DUMMYFUNCTION("JOIN("""",VLOOKUP(D68,'для артикула'!$A$2:$B$7,2,0),VLOOKUP(G68,'для артикула'!$A$13:$B$14,2,0),VLOOKUP(E68,'для артикула'!$A$9:$B$11,2,0),VLOOKUP(F68,'для артикула'!$A$17:$B$19,2,0),VLOOKUP(J68,'для артикула'!$A$22:$B$23,2,0),VLOOKUP(H68,'для артикула'!$"&"A$26:$B$30,2,0))"),"002-2013E30Q13-OK") -> 002-2013E30Q13-OK | N68: =IF(ISNUMBER(MATCH(C68, 'Реестр договоров'!$D$2:$D$900, 0)), "Продано", "В наличии") -> Продано
A69: 45523.555 | C69: MX4000002R0001744 | D69: Прицеп 2,0*1,25 м (до 750 кг.) | E69: 50 | F69: R13 | G69: R13 | H69: 30 | I69: 45523 | J69: есть | K69: Кокшетау | L69: 1 ось | M69: =IFERROR(__xludf.DUMMYFUNCTION("JOIN("""",VLOOKUP(D69,'для артикула'!$A$2:$B$7,2,0),VLOOKUP(G69,'для артикула'!$A$13:$B$14,2,0),VLOOKUP(E69,'для артикула'!$A$9:$B$11,2,0),VLOOKUP(F69,'для артикула'!$A$17:$B$19,2,0),VLOOKUP(J69,'для артикула'!$A$22:$B$23,2,0),VLOOKUP(H69,'для артикула'!$"&"A$26:$B$30,2,0))"),"002-2013E50Q13-OK30") -> 002-2013E50Q13-OK30 | N69: =IF(ISNUMBER(MATCH(C69, 'Реестр договоров'!$D$2:$D$900, 0)), "Продано", "В наличии") -> Продано
A70: 45502.525 | C70: MX4000002R0001743 | D70: Прицеп 2,0*1,25 м (до 750 кг.) | E70: 30 | F70: R13 | G70: R13 | H70: нет | I70: 45499 | J70: нет | K70: Алматы | L70: 1 ось | M70: =IFERROR(__xludf.DUMMYFUNCTION("JOIN("""",VLOOKUP(D70,'для артикула'!$A$2:$B$7,2,0),VLOOKUP(G70,'для артикула'!$A$13:$B$14,2,0),VLOOKUP(E70,'для артикула'!$A$9:$B$11,2,0),VLOOKUP(F70,'для артикула'!$A$17:$B$19,2,0),VLOOKUP(J70,'для артикула'!$A$22:$B$23,2,0),VLOOKUP(H70,'для артикула'!$"&"A$26:$B$30,2,0))"),"002-2013E30Q13") -> 002-2013E30Q13 | N70: =IF(ISNUMBER(MATCH(C70, 'Реестр договоров'!$D$2:$D$900, 0)), "Продано", "В наличии") -> Продано
A71: 45502.525 | C71: MX4000002R0001742 | D71: Прицеп 2,0*1,25 м (до 750 кг.) | E71: 50 | F71: R13 | G71: R13 | H71: нет | I71: 45499 | J71: есть | K71: Алматы | L71: 1 ось | M71: =IFERROR(__xludf.DUMMYFUNCTION("JOIN("""",VLOOKUP(D71,'для артикула'!$A$2:$B$7,2,0),VLOOKUP(G71,'для артикула'!$A$13:$B$14,2,0),VLOOKUP(E71,'для артикула'!$A$9:$B$11,2,0),VLOOKUP(F71,'для артикула'!$A$17:$B$19,2,0),VLOOKUP(J71,'для артикула'!$A$22:$B$23,2,0),VLOOKUP(H71,'для артикула'!$"&"A$26:$B$30,2,0))"),"002-2013E50Q13-OK") -> 002-2013E50Q13-OK | N71: =IF(ISNUMBER(MATCH(C71, 'Реестр договоров'!$D$2:$D$900, 0)), "Продано", "В наличии") -> Продано
A72: 45502.525 | C72: MX4000002R0001741 | D72: Прицеп 2,0*1,25 м (до 750 кг.) | E72: 50 | F72: R13 | G72: R13 | H72: нет | I72: 45499 | J72: есть | K72: Алматы | L72: 1 ось | M72: =IFERROR(__xludf.DUMMYFUNCTION("JOIN("""",VLOOKUP(D72,'для артикула'!$A$2:$B$7,2,0),VLOOKUP(G72,'для артикула'!$A$13:$B$14,2,0),VLOOKUP(E72,'для артикула'!$A$9:$B$11,2,0),VLOOKUP(F72,'для артикула'!$A$17:$B$19,2,0),VLOOKUP(J72,'для артикула'!$A$22:$B$23,2,0),VLOOKUP(H72,'для артикула'!$"&"A$26:$B$30,2,0))"),"002-2013E50Q13-OK") -> 002-2013E50Q13-OK | N72: =IF(ISNUMBER(MATCH(C72, 'Реестр договоров'!$D$2:$D$900, 0)), "Продано", "В наличии") -> Продано
A73: 45502.524 | C73: MX4000002R0001740 | D73: Прицеп 2,0*1,25 м (до 750 кг.) | E73: 50 | F73: R13 | G73: R13 | H73: нет | I73: 45499 | J73: есть | K73: Алматы | L73: 1 ось | M73: =IFERROR(__xludf.DUMMYFUNCTION("JOIN("""",VLOOKUP(D73,'для артикула'!$A$2:$B$7,2,0),VLOOKUP(G73,'для артикула'!$A$13:$B$14,2,0),VLOOKUP(E73,'для артикула'!$A$9:$B$11,2,0),VLOOKUP(F73,'для артикула'!$A$17:$B$19,2,0),VLOOKUP(J73,'для артикула'!$A$22:$B$23,2,0),VLOOKUP(H73,'для артикула'!$"&"A$26:$B$30,2,0))"),"002-2013E50Q13-OK") -> 002-2013E50Q13-OK | N73: =IF(ISNUMBER(MATCH(C73, 'Реестр договоров'!$D$2:$D$900, 0)), "Продано", "В наличии") -> Продано
A74: 45502.524 | C74: MX4000002R0001739 | D74: Прицеп 2,0*1,25 м (до 750 кг.) | E74: 50 | F74: R13 | G74: R13 | H74: нет | I74: 45499 | J74: есть | K74: Алматы | L74: 1 ось | M74: =IFERROR(__xludf.DUMMYFUNCTION("JOIN("""",VLOOKUP(D74,'для артикула'!$A$2:$B$7,2,0),VLOOKUP(G74,'для артикула'!$A$13:$B$14,2,0),VLOOKUP(E74,'для артикула'!$A$9:$B$11,2,0),VLOOKUP(F74,'для артикула'!$A$17:$B$19,2,0),VLOOKUP(J74,'для артикула'!$A$22:$B$23,2,0),VLOOKUP(H74,'для артикула'!$"&"A$26:$B$30,2,0))"),"002-2013E50Q13-OK") -> 002-2013E50Q13-OK | N74: =IF(ISNUMBER(MATCH(C74, 'Реестр договоров'!$D$2:$D$900, 0)), "Продано", "В наличии") -> Продано
A75: 45502.523 | C75: MX4000002R0001738 | D75: Прицеп 2,0*1,25 м (до 750 кг.) | E75: 30 | F75: R13 | G75: R13 | H75: нет | I75: 45499 | J75: есть | K75: Алматы | L75: 1 ось | M75: =IFERROR(__xludf.DUMMYFUNCTION("JOIN("""",VLOOKUP(D75,'для артикула'!$A$2:$B$7,2,0),VLOOKUP(G75,'для артикула'!$A$13:$B$14,2,0),VLOOKUP(E75,'для артикула'!$A$9:$B$11,2,0),VLOOKUP(F75,'для артикула'!$A$17:$B$19,2,0),VLOOKUP(J75,'для артикула'!$A$22:$B$23,2,0),VLOOKUP(H75,'для артикула'!$"&"A$26:$B$30,2,0))"),"002-2013E30Q13-OK") -> 002-2013E30Q13-OK | N75: =IF(ISNUMBER(MATCH(C75, 'Реестр договоров'!$D$2:$D$900, 0)), "Продано", "В наличии") -> Продано
A76: 45502.523 | C76: MX4000002R0001737 | D76: Прицеп 2,0*1,25 м (до 750 кг.) | E76: 30 | F76: R13 | G76: R13 | H76: нет | I76: 45499 | J76: есть | K76: Алматы | L76: 1 ось | M76: =IFERROR(__xludf.DUMMYFUNCTION("JOIN("""",VLOOKUP(D76,'для артикула'!$A$2:$B$7,2,0),VLOOKUP(G76,'для артикула'!$A$13:$B$14,2,0),VLOOKUP(E76,'для артикула'!$A$9:$B$11,2,0),VLOOKUP(F76,'для артикула'!$A$17:$B$19,2,0),VLOOKUP(J76,'для артикула'!$A$22:$B$23,2,0),VLOOKUP(H76,'для артикула'!$"&"A$26:$B$30,2,0))"),"002-2013E30Q13-OK") -> 002-2013E30Q13-OK | N76: =IF(ISNUMBER(MATCH(C76, 'Реестр договоров'!$D$2:$D$900, 0)), "Продано", "В наличии") -> Продано
A77: 45502.522 | C77: MX4000002R0001736 | D77: Прицеп 2,0*1,25 м (до 750 кг.) | E77: 50 | F77: R13 | G77: R13 | H77: нет | I77: 45499 | J77: есть | K77: Алматы | L77: 1 ось | M77: =IFERROR(__xludf.DUMMYFUNCTION("JOIN("""",VLOOKUP(D77,'для артикула'!$A$2:$B$7,2,0),VLOOKUP(G77,'для артикула'!$A$13:$B$14,2,0),VLOOKUP(E77,'для артикула'!$A$9:$B$11,2,0),VLOOKUP(F77,'для артикула'!$A$17:$B$19,2,0),VLOOKUP(J77,'для артикула'!$A$22:$B$23,2,0),VLOOKUP(H77,'для артикула'!$"&"A$26:$B$30,2,0))"),"002-2013E50Q13-OK") -> 002-2013E50Q13-OK | N77: =IF(ISNUMBER(MATCH(C77, 'Реестр договоров'!$D$2:$D$900, 0)), "Продано", "В наличии") -> Продано
A78: 45502.521 | C78: MX4000002R0001735 | D78: Прицеп 2,0*1,25 м (до 750 кг.) | E78: 50 | F78: R13 | G78: R13 | H78: нет | I78: 45499 | J78: есть | K78: Алматы | L78: 1 ось | M78: =IFERROR(__xludf.DUMMYFUNCTION("JOIN("""",VLOOKUP(D78,'для артикула'!$A$2:$B$7,2,0),VLOOKUP(G78,'для артикула'!$A$13:$B$14,2,0),VLOOKUP(E78,'для артикула'!$A$9:$B$11,2,0),VLOOKUP(F78,'для артикула'!$A$17:$B$19,2,0),VLOOKUP(J78,'для артикула'!$A$22:$B$23,2,0),VLOOKUP(H78,'для артикула'!$"&"A$26:$B$30,2,0))"),"002-2013E50Q13-OK") -> 002-2013E50Q13-OK | N78: =IF(ISNUMBER(MATCH(C78, 'Реестр договоров'!$D$2:$D$900, 0)), "Продано", "В наличии") -> Продано
A79: 45502.52 | C79: MX4000002R0001734 | D79: Прицеп 2,0*1,25 м (до 750 кг.) | E79: 50 | F79: R13 | G79: R13 | H79: 30 | I79: 45499 | J79: есть | K79: Алматы | L79: 1 ось | M79: =IFERROR(__xludf.DUMMYFUNCTION("JOIN("""",VLOOKUP(D79,'для артикула'!$A$2:$B$7,2,0),VLOOKUP(G79,'для артикула'!$A$13:$B$14,2,0),VLOOKUP(E79,'для артикула'!$A$9:$B$11,2,0),VLOOKUP(F79,'для артикула'!$A$17:$B$19,2,0),VLOOKUP(J79,'для артикула'!$A$22:$B$23,2,0),VLOOKUP(H79,'для артикула'!$"&"A$26:$B$30,2,0))"),"002-2013E50Q13-OK30") -> 002-2013E50Q13-OK30 | N79: =IF(ISNUMBER(MATCH(C79, 'Реестр договоров'!$D$2:$D$900, 0)), "Продано", "В наличии") -> Продано
A80: 45502.519 | C80: MX4000002R0001733 | D80: Прицеп 2,0*1,25 м (до 750 кг.) | E80: 30 | F80: R13 | G80: R13 | H80: нет | I80: 45499 | J80: есть | K80: Алматы | L80: 1 ось | M80: =IFERROR(__xludf.DUMMYFUNCTION("JOIN("""",VLOOKUP(D80,'для артикула'!$A$2:$B$7,2,0),VLOOKUP(G80,'для артикула'!$A$13:$B$14,2,0),VLOOKUP(E80,'для артикула'!$A$9:$B$11,2,0),VLOOKUP(F80,'для артикула'!$A$17:$B$19,2,0),VLOOKUP(J80,'для артикула'!$A$22:$B$23,2,0),VLOOKUP(H80,'для артикула'!$"&"A$26:$B$30,2,0))"),"002-2013E30Q13-OK") -> 002-2013E30Q13-OK | N80: =IF(ISNUMBER(MATCH(C80, 'Реестр договоров'!$D$2:$D$900, 0)), "Продано", "В наличии") -> Продано
A81: 45502.518 | C81: MX4000002R0001732 | D81: Прицеп 2,0*1,25 м (до 750 кг.) | E81: 30 | F81: R13 | G81: R13 | H81: нет | I81: 45499 | J81: есть | K81: Алматы | L81: 1 ось | M81: =IFERROR(__xludf.DUMMYFUNCTION("JOIN("""",VLOOKUP(D81,'для артикула'!$A$2:$B$7,2,0),VLOOKUP(G81,'для артикула'!$A$13:$B$14,2,0),VLOOKUP(E81,'для артикула'!$A$9:$B$11,2,0),VLOOKUP(F81,'для артикула'!$A$17:$B$19,2,0),VLOOKUP(J81,'для артикула'!$A$22:$B$23,2,0),VLOOKUP(H81,'для артикула'!$"&"A$26:$B$30,2,0))"),"002-2013E30Q13-OK") -> 002-2013E30Q13-OK | N81: =IF(ISNUMBER(MATCH(C81, 'Реестр договоров'!$D$2:$D$900, 0)), "Продано", "В наличии") -> Продано
A82: 45502.518 | C82: MX4000002R0001731 | D82: Прицеп 2,0*1,25 м (до 750 кг.) | E82: 30 | F82: R13 | G82: R13 | H82: нет | I82: 45499 | J82: есть | K82: Алматы | L82: 1 ось | M82: =IFERROR(__xludf.DUMMYFUNCTION("JOIN("""",VLOOKUP(D82,'для артикула'!$A$2:$B$7,2,0),VLOOKUP(G82,'для артикула'!$A$13:$B$14,2,0),VLOOKUP(E82,'для артикула'!$A$9:$B$11,2,0),VLOOKUP(F82,'для артикула'!$A$17:$B$19,2,0),VLOOKUP(J82,'для артикула'!$A$22:$B$23,2,0),VLOOKUP(H82,'для артикула'!$"&"A$26:$B$30,2,0))"),"002-2013E30Q13-OK") -> 002-2013E30Q13-OK | N82: =IF(ISNUMBER(MATCH(C82, 'Реестр договоров'!$D$2:$D$900, 0)), "Продано", "В наличии") -> Продано
A83: 45502.517 | C83: MX4000002R0001730 | D83: Прицеп 2,0*1,25 м (до 750 кг.) | E83: 50 | F83: R13 | G83: R13 | H83: 30 | I83: 45499 | J83: есть | K83: Алматы | L83: 1 ось | M83: =IFERROR(__xludf.DUMMYFUNCTION("JOIN("""",VLOOKUP(D83,'для артикула'!$A$2:$B$7,2,0),VLOOKUP(G83,'для артикула'!$A$13:$B$14,2,0),VLOOKUP(E83,'для артикула'!$A$9:$B$11,2,0),VLOOKUP(F83,'для артикула'!$A$17:$B$19,2,0),VLOOKUP(J83,'для артикула'!$A$22:$B$23,2,0),VLOOKUP(H83,'для артикула'!$"&"A$26:$B$30,2,0))"),"002-2013E50Q13-OK30") -> 002-2013E50Q13-OK30 | N83: =IF(ISNUMBER(MATCH(C83, 'Реестр договоров'!$D$2:$D$900, 0)), "Продано", "В наличии") -> Продано
A84: 45502.516 | C84: MX4000002R0001729 | D84: Прицеп 2,0*1,25 м (до 750 кг.) | E84: 50 | F84: R13 | G84: R13 | H84: нет | I84: 45499 | J84: есть | K84: Алматы | L84: 1 ось | M84: =IFERROR(__xludf.DUMMYFUNCTION("JOIN("""",VLOOKUP(D84,'для артикула'!$A$2:$B$7,2,0),VLOOKUP(G84,'для артикула'!$A$13:$B$14,2,0),VLOOKUP(E84,'для артикула'!$A$9:$B$11,2,0),VLOOKUP(F84,'для артикула'!$A$17:$B$19,2,0),VLOOKUP(J84,'для артикула'!$A$22:$B$23,2,0),VLOOKUP(H84,'для артикула'!$"&"A$26:$B$30,2,0))"),"002-2013E50Q13-OK") -> 002-2013E50Q13-OK | N84: =IF(ISNUMBER(MATCH(C84, 'Реестр договоров'!$D$2:$D$900, 0)), "Продано", "В наличии") -> Продано
A85: 45502.515 | C85: MX4000002R0001728 | D85: Прицеп 2,0*1,25 м (до 750 кг.) | E85: 50 | F85: R13 | G85: R13 | H85: нет | I85: 45499 | J85: есть | K85: Алматы | L85: 1 ось | M85: =IFERROR(__xludf.DUMMYFUNCTION("JOIN("""",VLOOKUP(D85,'для артикула'!$A$2:$B$7,2,0),VLOOKUP(G85,'для артикула'!$A$13:$B$14,2,0),VLOOKUP(E85,'для артикула'!$A$9:$B$11,2,0),VLOOKUP(F85,'для артикула'!$A$17:$B$19,2,0),VLOOKUP(J85,'для артикула'!$A$22:$B$23,2,0),VLOOKUP(H85,'для артикула'!$"&"A$26:$B$30,2,0))"),"002-2013E50Q13-OK") -> 002-2013E50Q13-OK | N85: =IF(ISNUMBER(MATCH(C85, 'Реестр договоров'!$D$2:$D$900, 0)), "Продано", "В наличии") -> Продано
A86: 45502.515 | C86: MX4000002R0001727 | D86: Прицеп 2,0*1,25 м (до 750 кг.) | E86: 50 | F86: R13 | G86: R13 | H86: нет | I86: 45499 | J86: есть | K86: Алматы | L86: 1 ось | M86: =IFERROR(__xludf.DUMMYFUNCTION("JOIN("""",VLOOKUP(D86,'для артикула'!$A$2:$B$7,2,0),VLOOKUP(G86,'для артикула'!$A$13:$B$14,2,0),VLOOKUP(E86,'для артикула'!$A$9:$B$11,2,0),VLOOKUP(F86,'для артикула'!$A$17:$B$19,2,0),VLOOKUP(J86,'для артикула'!$A$22:$B$23,2,0),VLOOKUP(H86,'для артикула'!$"&"A$26:$B$30,2,0))"),"002-2013E50Q13-OK") -> 002-2013E50Q13-OK | N86: =IF(ISNUMBER(MATCH(C86, 'Реестр договоров'!$D$2:$D$900, 0)), "Продано", "В наличии") -> Продано
A87: 45498.541 | C87: MX4000002R0001725 | D87: Прицеп 2,0*1,25 м (до 750 кг.) | E87: 30 | F87: R15 | G87: R15 | H87: нет | I87: 45498 | J87: есть | K87: Кокшетау | L87: 1 ось | M87: =IFERROR(__xludf.DUMMYFUNCTION("JOIN("""",VLOOKUP(D87,'для артикула'!$A$2:$B$7,2,0),VLOOKUP(G87,'для артикула'!$A$13:$B$14,2,0),VLOOKUP(E87,'для артикула'!$A$9:$B$11,2,0),VLOOKUP(F87,'для артикула'!$A$17:$B$19,2,0),VLOOKUP(J87,'для артикула'!$A$22:$B$23,2,0),VLOOKUP(H87,'для артикула'!$"&"A$26:$B$30,2,0))"),"002-2013E30Q15-OK") -> 002-2013E30Q15-OK | N87: =IF(ISNUMBER(MATCH(C87, 'Реестр договоров'!$D$2:$D$900, 0)), "Продано", "В наличии") -> Продано
A88: 45537.729 | C88: MX4000002R0001723 | D88: Прицеп 2,0*1,25 м (до 750 кг.) | E88: 50 | F88: R13 | G88: R13 | H88: 60 | I88: 45537 | J88: есть | K88: Алматы | L88: 1 ось | M88: =IFERROR(__xludf.DUMMYFUNCTION("JOIN("""",VLOOKUP(D88,'для артикула'!$A$2:$B$7,2,0),VLOOKUP(G88,'для артикула'!$A$13:$B$14,2,0),VLOOKUP(E88,'для артикула'!$A$9:$B$11,2,0),VLOOKUP(F88,'для артикула'!$A$17:$B$19,2,0),VLOOKUP(J88,'для артикула'!$A$22:$B$23,2,0),VLOOKUP(H88,'для артикула'!$"&"A$26:$B$30,2,0))"),"002-2013E50Q13-OK60") -> 002-2013E50Q13-OK60 | N88: =IF(ISNUMBER(MATCH(C88, 'Реестр договоров'!$D$2:$D$900, 0)), "Продано", "В наличии") -> Продано
A89: 45469.72 | C89: MX4000002R0001722 | D89: Прицеп 2,0*1,25 м (до 750 кг.) | E89: 50 | F89: R13 | G89: R13 | H89: нет | I89: 45469 | J89: есть | K89: Кокшетау | L89: 1 ось | M89: =IFERROR(__xludf.DUMMYFUNCTION("JOIN("""",VLOOKUP(D89,'для артикула'!$A$2:$B$7,2,0),VLOOKUP(G89,'для артикула'!$A$13:$B$14,2,0),VLOOKUP(E89,'для артикула'!$A$9:$B$11,2,0),VLOOKUP(F89,'для артикула'!$A$17:$B$19,2,0),VLOOKUP(J89,'для артикула'!$A$22:$B$23,2,0),VLOOKUP(H89,'для артикула'!$"&"A$26:$B$30,2,0))"),"002-2013E50Q13-OK") -> 002-2013E50Q13-OK | N89: =IF(ISNUMBER(MATCH(C89, 'Реестр договоров'!$D$2:$D$900, 0)), "Продано", "В наличии") -> Продано
A90: 45467.692 | C90: MX4000002R0001698 | D90: Прицеп 2,0*1,25 м (до 750 кг.) | E90: 50 | F90: R13 | G90: R13 | H90: нет | I90: 45467 | J90: есть | K90: Кокшетау | L90: 1 ось | M90: =IFERROR(__xludf.DUMMYFUNCTION("JOIN("""",VLOOKUP(D90,'для артикула'!$A$2:$B$7,2,0),VLOOKUP(G90,'для артикула'!$A$13:$B$14,2,0),VLOOKUP(E90,'для артикула'!$A$9:$B$11,2,0),VLOOKUP(F90,'для артикула'!$A$17:$B$19,2,0),VLOOKUP(J90,'для артикула'!$A$22:$B$23,2,0),VLOOKUP(H90,'для артикула'!$"&"A$26:$B$30,2,0))"),"002-2013E50Q13-OK") -> 002-2013E50Q13-OK | N90: =IF(ISNUMBER(MATCH(C90, 'Реестр договоров'!$D$2:$D$900, 0)), "Продано", "В наличии") -> Продано
A91: 45510.639 | C91: MX4000002R0001696 | D91: Прицеп 2,0*1,25 м (до 750 кг.) | E91: 50 | F91: R13 | G91: R13 | H91: 60 | I91: 45510 | J91: есть | K91: Кокшетау | L91: 1 ось | M91: 002-2013E50Q13-OK60 | N91: =IF(ISNUMBER(MATCH(C91, 'Реестр договоров'!$D$2:$D$900, 0)), "Продано", "В наличии") -> Продано
A92: 45497.512 | C92: MX4000002R0001693 | D92: Прицеп 2,0*1,25 м (до 750 кг.) | E92: 50 | F92: R13 | G92: R13 | H92: нет | I92: 45497 | J92: есть | K92: Астана | L92: 1 ось | M92: =IFERROR(__xludf.DUMMYFUNCTION("JOIN("""",VLOOKUP(D92,'для артикула'!$A$2:$B$7,2,0),VLOOKUP(G92,'для артикула'!$A$13:$B$14,2,0),VLOOKUP(E92,'для артикула'!$A$9:$B$11,2,0),VLOOKUP(F92,'для артикула'!$A$17:$B$19,2,0),VLOOKUP(J92,'для артикула'!$A$22:$B$23,2,0),VLOOKUP(H92,'для артикула'!$"&"A$26:$B$30,2,0))"),"002-2013E50Q13-OK") -> 002-2013E50Q13-OK | N92: =IF(ISNUMBER(MATCH(C92, 'Реестр договоров'!$D$2:$D$900, 0)), "Продано", "В наличии") -> Продано
A93: 45483.737 | C93: MX4000002R0001692 | D93: Прицеп 2,0*1,25 м (до 750 кг.) | E93: 30 | F93: R13 | G93: R13 | H93: нет | I93: 45483 | J93: есть | K93: Астана | L93: 1 ось | M93: =IFERROR(__xludf.DUMMYFUNCTION("JOIN("""",VLOOKUP(D93,'для артикула'!$A$2:$B$7,2,0),VLOOKUP(G93,'для артикула'!$A$13:$B$14,2,0),VLOOKUP(E93,'для артикула'!$A$9:$B$11,2,0),VLOOKUP(F93,'для артикула'!$A$17:$B$19,2,0),VLOOKUP(J93,'для артикула'!$A$22:$B$23,2,0),VLOOKUP(H93,'для артикула'!$"&"A$26:$B$30,2,0))"),"002-2013E30Q13-OK") -> 002-2013E30Q13-OK | N93: =IF(ISNUMBER(MATCH(C93, 'Реестр договоров'!$D$2:$D$900, 0)), "Продано", "В наличии") -> Продано
A94: 45504.627 | C94: MX4000002R0001691 | D94: Прицеп 2,0*1,25 м (до 750 кг.) | E94: 50 | F94: R13 | G94: R13 | H94: нет | I94: 45504 | J94: есть | K94: Кокшетау | L94: 1 ось | M94: =IFERROR(__xludf.DUMMYFUNCTION("JOIN("""",VLOOKUP(D94,'для артикула'!$A$2:$B$7,2,0),VLOOKUP(G94,'для артикула'!$A$13:$B$14,2,0),VLOOKUP(E94,'для артикула'!$A$9:$B$11,2,0),VLOOKUP(F94,'для артикула'!$A$17:$B$19,2,0),VLOOKUP(J94,'для артикула'!$A$22:$B$23,2,0),VLOOKUP(H94,'для артикула'!$"&"A$26:$B$30,2,0))"),"002-2013E50Q13-OK") -> 002-2013E50Q13-OK | N94: =IF(ISNUMBER(MATCH(C94, 'Реестр договоров'!$D$2:$D$900, 0)), "Продано", "В наличии") -> Продано
A95: 45502.526 | C95: MX4000002R0001690 | D95: Прицеп 2,0*1,25 м (до 750 кг.) | E95: 50 | F95: R13 | G95: R13 | H95: нет | I95: 45499 | J95: есть | K95: Алматы | L95: 1 ось | M95: =IFERROR(__xludf.DUMMYFUNCTION("JOIN("""",VLOOKUP(D95,'для артикула'!$A$2:$B$7,2,0),VLOOKUP(G95,'для артикула'!$A$13:$B$14,2,0),VLOOKUP(E95,'для артикула'!$A$9:$B$11,2,0),VLOOKUP(F95,'для артикула'!$A$17:$B$19,2,0),VLOOKUP(J95,'для артикула'!$A$22:$B$23,2,0),VLOOKUP(H95,'для артикула'!$"&"A$26:$B$30,2,0))"),"002-2013E50Q13-OK") -> 002-2013E50Q13-OK | N95: =IF(ISNUMBER(MATCH(C95, 'Реестр договоров'!$D$2:$D$900, 0)), "Продано", "В наличии") -> Продано
A96: 45484.654 | C96: MX4000002R0001689 | D96: Прицеп 2,0*1,25 м (до 750 кг.) | E96: 30 | F96: R13 | G96: R13 | H96: нет | I96: 45484 | J96: есть | K96: Кокшетау | L96: 1 ось | M96: =IFERROR(__xludf.DUMMYFUNCTION("JOIN("""",VLOOKUP(D96,'для артикула'!$A$2:$B$7,2,0),VLOOKUP(G96,'для артикула'!$A$13:$B$14,2,0),VLOOKUP(E96,'для артикула'!$A$9:$B$11,2,0),VLOOKUP(F96,'для артикула'!$A$17:$B$19,2,0),VLOOKUP(J96,'для артикула'!$A$22:$B$23,2,0),VLOOKUP(H96,'для артикула'!$"&"A$26:$B$30,2,0))"),"002-2013E30Q13-OK") -> 002-2013E30Q13-OK | N96: =IF(ISNUMBER(MATCH(C96, 'Реестр договоров'!$D$2:$D$900, 0)), "Продано", "В наличии") -> Продано
A97: 45467.641 | C97: MX4000002R0001687 | D97: Прицеп 2,0*1,25 м (до 750 кг.) | E97: 50 | F97: R13 | G97: R13 | H97: нет | I97: 45467 | J97: есть | K97: Астана | L97: 1 ось | M97: =IFERROR(__xludf.DUMMYFUNCTION("JOIN("""",VLOOKUP(D97,'для артикула'!$A$2:$B$7,2,0),VLOOKUP(G97,'для артикула'!$A$13:$B$14,2,0),VLOOKUP(E97,'для артикула'!$A$9:$B$11,2,0),VLOOKUP(F97,'для артикула'!$A$17:$B$19,2,0),VLOOKUP(J97,'для артикула'!$A$22:$B$23,2,0),VLOOKUP(H97,'для артикула'!$"&"A$26:$B$30,2,0))"),"002-2013E50Q13-OK") -> 002-2013E50Q13-OK | N97: =IF(ISNUMBER(MATCH(C97, 'Реестр договоров'!$D$2:$D$900, 0)), "Продано", "В наличии") -> Продано
A98: 45491.427 | C98: MX4000002R0001683 | D98: Прицеп 2,0*1,25 м (до 750 кг.) | E98: 50 | F98: R13 | G98: R13 | H98: нет | I98: 45491 | J98: есть | K98: Астана | L98: 1 ось | M98: =IFERROR(__xludf.DUMMYFUNCTION("JOIN("""",VLOOKUP(D98,'для артикула'!$A$2:$B$7,2,0),VLOOKUP(G98,'для артикула'!$A$13:$B$14,2,0),VLOOKUP(E98,'для артикула'!$A$9:$B$11,2,0),VLOOKUP(F98,'для артикула'!$A$17:$B$19,2,0),VLOOKUP(J98,'для артикула'!$A$22:$B$23,2,0),VLOOKUP(H98,'для артикула'!$"&"A$26:$B$30,2,0))"),"002-2013E50Q13-OK") -> 002-2013E50Q13-OK | N98: =IF(ISNUMBER(MATCH(C98, 'Реестр договоров'!$D$2:$D$900, 0)), "Продано", "В наличии") -> Продано
A99: 45491.409 | C99: MX4000002R0001682 | D99: Прицеп 2,0*1,25 м (до 750 кг.) | E99: 50 | F99: R13 | G99: R13 | H99: нет | I99: 45491 | J99: есть | K99: Астана | L99: 1 ось | M99: =IFERROR(__xludf.DUMMYFUNCTION("JOIN("""",VLOOKUP(D99,'для артикула'!$A$2:$B$7,2,0),VLOOKUP(G99,'для артикула'!$A$13:$B$14,2,0),VLOOKUP(E99,'для артикула'!$A$9:$B$11,2,0),VLOOKUP(F99,'для артикула'!$A$17:$B$19,2,0),VLOOKUP(J99,'для артикула'!$A$22:$B$23,2,0),VLOOKUP(H99,'для артикула'!$"&"A$26:$B$30,2,0))"),"002-2013E50Q13-OK") -> 002-2013E50Q13-OK | N99: =IF(ISNUMBER(MATCH(C99, 'Реестр договоров'!$D$2:$D$900, 0)), "Продано", "В наличии") -> Продано
A100: 45464.523 | C100: MX4000002R0001680 | D100: Прицеп 2,0*1,25 м (до 750 кг.) | E100: 50 | F100: R13 | G100: R13 | H100: нет | I100: 45464 | J100: есть | K100: Астана | L100: 1 ось | M100: =IFERROR(__xludf.DUMMYFUNCTION("JOIN("""",VLOOKUP(D100,'для артикула'!$A$2:$B$7,2,0),VLOOKUP(G100,'для артикула'!$A$13:$B$14,2,0),VLOOKUP(E100,'для артикула'!$A$9:$B$11,2,0),VLOOKUP(F100,'для артикула'!$A$17:$B$19,2,0),VLOOKUP(J100,'для артикула'!$A$22:$B$23,2,0),VLOOKUP(H100,'для артик"&"ула'!$A$26:$B$30,2,0))"),"002-2013E50Q13-OK") -> 002-2013E50Q13-OK | N100: =IF(ISNUMBER(MATCH(C100, 'Реестр договоров'!$D$2:$D$900, 0)), "Продано", "В наличии") -> Продано
...

Sheet Сводная таблица ФЛ
B1: дата | C1: фамилия | D1: Имя | E1: Отчество | F1: удостоверение № | G1: дата выдачи удостоверения | H1: кем выдано | I1: ИИН | J1: Адрес проживания | K1: Телефон | L1: VIN | M1: Артикул | N1: прицеп | O1: Количество осей | P1: год выпуска прицепа | Q1: габариты | R1: размеры кузова | S1: ОТТС | T1: цена | U1: склад
A2: 1161 | B2: =VLOOKUP(A2,'Реестр договоров'!$A$2:$D$149,2,0) -> 45447 | C2: =VLOOKUP(A2,Реестр_Договоров,3,0) -> Белоногова | D2: =VLOOKUP(C2,Покупатели,2,0) -> Алена | E2: =VLOOKUP(C2,Покупатели,3,0) -> Андреевна | F2: =VLOOKUP(C2,Покупатели,4,0) -> 040645875 | G2: =VLOOKUP(F2,Покупатели!$F$2:$N$762,2,0) -> 42627 | H2: =VLOOKUP(F2,Покупатели!$F$2:$N$762,3,0) -> МВД РК | I2: =VLOOKUP(C2,Покупатели!$C$2:$M$805,7,0) -> 890311400050 | J2: =IFERROR(__xludf.DUMMYFUNCTION("JOIN("" "", VLOOKUP(C2,Покупатели,8,0),VLOOKUP(C2,Покупатели,9,0),VLOOKUP(C2,Покупатели,10,0),VLOOKUP(C2,Покупатели,11,0))"),"г.Алматы ") -> г.Алматы | K2: =VLOOKUP(C2,Покупатели,12,0) -> 87764755555 | L2: =VLOOKUP(A2,Реестр_Договоров,4,0) -> MX4000002R0001522 | M2: 002-2313E30Q13-OK | N2: Прицеп 2,3*1,25 м (до 750 кг.) | O2: =VLOOKUP(L2,ПРИЦЕПЫ,10,0) -> 1 ось | P2: =YEAR(VLOOKUP(L2,ПРИЦЕПЫ,7,0)) -> 2024 | Q2: 3450*1700*900 | R2: 2300*1250*300 | S2: =VLOOKUP(O2,ОТТС!$A$2:$B$3,2,0) -> ТС KZ Е-KZ.0317.00251 от 28.02.2023 | T2: 320000 | U2: =VLOOKUP(L2,ПРИЦЕПЫ,9,0) -> Алматы
A3: 1162 | B3: =VLOOKUP(A3,'Реестр договоров'!$A$2:$D$169,2,0) -> 45449 | C3: =VLOOKUP(A3,Реестр_Договоров,3,0) -> Рахманов | D3: =VLOOKUP(C3,Покупатели,2,0) -> Мурат | E3: =VLOOKUP(C3,Покупатели,3,0) -> Халмуратович | F3: =VLOOKUP(C3,Покупатели,4,0) -> 044798593 | G3: =VLOOKUP(F3,Покупатели!$F$2:$N$762,2,0) -> 43531 | H3: =VLOOKUP(F3,Покупатели!$F$2:$N$762,3,0) -> МВД РК | I3: =VLOOKUP(C3,Покупатели!$C$2:$M$805,7,0) -> 881115302551 | J3: =IFERROR(__xludf.DUMMYFUNCTION("JOIN("" "", VLOOKUP(C3,Покупатели,8,0),VLOOKUP(C3,Покупатели,9,0),VLOOKUP(C3,Покупатели,10,0),VLOOKUP(C3,Покупатели,11,0))"),"Талгарский район, пос.Бесагаш, ул.Бейбитшилик 30 Бейбитшилик 30") -> Талгарский район, пос.Бесагаш, ул.Бейбитшилик 30 Бейбитшилик 30 | K3: =VLOOKUP(C3,Покупатели,12,0) -> 87071133370 | L3: =VLOOKUP(A3,Реестр_Договоров,4,0) -> MX4000002R0001502 | M3: =VLOOKUP(L3,ПРИЦЕПЫ,11,0) -> 002-2513E50Q13-OK | N3: =VLOOKUP(L3,ПРИЦЕПЫ,2,0) -> Прицеп 2,5*1,25 м (до 750 кг.) | O3: =VLOOKUP(L3,ПРИЦЕПЫ,10,0) -> 1 ось | P3: =YEAR(VLOOKUP(L3,ПРИЦЕПЫ,7,0)) -> 2024 | Q3: =VLOOKUP(M3,матрица,16,0) -> 3650*1700*1070 | R3: =VLOOKUP(M3,матрица,17,0) -> 2500*1250*500 | S3: =VLOOKUP(O3,ОТТС!$A$2:$B$3,2,0) -> ТС KZ Е-KZ.0317.00251 от 28.02.2023 | T3: 410000 | U3: =VLOOKUP(L3,ПРИЦЕПЫ,9,0) -> Алматы
A4: 1163 | B4: =VLOOKUP(A4,'Реестр договоров'!$A$2:$D$506,2,0) -> 45450 | C4: =VLOOKUP(A4,Реестр_Договоров,3,0) -> Кулиева | D4: =VLOOKUP(C4,Покупатели,2,0) -> Ёсма | E4: =VLOOKUP(C4,Покупатели,3,0) -> Ахмедовна | F4: =VLOOKUP(C4,Покупатели,4,0) -> 045683377 | G4: =VLOOKUP(F4,Покупатели!$F$2:$N$762,2,0) -> 43852 | H4: =VLOOKUP(F4,Покупатели!$F$2:$N$762,3,0) -> МВД РК | I4: =VLOOKUP(C4,Покупатели!$C$2:$M$805,7,0) -> 841220400347 | J4: =IFERROR(__xludf.DUMMYFUNCTION("JOIN("" "", VLOOKUP(C4,Покупатели,8,0),VLOOKUP(C4,Покупатели,9,0),VLOOKUP(C4,Покупатели,10,0),VLOOKUP(C4,Покупатели,11,0))"),"Алматинская область Алматы _____ ______") -> Алматинская область Алматы _____ ______ | K4: =VLOOKUP(C4,Покупатели,12,0) -> 87476056411 | L4: =VLOOKUP(A4,Реестр_Договоров,4,0) -> MX4000002R0001511 | M4: =VLOOKUP(L4,ПРИЦЕПЫ,11,0) -> 002-2513E30Q13-OK | N4: =VLOOKUP(L4,ПРИЦЕПЫ,2,0) -> Прицеп 2,5*1,25 м (до 750 кг.) | O4: =VLOOKUP(L4,ПРИЦЕПЫ,10,0) -> 1 ось | P4: =YEAR(VLOOKUP(L4,ПРИЦЕПЫ,7,0)) -> 2024 | Q4: =VLOOKUP(M4,матрица,16,0) -> 3650*1700*900 | R4: =VLOOKUP(M4,матрица,17,0) -> 2500*1250*300 | S4: =VLOOKUP(O4,ОТТС!$A$2:$B$3,2,0) -> ТС KZ Е-KZ.0317.00251 от 28.02.2023 | T4: 320000 | U4: =VLOOKUP(L4,ПРИЦЕПЫ,9,0) -> Алматы
A5: 1164 | B5: =VLOOKUP(A5,'Реестр договоров'!$A$2:$D$89,2,0) -> 45451 | C5: =VLOOKUP(A5,Реестр_Договоров,3,0) -> Петрик | D5: =VLOOKUP(C5,Покупатели,2,0) -> Владимир | E5: =VLOOKUP(C5,Покупатели,3,0) -> Ярославович | F5: =VLOOKUP(C5,Покупатели,4,0) -> 050163641 | G5: =VLOOKUP(F5,Покупатели!$F$2:$N$762,2,0) -> 44614 | H5: =VLOOKUP(F5,Покупатели!$F$2:$N$762,3,0) -> МВД РК | I5: =VLOOKUP(C5,Покупатели!$C$2:$M$805,7,0) -> 870213300256 | J5: =IFERROR(__xludf.DUMMYFUNCTION("JOIN("" "", VLOOKUP(C5,Покупатели,8,0),VLOOKUP(C5,Покупатели,9,0),VLOOKUP(C5,Покупатели,10,0),VLOOKUP(C5,Покупатели,11,0))"),"Алматинская Алматы неизвестно неизвестно") -> Алматинская Алматы неизвестно неизвестно | K5: =VLOOKUP(C5,Покупатели,12,0) -> 87019294069 | L5: =VLOOKUP(A5,Реестр_Договоров,4,0) -> MX4000002R0001518 | M5: =VLOOKUP(L5,ПРИЦЕПЫ,11,0) -> 002-2513E50Q13 | N5: =VLOOKUP(L5,ПРИЦЕПЫ,2,0) -> Прицеп 2,5*1,25 м (до 750 кг.) | O5: =VLOOKUP(L5,ПРИЦЕПЫ,10,0) -> 1 ось | P5: =YEAR(VLOOKUP(L5,ПРИЦЕПЫ,7,0)) -> 2024 | Q5: =VLOOKUP(M5,матрица,16,0) -> 3650*1700*1070 | R5: =VLOOKUP(M5,матрица,17,0) -> 2500*1250*500 | S5: =VLOOKUP(O5,ОТТС!$A$2:$B$3,2,0) -> ТС KZ Е-KZ.0317.00251 от 28.02.2023 | T5: 460000 | U5: =VLOOKUP(L5,ПРИЦЕПЫ,9,0) -> Алматы
A6: 1165 | B6: =VLOOKUP(A6,'Реестр договоров'!$A$2:$D$506,2,0) -> 45451 | C6: =VLOOKUP(A6,Реестр_Договоров,3,0) -> Ребенков | D6: =VLOOKUP(C6,Покупатели,2,0) -> Вячеслав | E6: =VLOOKUP(C6,Покупатели,3,0) -> Сергеевич | F6: =VLOOKUP(C6,Покупатели,4,0) -> 046534151 | G6: =VLOOKUP(F6,Покупатели!$F$2:$N$762,2,0) -> 44013 | H6: =VLOOKUP(F6,Покупатели!$F$2:$N$762,3,0) -> МВД РК | I6: =VLOOKUP(C6,Покупатели!$C$2:$M$805,7,0) -> 850210303171 | J6: =IFERROR(__xludf.DUMMYFUNCTION("JOIN("" "", VLOOKUP(C6,Покупатели,8,0),VLOOKUP(C6,Покупатели,9,0),VLOOKUP(C6,Покупатели,10,0),VLOOKUP(C6,Покупатели,11,0))"),"Алматинская Алматы неизвестно неизвестно") -> Алматинская Алматы неизвестно неизвестно | K6: =VLOOKUP(C6,Покупатели,12,0) -> 87770334835 | L6: =VLOOKUP(A6,Реестр_Договоров,4,0) -> MX4000002R0001573 | M6: =VLOOKUP(L6,ПРИЦЕПЫ,11,0) -> 002-2013E30Q13-OK | N6: =VLOOKUP(L6,ПРИЦЕПЫ,2,0) -> Прицеп 2,0*1,25 м (до 750 кг.) | O6: =VLOOKUP(L6,ПРИЦЕПЫ,10,0) -> 1 ось | P6: =YEAR(VLOOKUP(L6,ПРИЦЕПЫ,7,0)) -> 2024 | Q6: =VLOOKUP(M6,матрица,16,0) -> 3150*1700*900 | R6: =VLOOKUP(M6,матрица,17,0) -> 2000*1250*300 | S6: =VLOOKUP(O6,ОТТС!$A$2:$B$3,2,0) -> ТС KZ Е-KZ.0317.00251 от 28.02.2023 | T6: 350000 | U6: =VLOOKUP(L6,ПРИЦЕПЫ,9,0) -> Алматы
A7: 1166 | B7: =VLOOKUP(A7,'Реестр договоров'!$A$2:$D$506,2,0) -> 45451 | C7: =VLOOKUP(A7,Реестр_Договоров,3,0) -> Темирбаев | D7: =VLOOKUP(C7,Покупатели,2,0) -> Талгат | E7: =VLOOKUP(C7,Покупатели,3,0) -> Ахванович | F7: =VLOOKUP(C7,Покупатели,4,0) -> 045893821 | G7: =VLOOKUP(F7,Покупатели!$F$2:$N$762,2,0) -> 43882 | H7: =VLOOKUP(F7,Покупатели!$F$2:$N$762,3,0) -> МВД РК | I7: =VLOOKUP(C7,Покупатели!$C$2:$M$805,7,0) -> 720613302306 | J7: =IFERROR(__xludf.DUMMYFUNCTION("JOIN("" "", VLOOKUP(C7,Покупатели,8,0),VLOOKUP(C7,Покупатели,9,0),VLOOKUP(C7,Покупатели,10,0),VLOOKUP(C7,Покупатели,11,0))"),"Алматинская Алматы ____ ____") -> Алматинская Алматы ____ ____ | K7: =VLOOKUP(C7,Покупатели,12,0) -> 87754573372 | L7: =VLOOKUP(A7,Реестр_Договоров,4,0) -> MX4000002R0001455 | M7: =VLOOKUP(L7,ПРИЦЕПЫ,11,0) -> 002-2013E50Q13-OK | N7: =VLOOKUP(L7,ПРИЦЕПЫ,2,0) -> Прицеп 2,0*1,25 м (до 750 кг.) | O7: =VLOOKUP(L7,ПРИЦЕПЫ,10,0) -> 1 ось | P7: =YEAR(VLOOKUP(L7,ПРИЦЕПЫ,7,0)) -> 2024 | Q7: =VLOOKUP(M7,матрица,16,0) -> 3150*1700*1070 | R7: =VLOOKUP(M7,матрица,17,0) -> 2000*1250*500 | S7: =VLOOKUP(O7,ОТТС!$A$2:$B$3,2,0) -> ТС KZ Е-KZ.0317.00251 от 28.02.2023 | T7: 410000 | U7: =VLOOKUP(L7,ПРИЦЕПЫ,9,0) -> Алматы
A8: 1167 | B8: =VLOOKUP(A8,'Реестр договоров'!$A$2:$D$55,2,0) -> 45453 | C8: =VLOOKUP(A8,Реестр_Договоров,3,0) -> Доспергенов | D8: =VLOOKUP(C8,Покупатели,2,0) -> Акылбек | E8: =VLOOKUP(C8,Покупатели,3,0) -> Казисович | F8: =VLOOKUP(C8,Покупатели,4,0) -> 047229978 | G8: =VLOOKUP(F8,Покупатели!$F$2:$N$762,2,0) -> 43844 | H8: =VLOOKUP(F8,Покупатели!$F$2:$N$762,3,0) -> МВД РК | I8: =VLOOKUP(C8,Покупатели!$C$2:$M$805,7,0) -> 680601300126 | J8: =IFERROR(__xludf.DUMMYFUNCTION("JOIN("" "", VLOOKUP(C8,Покупатели,8,0),VLOOKUP(C8,Покупатели,9,0),VLOOKUP(C8,Покупатели,10,0),VLOOKUP(C8,Покупатели,11,0))"),"Акмолинская область Район Биржан Сал, г.Степняк ул.Сейфуллина 31") -> Акмолинская область Район Биржан Сал, г.Степняк ул.Сейфуллина 31 | K8: =VLOOKUP(C8,Покупатели,12,0) -> 87752586301 | L8: =VLOOKUP(A8,Реестр_Договоров,4,0) -> MX4000002R0001719 | M8: =VLOOKUP(L8,ПРИЦЕПЫ,11,0) -> 002-2515E50Q13-OK60 | N8: =VLOOKUP(L8,ПРИЦЕПЫ,2,0) -> Прицеп 2,5*1,5 м (до 750 кг.) | O8: =VLOOKUP(L8,ПРИЦЕПЫ,10,0) -> 1 ось | P8: =YEAR(VLOOKUP(L8,ПРИЦЕПЫ,7,0)) -> 2024 | Q8: =VLOOKUP(M8,матрица,16,0) -> #N/A | R8: =VLOOKUP(M8,матрица,17,0) -> #N/A | S8: =VLOOKUP(O8,ОТТС!$A$2:$B$3,2,0) -> ТС KZ Е-KZ.0317.00251 от 28.02.2023 | T8: 430000 | U8: =VLOOKUP(L8,ПРИЦЕПЫ,9,0) -> Кокшетау
A9: 1168 | B9: =VLOOKUP(A9,'Реестр договоров'!$A$2:$D$149,2,0) -> 45451 | C9: =VLOOKUP(A9,Реестр_Договоров,3,0) -> Касымов | D9: =VLOOKUP(C9,Покупатели,2,0) -> Серик | E9: =VLOOKUP(C9,Покупатели,3,0) -> Кушенович | F9: =VLOOKUP(C9,Покупатели,4,0) -> 019325596 | G9: =VLOOKUP(F9,Покупатели!$F$2:$N$762,2,0) -> 38940 | H9: =VLOOKUP(F9,Покупатели!$F$2:$N$762,3,0) -> МЮ РК | I9: =VLOOKUP(C9,Покупатели!$C$2:$M$805,7,0) -> 610801350197 | J9: =IFERROR(__xludf.DUMMYFUNCTION("JOIN("" "", VLOOKUP(C9,Покупатели,8,0),VLOOKUP(C9,Покупатели,9,0),VLOOKUP(C9,Покупатели,10,0),VLOOKUP(C9,Покупатели,11,0))"),"Акмолинская область г.Макинск Ул.Луговая 48") -> Акмолинская область г.Макинск Ул.Луговая 48 | K9: =VLOOKUP(C9,Покупатели,12,0) -> 87752523752 | L9: =VLOOKUP(A9,Реестр_Договоров,4,0) -> MX4000002R0001642 | M9: =VLOOKUP(L9,ПРИЦЕПЫ,11,0) -> 002-2513E50Q13-OK60 | N9: =VLOOKUP(L9,ПРИЦЕПЫ,2,0) -> Прицеп 2,5*1,25 м (до 750 кг.) | O9: =VLOOKUP(L9,ПРИЦЕПЫ,10,0) -> 1 ось | P9: =YEAR(VLOOKUP(L9,ПРИЦЕПЫ,7,0)) -> 2024 | Q9: =VLOOKUP(M9,матрица,16,0) -> 3650*1700*1070 | R9: =VLOOKUP(M9,матрица,17,0) -> 2500*1250*500 | S9: =VLOOKUP(O9,ОТТС!$A$2:$B$3,2,0) -> ТС KZ Е-KZ.0317.00251 от 28.02.2023 | T9: 450000 | U9: =VLOOKUP(L9,ПРИЦЕПЫ,9,0) -> Астана
A10: 1169 | B10: =VLOOKUP(A10,'Реестр договоров'!$A$2:$D$100,2,0) -> 45455 | C10: =VLOOKUP(A10,Реестр_Договоров,3,0) -> Сулейменов 2 | D10: =VLOOKUP(C10,Покупатели,2,0) -> Ерсин | E10: =VLOOKUP(C10,Покупатели,3,0) -> Султанович | F10: =VLOOKUP(C10,Покупатели,4,0) -> 048516590 | G10: =VLOOKUP(F10,Покупатели!$F$2:$N$762,2,0) -> 44057 | H10: =VLOOKUP(F10,Покупатели!$F$2:$N$762,3,0) -> МВД РК | I10: =VLOOKUP(C10,Покупатели!$C$2:$M$805,7,0) -> 640617350370 | J10: =IFERROR(__xludf.DUMMYFUNCTION("JOIN("" "", VLOOKUP(C10,Покупатели,8,0),VLOOKUP(C10,Покупатели,9,0),VLOOKUP(C10,Покупатели,10,0),VLOOKUP(C10,Покупатели,11,0))"),"Костанайская область г.Аркалык ул.Ашу тасты, 60 лет казахстан ") -> Костанайская область г.Аркалык ул.Ашу тасты, 60 лет казахстан | K10: =VLOOKUP(C10,Покупатели,12,0) -> 87783266344 | L10: =VLOOKUP(A10,Реестр_Договоров,4,0) -> MX4000002R0001659 | M10: =VLOOKUP(L10,ПРИЦЕПЫ,11,0) -> 002-2013E50Q13-OK | N10: =VLOOKUP(L10,ПРИЦЕПЫ,2,0) -> Прицеп 2,0*1,25 м (до 750 кг.) | O10: =VLOOKUP(L10,ПРИЦЕПЫ,10,0) -> 1 ось | P10: =YEAR(VLOOKUP(L10,ПРИЦЕПЫ,7,0)) -> 2024 | Q10: =VLOOKUP(M10,матрица,16,0) -> 3150*1700*1070 | R10: =VLOOKUP(M10,матрица,17,0) -> 2000*1250*500 | S10: =VLOOKUP(O10,ОТТС!$A$2:$B$3,2,0) -> ТС KZ Е-KZ.0317.00251 от 28.02.2023 | T10: 340000 | U10: =VLOOKUP(L10,ПРИЦЕПЫ,9,0) -> Астана
A11: 1170 | B11: =VLOOKUP(A11,'Реестр договоров'!$A$2:$D$80,2,0) -> 45460 | C11: =VLOOKUP(A11,Реестр_Договоров,3,0) -> Курбанова | D11: =VLOOKUP(C11,Покупатели,2,0) -> Лязиза | E11: =VLOOKUP(C11,Покупатели,3,0) -> Зерупжановна | F11: =VLOOKUP(C11,Покупатели,4,0) -> 036786727 | G11: =VLOOKUP(F11,Покупатели!$F$2:$N$762,2,0) -> 41851 | H11: =VLOOKUP(F11,Покупатели!$F$2:$N$762,3,0) -> МВД РК | I11: =VLOOKUP(C11,Покупатели!$C$2:$M$805,7,0) -> 930829401203 | J11: =IFERROR(__xludf.DUMMYFUNCTION("JOIN("" "", VLOOKUP(C11,Покупатели,8,0),VLOOKUP(C11,Покупатели,9,0),VLOOKUP(C11,Покупатели,10,0),VLOOKUP(C11,Покупатели,11,0))"),"Алматинская область Г.Талгар Ул.Рыскулова Д.104") -> Алматинская область Г.Талгар Ул.Рыскулова Д.104 | K11: =VLOOKUP(C11,Покупатели,12,0) -> 87475777615 | L11: =VLOOKUP(A11,Реестр_Договоров,4,0) -> MX4000002R0001508 | M11: =VLOOKUP(L11,ПРИЦЕПЫ,11,0) -> 002-2513E30Q13-OK | N11: =VLOOKUP(L11,ПРИЦЕПЫ,2,0) -> Прицеп 2,5*1,25 м (до 750 кг.) | O11: =VLOOKUP(L11,ПРИЦЕПЫ,10,0) -> 1 ось | P11: =YEAR(VLOOKUP(L11,ПРИЦЕПЫ,7,0)) -> 2024 | Q11: =VLOOKUP(M11,матрица,16,0) -> 3650*1700*900 | R11: =VLOOKUP(M11,матрица,17,0) -> 2500*1250*300 | S11: =VLOOKUP(O11,ОТТС!$A$2:$B$3,2,0) -> ТС KZ Е-KZ.0317.00251 от 28.02.2023 | T11: 320000 | U11: =VLOOKUP(L11,ПРИЦЕПЫ,9,0) -> Алматы
A12: 1171 | B12: =VLOOKUP(A12,'Реестр договоров'!$A$2:$D$55,2,0) -> 45461 | C12: =VLOOKUP(A12,Реестр_Договоров,3,0) -> Абайқызы | D12: =VLOOKUP(C12,Покупатели,2,0) -> Нұргүл | E12: =VLOOKUP(C12,Покупатели,3,0) -> 0 | F12: =VLOOKUP(C12,Покупатели,4,0) -> 052028739 | G12: =VLOOKUP(F12,Покупатели!$F$2:$N$762,2,0) -> 44875 | H12: =VLOOKUP(F12,Покупатели!$F$2:$N$762,3,0) -> ҚР ІІМ | I12: =VLOOKUP(C12,Покупатели!$C$2:$M$805,7,0) -> 871112400513 | J12: =IFERROR(__xludf.DUMMYFUNCTION("JOIN("" "", VLOOKUP(C12,Покупатели,8,0),VLOOKUP(C12,Покупатели,9,0),VLOOKUP(C12,Покупатели,10,0),VLOOKUP(C12,Покупатели,11,0))"),"Алматинская область Илийский район, пос.Караой Шугыла 5") -> Алматинская область Илийский район, пос.Караой Шугыла 5 | K12: =VLOOKUP(C12,Покупатели,12,0) -> 87079209555 | L12: =VLOOKUP(A12,Реестр_Договоров,4,0) -> MX4000002R0001517 | M12: =VLOOKUP(L12,ПРИЦЕПЫ,11,0) -> 002-2513E50Q13-OK | N12: =VLOOKUP(L12,ПРИЦЕПЫ,2,0) -> Прицеп 2,5*1,25 м (до 750 кг.) | O12: =VLOOKUP(L12,ПРИЦЕПЫ,10,0) -> 1 ось | P12: =YEAR(VLOOKUP(L12,ПРИЦЕПЫ,7,0)) -> 2024 | Q12: =VLOOKUP(M12,матрица,16,0) -> 3650*1700*1070 | R12: =VLOOKUP(M12,матрица,17,0) -> 2500*1250*500 | S12: =VLOOKUP(O12,ОТТС!$A$2:$B$3,2,0) -> ТС KZ Е-KZ.0317.00251 от 28.02.2023 | T12: 380000 | U12: =VLOOKUP(L12,ПРИЦЕПЫ,9,0) -> Алматы
A13: 1172 | B13: =VLOOKUP(A13,'Реестр договоров'!$A$2:$D$80,2,0) -> 45461 | C13: =VLOOKUP(A13,Реестр_Договоров,3,0) -> Меньшиков | D13: =VLOOKUP(C13,Покупатели,2,0) -> Андрей | E13: =VLOOKUP(C13,Покупатели,3,0) -> Геннадьевич | F13: =VLOOKUP(C13,Покупатели,4,0) -> б/н | G13: =VLOOKUP(F13,Покупатели!$F$2:$N$762,2,0) -> 45461 | H13: =VLOOKUP(F13,Покупатели!$F$2:$N$762,3,0) -> МВД РК | I13: =VLOOKUP(C13,Покупатели!$C$2:$M$805,7,0) -> 911205300562 | J13: =IFERROR(__xludf.DUMMYFUNCTION("JOIN("" "", VLOOKUP(C13,Покупатели,8,0),VLOOKUP(C13,Покупатели,9,0),VLOOKUP(C13,Покупатели,10,0),VLOOKUP(C13,Покупатели,11,0))"),"Алматинская область Талдыкурган нет нет") -> Алматинская область Талдыкурган нет нет | K13: =VLOOKUP(C13,Покупатели,12,0) -> нет | L13: =VLOOKUP(A13,Реестр_Договоров,4,0) -> MX4000002R0001538 | M13: =VLOOKUP(L13,ПРИЦЕПЫ,11,0) -> 002-2013E30Q13-OK | N13: =VLOOKUP(L13,ПРИЦЕПЫ,2,0) -> Прицеп 2,0*1,25 м (до 750 кг.) | O13: =VLOOKUP(L13,ПРИЦЕПЫ,10,0) -> 1 ось | P13: =YEAR(VLOOKUP(L13,ПРИЦЕПЫ,7,0)) -> 2024 | Q13: =VLOOKUP(M13,матрица,16,0) -> 3150*1700*900 | R13: =VLOOKUP(M13,матрица,17,0) -> 2000*1250*300 | S13: =VLOOKUP(O13,ОТТС!$A$2:$B$3,2,0) -> ТС KZ Е-KZ.0317.00251 от 28.02.2023 | T13: 380000 | U13: =VLOOKUP(L13,ПРИЦЕПЫ,9,0) -> Алматы
A14: 1173 | B14: =VLOOKUP(A14,'Реестр договоров'!$A$2:$D$120,2,0) -> 45462 | C14: =VLOOKUP(A14,Реестр_Договоров,3,0) -> Билочук | D14: =VLOOKUP(C14,Покупатели,2,0) -> Игорь | E14: =VLOOKUP(C14,Покупатели,3,0) -> Владимирович | F14: =VLOOKUP(C14,Покупатели,4,0) -> 042054030 | G14: =VLOOKUP(F14,Покупатели!$F$2:$N$762,2,0) -> 42709 | H14: =VLOOKUP(F14,Покупатели!$F$2:$N$762,3,0) -> МВД РК | I14: =VLOOKUP(C14,Покупатели!$C$2:$M$805,7,0) -> 001128551373 | J14: =IFERROR(__xludf.DUMMYFUNCTION("JOIN("" "", VLOOKUP(C14,Покупатели,8,0),VLOOKUP(C14,Покупатели,9,0),VLOOKUP(C14,Покупатели,10,0),VLOOKUP(C14,Покупатели,11,0))"),"Акмолинская область с.Астраханка Маяковского 2/2") -> Акмолинская область с.Астраханка Маяковского 2/2 | K14: =VLOOKUP(C14,Покупатели,12,0) -> 87057433768 | L14: =VLOOKUP(A14,Реестр_Договоров,4,0) -> MX4000002R0001653 | M14: =VLOOKUP(L14,ПРИЦЕПЫ,11,0) -> 002-2013E30Q13-OK | N14: =VLOOKUP(L14,ПРИЦЕПЫ,2,0) -> Прицеп 2,0*1,25 м (до 750 кг.) | O14: =VLOOKUP(L14,ПРИЦЕПЫ,10,0) -> 1 ось | P14: =YEAR(VLOOKUP(L14,ПРИЦЕПЫ,7,0)) -> 2024 | Q14: =VLOOKUP(M14,матрица,16,0) -> 3150*1700*900 | R14: =VLOOKUP(M14,матрица,17,0) -> 2000*1250*300 | S14: =VLOOKUP(O14,ОТТС!$A$2:$B$3,2,0) -> ТС KZ Е-KZ.0317.00251 от 28.02.2023 | T14: 360000 | U14: =VLOOKUP(L14,ПРИЦЕПЫ,9,0) -> Астана
A15: 1174 | B15: =VLOOKUP(A15,'Реестр договоров'!$A$2:$D$55,2,0) -> 45463 | C15: =VLOOKUP(A15,Реестр_Договоров,3,0) -> Ягминас | D15: =VLOOKUP(C15,Покупатели,2,0) -> Андрей | E15: =VLOOKUP(C15,Покупатели,3,0) -> Николаевич | F15: =VLOOKUP(C15,Покупатели,4,0) -> 047758074 | G15: =VLOOKUP(F15,Покупатели!$F$2:$N$762,2,0) -> 43965 | H15: =VLOOKUP(F15,Покупатели!$F$2:$N$762,3,0) -> МВД РК | I15: =VLOOKUP(C15,Покупатели!$C$2:$M$805,7,0) -> 850321351214 | J15: =IFERROR(__xludf.DUMMYFUNCTION("JOIN("" "", VLOOKUP(C15,Покупатели,8,0),VLOOKUP(C15,Покупатели,9,0),VLOOKUP(C15,Покупатели,10,0),VLOOKUP(C15,Покупатели,11,0))"),"Астана район Байконыр ул.Коксенгир д.12 кв.2") -> Астана район Байконыр ул.Коксенгир д.12 кв.2 | K15: =VLOOKUP(C15,Покупатели,12,0) -> 87073831806 | L15: =VLOOKUP(A15,Реестр_Договоров,4,0) -> MX4000002R0001654 | M15: =VLOOKUP(L15,ПРИЦЕПЫ,11,0) -> 002-2013E50Q13-OK | N15: =VLOOKUP(L15,ПРИЦЕПЫ,2,0) -> Прицеп 2,0*1,25 м (до 750 кг.) | O15: =VLOOKUP(L15,ПРИЦЕПЫ,10,0) -> 1 ось | P15: =YEAR(VLOOKUP(L15,ПРИЦЕПЫ,7,0)) -> 2024 | Q15: =VLOOKUP(M15,матрица,16,0) -> 3150*1700*1070 | R15: =VLOOKUP(M15,матрица,17,0) -> 2000*1250*500 | S15: =VLOOKUP(O15,ОТТС!$A$2:$B$3,2,0) -> ТС KZ Е-KZ.0317.00251 от 28.02.2023 | T15: 340000 | U15: =VLOOKUP(L15,ПРИЦЕПЫ,9,0) -> Астана
A16: 1175 | B16: =VLOOKUP(A16,'Реестр договоров'!$A$2:$D$55,2,0) -> 45464 | C16: =VLOOKUP(A16,Реестр_Договоров,3,0) -> Костюков1 | D16: =VLOOKUP(C16,Покупатели,2,0) -> Александр | E16: =VLOOKUP(C16,Покупатели,3,0) -> Дмитриевич | F16: =VLOOKUP(C16,Покупатели,4,0) -> 054358115 | G16: =VLOOKUP(F16,Покупатели!$F$2:$N$762,2,0) -> 45174 | H16: =VLOOKUP(F16,Покупатели!$F$2:$N$762,3,0) -> МВД РК | I16: =VLOOKUP(C16,Покупатели!$C$2:$M$805,7,0) -> 940702301406 | J16: =IFERROR(__xludf.DUMMYFUNCTION("JOIN("" "", VLOOKUP(C16,Покупатели,8,0),VLOOKUP(C16,Покупатели,9,0),VLOOKUP(C16,Покупатели,10,0),VLOOKUP(C16,Покупатели,11,0))"),"Алматинская область город Алматы мкр.Орбита 2 дом 18, кв.26") -> Алматинская область город Алматы мкр.Орбита 2 дом 18, кв.26 | K16: =VLOOKUP(C16,Покупатели,12,0) -> 87477894960 | L16: =VLOOKUP(A16,Реестр_Договоров,4,0) -> MX4000002R0001506 | M16: =VLOOKUP(L16,ПРИЦЕПЫ,11,0) -> 002-2513E30Q13-OK | N16: =VLOOKUP(L16,ПРИЦЕПЫ,2,0) -> Прицеп 2,5*1,25 м (до 750 кг.) | O16: =VLOOKUP(L16,ПРИЦЕПЫ,10,0) -> 1 ось | P16: =YEAR(VLOOKUP(L16,ПРИЦЕПЫ,7,0)) -> 2024 | Q16: =VLOOKUP(M16,матрица,16,0) -> 3650*1700*900 | R16: =VLOOKUP(M16,матрица,17,0) -> 2500*1250*300 | S16: =VLOOKUP(O16,ОТТС!$A$2:$B$3,2,0) -> ТС KZ Е-KZ.0317.00251 от 28.02.2023 | T16: 380000 | U16: =VLOOKUP(L16,ПРИЦЕПЫ,9,0) -> Алматы
A17: 1176 | B17: =VLOOKUP(A17,'Реестр договоров'!$A$2:$D$55,2,0) -> 45464 | C17: =VLOOKUP(A17,Реестр_Договоров,3,0) -> Байзаков | D17: =VLOOKUP(C17,Покупатели,2,0) -> Айбар | E17: =VLOOKUP(C17,Покупатели,3,0) -> Сайлауович | F17: =VLOOKUP(C17,Покупатели,4,0) -> 053400172 | G17: =VLOOKUP(F17,Покупатели!$F$2:$N$762,2,0) -> 44763 | H17: =VLOOKUP(F17,Покупатели!$F$2:$N$762,3,0) -> МВД РК | I17: =VLOOKUP(C17,Покупатели!$C$2:$M$805,7,0) -> 631102301472 | J17: =IFERROR(__xludf.DUMMYFUNCTION("JOIN("" "", VLOOKUP(C17,Покупатели,8,0),VLOOKUP(C17,Покупатели,9,0),VLOOKUP(C17,Покупатели,10,0),VLOOKUP(C17,Покупатели,11,0))"),"город Астана мкр. Шубары ул.Каратай Турысова 36") -> город Астана мкр. Шубары ул.Каратай Турысова 36 | K17: =VLOOKUP(C17,Покупатели,12,0) -> 87051000909 | L17: =VLOOKUP(A17,Реестр_Договоров,4,0) -> MX4000002R0001680 | M17: 002-2013E30Q13-OK30 | N17: =VLOOKUP(L17,ПРИЦЕПЫ,2,0) -> Прицеп 2,0*1,25 м (до 750 кг.) | O17: =VLOOKUP(L17,ПРИЦЕПЫ,10,0) -> 1 ось | P17: =YEAR(VLOOKUP(L17,ПРИЦЕПЫ,7,0)) -> 2024 | Q17: 3150*1700*900 | R17: 2000*1250*300 | S17: =VLOOKUP(O17,ОТТС!$A$2:$B$3,2,0) -> ТС KZ Е-KZ.0317.00251 от 28.02.2023 | T17: 350000 | U17: =VLOOKUP(L17,ПРИЦЕПЫ,9,0) -> Астана
A18: 1177 | B18: =VLOOKUP(A18,'Реестр договоров'!$A$2:$D$80,2,0) -> 45464 | C18: =VLOOKUP(A18,Реестр_Договоров,3,0) -> Оспанова | D18: =VLOOKUP(C18,Покупатели,2,0) -> Гульден | E18: =VLOOKUP(C18,Покупатели,3,0) -> Сериковна | F18: =VLOOKUP(C18,Покупатели,4,0) -> 050380494 | G18: =VLOOKUP(F18,Покупатели!$F$2:$N$762,2,0) -> 44321 | H18: =VLOOKUP(F18,Покупатели!$F$2:$N$762,3,0) -> МВД РК | I18: =VLOOKUP(C18,Покупатели!$C$2:$M$805,7,0) -> 860401450774 | J18: =IFERROR(__xludf.DUMMYFUNCTION("JOIN("" "", VLOOKUP(C18,Покупатели,8,0),VLOOKUP(C18,Покупатели,9,0),VLOOKUP(C18,Покупатели,10,0),VLOOKUP(C18,Покупатели,11,0))"),"город Астана район Алматы ул.Жансугурулы д.4/3 КВ.225") -> город Астана район Алматы ул.Жансугурулы д.4/3 КВ.225 | K18: =VLOOKUP(C18,Покупатели,12,0) -> 87078692966 | L18: =VLOOKUP(A18,Реестр_Договоров,4,0) -> MX4000002R0001497 | M18: =VLOOKUP(L18,ПРИЦЕПЫ,11,0) -> 002-2013E50Q13-OK | N18: =VLOOKUP(L18,ПРИЦЕПЫ,2,0) -> Прицеп 2,0*1,25 м (до 750 кг.) | O18: =VLOOKUP(L18,ПРИЦЕПЫ,10,0) -> 1 ось | P18: =YEAR(VLOOKUP(L18,ПРИЦЕПЫ,7,0)) -> 2024 | Q18: =VLOOKUP(M18,матрица,16,0) -> 3150*1700*1070 | R18: =VLOOKUP(M18,матрица,17,0) -> 2000*1250*500 | S18: =VLOOKUP(O18,ОТТС!$A$2:$B$3,2,0) -> ТС KZ Е-KZ.0317.00251 от 28.02.2023 | T18: 350000 | U18: =VLOOKUP(L18,ПРИЦЕПЫ,9,0) -> Астана
A19: 1178 | B19: =VLOOKUP(A19,'Реестр договоров'!$A$2:$D$55,2,0) -> 45464 | C19: =VLOOKUP(A19,Реестр_Договоров,3,0) -> Шапарев | D19: =VLOOKUP(C19,Покупатели,2,0) -> Антон | E19: =VLOOKUP(C19,Покупатели,3,0) -> Витальевич | F19: =VLOOKUP(C19,Покупатели,4,0) -> 056014519 | G19: =VLOOKUP(F19,Покупатели!$F$2:$N$762,2,0) -> 45379 | H19: =VLOOKUP(F19,Покупатели!$F$2:$N$762,3,0) -> МЮ РК | I19: =VLOOKUP(C19,Покупатели!$C$2:$M$805,7,0) -> 890806301201 | J19: =IFERROR(__xludf.DUMMYFUNCTION("JOIN("" "", VLOOKUP(C19,Покупатели,8,0),VLOOKUP(C19,Покупатели,9,0),VLOOKUP(C19,Покупатели,10,0),VLOOKUP(C19,Покупатели,11,0))"),"Алматинская область Илийский район, село Мухаметжан Туймебаев ПКСТ Ардагер-Ветеран, 21 линия 41") -> Алматинская область Илийский район, село Мухаметжан Туймебаев ПКСТ Ардагер-Ветеран, 21 линия 41 | K19: =VLOOKUP(C19,Покупатели,12,0) -> 87772906865 | L19: =VLOOKUP(A19,Реестр_Договоров,4,0) -> MX4000002R0001516 | M19: =VLOOKUP(L19,ПРИЦЕПЫ,11,0) -> 002-2513E50Q13-OK | N19: =VLOOKUP(L19,ПРИЦЕПЫ,2,0) -> Прицеп 2,5*1,25 м (до 750 кг.) | O19: =VLOOKUP(L19,ПРИЦЕПЫ,10,0) -> 1 ось | P19: =YEAR(VLOOKUP(L19,ПРИЦЕПЫ,7,0)) -> 2024 | Q19: =VLOOKUP(M19,матрица,16,0) -> 3650*1700*1070 | R19: =VLOOKUP(M19,матрица,17,0) -> 2500*1250*500 | S19: =VLOOKUP(O19,ОТТС!$A$2:$B$3,2,0) -> ТС KZ Е-KZ.0317.00251 от 28.02.2023 | T19: 380000 | U19: =VLOOKUP(L19,ПРИЦЕПЫ,9,0) -> Алматы
A20: 1179 | B20: =VLOOKUP(A20,'Реестр договоров'!$A$2:$D$89,2,0) -> 45464 | C20: =VLOOKUP(A20,Реестр_Договоров,3,0) -> Бикенова | D20: =VLOOKUP(C20,Покупатели,2,0) -> Анаргуль | E20: =VLOOKUP(C20,Покупатели,3,0) -> Косымбековна | F20: =VLOOKUP(C20,Покупатели,4,0) -> 048906928 | G20: =VLOOKUP(F20,Покупатели!$F$2:$N$762,2,0) -> 44105 | H20: =VLOOKUP(F20,Покупатели!$F$2:$N$762,3,0) -> МВД РК | I20: =VLOOKUP(C20,Покупатели!$C$2:$M$805,7,0) -> 700312400633 | J20: =IFERROR(__xludf.DUMMYFUNCTION("JOIN("" "", VLOOKUP(C20,Покупатели,8,0),VLOOKUP(C20,Покупатели,9,0),VLOOKUP(C20,Покупатели,10,0),VLOOKUP(C20,Покупатели,11,0))"),"Акмолинская область Зерендинский район, с. Конысбай Габдуллина 33") -> Акмолинская область Зерендинский район, с. Конысбай Габдуллина 33 | K20: =VLOOKUP(C20,Покупатели,12,0) -> 87087496491 | L20: =VLOOKUP(A20,Реестр_Договоров,4,0) -> MX4000002R0001643 | M20: =VLOOKUP(L20,ПРИЦЕПЫ,11,0) -> 002-2513E50Q13-OK | N20: =VLOOKUP(L20,ПРИЦЕПЫ,2,0) -> Прицеп 2,5*1,25 м (до 750 кг.) | O20: =VLOOKUP(L20,ПРИЦЕПЫ,10,0) -> 1 ось | P20: =YEAR(VLOOKUP(L20,ПРИЦЕПЫ,7,0)) -> 2024 | Q20: =VLOOKUP(M20,матрица,16,0) -> 3650*1700*1070 | R20: =VLOOKUP(M20,матрица,17,0) -> 2500*1250*500 | S20: =VLOOKUP(O20,ОТТС!$A$2:$B$3,2,0) -> ТС KZ Е-KZ.0317.00251 от 28.02.2023 | T20: 330000 | U20: =VLOOKUP(L20,ПРИЦЕПЫ,9,0) -> Кокшетау
A21: 1180 | B21: =VLOOKUP(A21,'Реестр договоров'!$A$2:$D$80,2,0) -> 45464 | C21: =VLOOKUP(A21,Реестр_Договоров,3,0) -> Боровиков | D21: =VLOOKUP(C21,Покупатели,2,0) -> Александр | E21: =VLOOKUP(C21,Покупатели,3,0) -> Викторович | F21: =VLOOKUP(C21,Покупатели,4,0) -> 049617497 | G21: =VLOOKUP(F21,Покупатели!$F$2:$N$762,2,0) -> 44529 | H21: =VLOOKUP(F21,Покупатели!$F$2:$N$762,3,0) -> МВД РК | I21: =VLOOKUP(C21,Покупатели!$C$2:$M$805,7,0) -> 860706300175 | J21: =IFERROR(__xludf.DUMMYFUNCTION("JOIN("" "", VLOOKUP(C21,Покупатели,8,0),VLOOKUP(C21,Покупатели,9,0),VLOOKUP(C21,Покупатели,10,0),VLOOKUP(C21,Покупатели,11,0))"),"г.Алматы мкр.Рахат ул.Шагала 3/1") -> г.Алматы мкр.Рахат ул.Шагала 3/1 | K21: =VLOOKUP(C21,Покупатели,12,0) -> 87080070078 | L21: =VLOOKUP(A21,Реестр_Договоров,4,0) -> MX4000002R0001521 | M21: =VLOOKUP(L21,ПРИЦЕПЫ,11,0) -> 002-2513E30Q13-OK | N21: =VLOOKUP(L21,ПРИЦЕПЫ,2,0) -> Прицеп 2,5*1,25 м (до 750 кг.) | O21: =VLOOKUP(L21,ПРИЦЕПЫ,10,0) -> 1 ось | P21: =YEAR(VLOOKUP(L21,ПРИЦЕПЫ,7,0)) -> 2024 | Q21: =VLOOKUP(M21,матрица,16,0) -> 3650*1700*900 | R21: =VLOOKUP(M21,матрица,17,0) -> 2500*1250*300 | S21: =VLOOKUP(O21,ОТТС!$A$2:$B$3,2,0) -> ТС KZ Е-KZ.0317.00251 от 28.02.2023 | T21: 380000 | U21: =VLOOKUP(L21,ПРИЦЕПЫ,9,0) -> Алматы
A22: 1181 | B22: =VLOOKUP(A22,'Реестр договоров'!$A$2:$D$506,2,0) -> 45465 | C22: =VLOOKUP(A22,Реестр_Договоров,3,0) -> Гаврилюк | D22: =VLOOKUP(C22,Покупатели,2,0) -> Артем | E22: =VLOOKUP(C22,Покупатели,3,0) -> Алексеевич | F22: =VLOOKUP(C22,Покупатели,4,0) -> 050735465 | G22: =VLOOKUP(F22,Покупатели!$F$2:$N$762,2,0) -> 44700 | H22: =VLOOKUP(F22,Покупатели!$F$2:$N$762,3,0) -> МЮ РК | I22: =VLOOKUP(C22,Покупатели!$C$2:$M$805,7,0) -> 841214350939 | J22: =IFERROR(__xludf.DUMMYFUNCTION("JOIN("" "", VLOOKUP(C22,Покупатели,8,0),VLOOKUP(C22,Покупатели,9,0),VLOOKUP(C22,Покупатели,10,0),VLOOKUP(C22,Покупатели,11,0))"),"Жамбульская область с.Кордай ул.Рыскулова 214") -> Жамбульская область с.Кордай ул.Рыскулова 214 | K22: =VLOOKUP(C22,Покупатели,12,0) -> 87776674530 | L22: =VLOOKUP(A22,Реестр_Договоров,4,0) -> MX4000002R0001572 | M22: =VLOOKUP(L22,ПРИЦЕПЫ,11,0) -> 002-2013E50Q13-OK | N22: =VLOOKUP(L22,ПРИЦЕПЫ,2,0) -> Прицеп 2,0*1,25 м (до 750 кг.) | O22: =VLOOKUP(L22,ПРИЦЕПЫ,10,0) -> 1 ось | P22: =YEAR(VLOOKUP(L22,ПРИЦЕПЫ,7,0)) -> 2024 | Q22: =VLOOKUP(M22,матрица,16,0) -> 3150*1700*1070 | R22: =VLOOKUP(M22,матрица,17,0) -> 2000*1250*500 | S22: =VLOOKUP(O22,ОТТС!$A$2:$B$3,2,0) -> ТС KZ Е-KZ.0317.00251 от 28.02.2023 | T22: 320000 | U22: =VLOOKUP(L22,ПРИЦЕПЫ,9,0) -> Алматы
A23: 1182 | B23: =VLOOKUP(A23,'Реестр договоров'!$A$2:$D$80,2,0) -> 45465 | C23: =VLOOKUP(A23,Реестр_Договоров,3,0) -> Каримов | D23: =VLOOKUP(C23,Покупатели,2,0) -> Нуршат | E23: =VLOOKUP(C23,Покупатели,3,0) -> Каримович | F23: =VLOOKUP(C23,Покупатели,4,0) -> 053045761 | G23: =VLOOKUP(F23,Покупатели!$F$2:$N$762,2,0) -> 45021 | H23: =VLOOKUP(F23,Покупатели!$F$2:$N$762,3,0) -> МВД РК | I23: =VLOOKUP(C23,Покупатели!$C$2:$M$805,7,0) -> 900926301536 | J23: =IFERROR(__xludf.DUMMYFUNCTION("JOIN("" "", VLOOKUP(C23,Покупатели,8,0),VLOOKUP(C23,Покупатели,9,0),VLOOKUP(C23,Покупатели,10,0),VLOOKUP(C23,Покупатели,11,0))"),"Алматы Горный гигант Сызганова 89") -> Алматы Горный гигант Сызганова 89 | K23: =VLOOKUP(C23,Покупатели,12,0) -> 87001990026 | L23: =VLOOKUP(A23,Реестр_Договоров,4,0) -> MX4000002R0001481 | M23: =VLOOKUP(L23,ПРИЦЕПЫ,11,0) -> 002-2013E50Q13-OK | N23: =VLOOKUP(L23,ПРИЦЕПЫ,2,0) -> Прицеп 2,0*1,25 м (до 750 кг.) | O23: =VLOOKUP(L23,ПРИЦЕПЫ,10,0) -> 1 ось | P23: =YEAR(VLOOKUP(L23,ПРИЦЕПЫ,7,0)) -> 2024 | Q23: =VLOOKUP(M23,матрица,16,0) -> 3150*1700*1070 | R23: =VLOOKUP(M23,матрица,17,0) -> 2000*1250*500 | S23: =VLOOKUP(O23,ОТТС!$A$2:$B$3,2,0) -> ТС KZ Е-KZ.0317.00251 от 28.02.2023 | T23: 380000 | U23: =VLOOKUP(L23,ПРИЦЕПЫ,9,0) -> Алматы
A24: 1183 | B24: =VLOOKUP(A24,'Реестр договоров'!$A$2:$D$80,2,0) -> 45465 | C24: =VLOOKUP(A24,Реестр_Договоров,3,0) -> Базимов | D24: =VLOOKUP(C24,Покупатели,2,0) -> Адил | E24: =VLOOKUP(C24,Покупатели,3,0) -> Джапаркулович | F24: =VLOOKUP(C24,Покупатели,4,0) -> 052723263 | G24: =VLOOKUP(F24,Покупатели!$F$2:$N$762,2,0) -> 44973 | H24: =VLOOKUP(F24,Покупатели!$F$2:$N$762,3,0) -> МВД РК | I24: =VLOOKUP(C24,Покупатели!$C$2:$M$805,7,0) -> 680120303087 | J24: =IFERROR(__xludf.DUMMYFUNCTION("JOIN("" "", VLOOKUP(C24,Покупатели,8,0),VLOOKUP(C24,Покупатели,9,0),VLOOKUP(C24,Покупатели,10,0),VLOOKUP(C24,Покупатели,11,0))"),"Жамбыльская область Кордайский район, с.Кордай ул.Кордайская 27") -> Жамбыльская область Кордайский район, с.Кордай ул.Кордайская 27 | K24: =VLOOKUP(C24,Покупатели,12,0) -> 87024803772 | L24: =VLOOKUP(A24,Реестр_Договоров,4,0) -> MX4000002R0001569 | M24: =VLOOKUP(L24,ПРИЦЕПЫ,11,0) -> 002-2013E50Q13-OK | N24: =VLOOKUP(L24,ПРИЦЕПЫ,2,0) -> Прицеп 2,0*1,25 м (до 750 кг.) | O24: =VLOOKUP(L24,ПРИЦЕПЫ,10,0) -> 1 ось | P24: =YEAR(VLOOKUP(L24,ПРИЦЕПЫ,7,0)) -> 2024 | Q24: =VLOOKUP(M24,матрица,16,0) -> 3150*1700*1070 | R24: =VLOOKUP(M24,матрица,17,0) -> 2000*1250*500 | S24: =VLOOKUP(O24,ОТТС!$A$2:$B$3,2,0) -> ТС KZ Е-KZ.0317.00251 от 28.02.2023 | T24: 340000 | U24: =VLOOKUP(L24,ПРИЦЕПЫ,9,0) -> Алматы
A25: 1184 | B25: =VLOOKUP(A25,'Реестр договоров'!$A$2:$D$169,2,0) -> 45465 | C25: =VLOOKUP(A25,Реестр_Договоров,3,0) -> Жунусов1 | D25: =VLOOKUP(C25,Покупатели,2,0) -> Жетписбай | E25: =VLOOKUP(C25,Покупатели,3,0) -> Серикбаевич | F25: =VLOOKUP(C25,Покупатели,4,0) -> 023553247 | G25: =VLOOKUP(F25,Покупатели!$F$2:$N$762,2,0) -> 39925 | H25: =VLOOKUP(F25,Покупатели!$F$2:$N$762,3,0) -> МЮ РК | I25: =VLOOKUP(C25,Покупатели!$C$2:$M$805,7,0) -> 820101351532 | J25: =IFERROR(__xludf.DUMMYFUNCTION("JOIN("" "", VLOOKUP(C25,Покупатели,8,0),VLOOKUP(C25,Покупатели,9,0),VLOOKUP(C25,Покупатели,10,0),VLOOKUP(C25,Покупатели,11,0))"),"Алматинская область Жамбылский район, пос.Танбалтас ул.Мусабаева 12/1") -> Алматинская область Жамбылский район, пос.Танбалтас ул.Мусабаева 12/1 | K25: =VLOOKUP(C25,Покупатели,12,0) -> 87718997482 | L25: =VLOOKUP(A25,Реестр_Договоров,4,0) -> MX4000002R0001500 | M25: =VLOOKUP(L25,ПРИЦЕПЫ,11,0) -> 002-2013E30Q13-OK | N25: =VLOOKUP(L25,ПРИЦЕПЫ,2,0) -> Прицеп 2,0*1,25 м (до 750 кг.) | O25: =VLOOKUP(L25,ПРИЦЕПЫ,10,0) -> 1 ось | P25: =YEAR(VLOOKUP(L25,ПРИЦЕПЫ,7,0)) -> 2024 | Q25: =VLOOKUP(M25,матрица,16,0) -> 3150*1700*900 | R25: =VLOOKUP(M25,матрица,17,0) -> 2000*1250*300 | S25: =VLOOKUP(O25,ОТТС!$A$2:$B$3,2,0) -> ТС KZ Е-KZ.0317.00251 от 28.02.2023 | T25: 360000 | U25: =VLOOKUP(L25,ПРИЦЕПЫ,9,0) -> Алматы
A26: 1185 | B26: =VLOOKUP(A26,'Реестр договоров'!$A$2:$D$89,2,0) -> 45465 | C26: =VLOOKUP(A26,Реестр_Договоров,3,0) -> Бирюков | D26: =VLOOKUP(C26,Покупатели,2,0) -> Александр | E26: =VLOOKUP(C26,Покупатели,3,0) -> Анатольевич | F26: =VLOOKUP(C26,Покупатели,4,0) -> 017772142 | G26: =VLOOKUP(F26,Покупатели!$F$2:$N$762,2,0) -> 38498 | H26: =VLOOKUP(F26,Покупатели!$F$2:$N$762,3,0) -> МЮ РК | I26: =VLOOKUP(C26,Покупатели!$C$2:$M$805,7,0) -> 800223300337 | J26: =IFERROR(__xludf.DUMMYFUNCTION("JOIN("" "", VLOOKUP(C26,Покупатели,8,0),VLOOKUP(C26,Покупатели,9,0),VLOOKUP(C26,Покупатели,10,0),VLOOKUP(C26,Покупатели,11,0))"),"Алматинская область г.Алматы ул.Верди дом.29") -> Алматинская область г.Алматы ул.Верди дом.29 | K26: =VLOOKUP(C26,Покупатели,12,0) -> 87077370165 | L26: =VLOOKUP(A26,Реестр_Договоров,4,0) -> MX4000002R0001571 | M26: =VLOOKUP(L26,ПРИЦЕПЫ,11,0) -> 002-2013E50Q13-OK | N26: =VLOOKUP(L26,ПРИЦЕПЫ,2,0) -> Прицеп 2,0*1,25 м (до 750 кг.) | O26: =VLOOKUP(L26,ПРИЦЕПЫ,10,0) -> 1 ось | P26: =YEAR(VLOOKUP(L26,ПРИЦЕПЫ,7,0)) -> 2024 | Q26: =VLOOKUP(M26,матрица,16,0) -> 3150*1700*1070 | R26: =VLOOKUP(M26,матрица,17,0) -> 2000*1250*500 | S26: =VLOOKUP(O26,ОТТС!$A$2:$B$3,2,0) -> ТС KZ Е-KZ.0317.00251 от 28.02.2023 | T26: 320000 | U26: =VLOOKUP(L26,ПРИЦЕПЫ,9,0) -> Алматы
A27: 1186 | B27: =VLOOKUP(A27,'Реестр договоров'!$A$2:$D$89,2,0) -> 45467 | C27: =VLOOKUP(A27,Реестр_Договоров,3,0) -> Сейдахмет | D27: =VLOOKUP(C27,Покупатели,2,0) -> Әнуар | E27: =VLOOKUP(C27,Покупатели,3,0) -> Талғатұлы | F27: =VLOOKUP(C27,Покупатели,4,0) -> 054382555 | G27: =VLOOKUP(F27,Покупатели!$F$2:$N$762,2,0) -> 45175 | H27: =VLOOKUP(F27,Покупатели!$F$2:$N$762,3,0) -> ҚР ІІМ | I27: =VLOOKUP(C27,Покупатели!$C$2:$M$805,7,0) -> 020904500596 | J27: =IFERROR(__xludf.DUMMYFUNCTION("JOIN("" "", VLOOKUP(C27,Покупатели,8,0),VLOOKUP(C27,Покупатели,9,0),VLOOKUP(C27,Покупатели,10,0),VLOOKUP(C27,Покупатели,11,0))"),"Жетысу обл. Кербулатский р-н, с.Караагаш ул.Алдабергенова д.6/1") -> Жетысу обл. Кербулатский р-н, с.Караагаш ул.Алдабергенова д.6/1 | K27: =VLOOKUP(C27,Покупатели,12,0) -> 87760777676 | L27: =VLOOKUP(A27,Реестр_Договоров,4,0) -> MX4000002R0001507 | M27: =VLOOKUP(L27,ПРИЦЕПЫ,11,0) -> 002-2513E30Q13-OK | N27: =VLOOKUP(L27,ПРИЦЕПЫ,2,0) -> Прицеп 2,5*1,25 м (до 750 кг.) | O27: =VLOOKUP(L27,ПРИЦЕПЫ,10,0) -> 1 ось | P27: =YEAR(VLOOKUP(L27,ПРИЦЕПЫ,7,0)) -> 2024 | Q27: =VLOOKUP(M27,матрица,16,0) -> 3650*1700*900 | R27: =VLOOKUP(M27,матрица,17,0) -> 2500*1250*300 | S27: =VLOOKUP(O27,ОТТС!$A$2:$B$3,2,0) -> ТС KZ Е-KZ.0317.00251 от 28.02.2023 | T27: 360000 | U27: =VLOOKUP(L27,ПРИЦЕПЫ,9,0) -> Алматы
A28: 1187 | B28: =VLOOKUP(A28,'Реестр договоров'!$A$2:$D$55,2,0) -> 45467 | C28: =VLOOKUP(A28,Реестр_Договоров,3,0) -> Некерев | D28: =VLOOKUP(C28,Покупатели,2,0) -> Николай | E28: =VLOOKUP(C28,Покупатели,3,0) -> Егорович | F28: =VLOOKUP(C28,Покупатели,4,0) -> 055134561 | G28: =VLOOKUP(F28,Покупатели!$F$2:$N$762,2,0) -> 45275 | H28: =VLOOKUP(F28,Покупатели!$F$2:$N$762,3,0) -> МВД РК | I28: =VLOOKUP(C28,Покупатели!$C$2:$M$805,7,0) -> 900123301035 | J28: =IFERROR(__xludf.DUMMYFUNCTION("JOIN("" "", VLOOKUP(C28,Покупатели,8,0),VLOOKUP(C28,Покупатели,9,0),VLOOKUP(C28,Покупатели,10,0),VLOOKUP(C28,Покупатели,11,0))"),"г.Алматы Турксибский р-н ул.Приозерная д.8") -> г.Алматы Турксибский р-н ул.Приозерная д.8 | K28: =VLOOKUP(C28,Покупатели,12,0) -> 87478169748 | L28: =VLOOKUP(A28,Реестр_Договоров,4,0) -> MX4000002R0001468 | M28: =VLOOKUP(L28,ПРИЦЕПЫ,11,0) -> 002-2013E50Q13-OK | N28: =VLOOKUP(L28,ПРИЦЕПЫ,2,0) -> Прицеп 2,0*1,25 м (до 750 кг.) | O28: =VLOOKUP(L28,ПРИЦЕПЫ,10,0) -> 1 ось | P28: =YEAR(VLOOKUP(L28,ПРИЦЕПЫ,7,0)) -> 2024 | Q28: =VLOOKUP(M28,матрица,16,0) -> 3150*1700*1070 | R28: =VLOOKUP(M28,матрица,17,0) -> 2000*1250*500 | S28: =VLOOKUP(O28,ОТТС!$A$2:$B$3,2,0) -> ТС KZ Е-KZ.0317.00251 от 28.02.2023 | T28: 430000 | U28: =VLOOKUP(L28,ПРИЦЕПЫ,9,0) -> Алматы
A29: 1188 | B29: =VLOOKUP(A29,'Реестр договоров'!$A$2:$D$55,2,0) -> 45467 | C29: =VLOOKUP(A29,Реестр_Договоров,3,0) -> Мещеряков | D29: =VLOOKUP(C29,Покупатели,2,0) -> Денис | E29: =VLOOKUP(C29,Покупатели,3,0) -> Николаевич | F29: =VLOOKUP(C29,Покупатели,4,0) -> 047611726 | G29: =VLOOKUP(F29,Покупатели!$F$2:$N$762,2,0) -> 43900 | H29: =VLOOKUP(F29,Покупатели!$F$2:$N$762,3,0) -> МВД РК | I29: =VLOOKUP(C29,Покупатели!$C$2:$M$805,7,0) -> 850129351220 | J29: =IFERROR(__xludf.DUMMYFUNCTION("JOIN("" "", VLOOKUP(C29,Покупатели,8,0),VLOOKUP(C29,Покупатели,9,0),VLOOKUP(C29,Покупатели,10,0),VLOOKUP(C29,Покупатели,11,0))"),"Акмолинская обл. г.Кокшетау ул.Ауезова д.213б кв.135") -> Акмолинская обл. г.Кокшетау ул.Ауезова д.213б кв.135 | K29: =VLOOKUP(C29,Покупатели,12,0) -> 87076566662 | L29: =VLOOKUP(A29,Реестр_Договоров,4,0) -> MX4000002R0001664 | M29: =VLOOKUP(L29,ПРИЦЕПЫ,11,0) -> 002-2013E50Q13-OK | N29: =VLOOKUP(L29,ПРИЦЕПЫ,2,0) -> Прицеп 2,0*1,25 м (до 750 кг.) | O29: =VLOOKUP(L29,ПРИЦЕПЫ,10,0) -> 1 ось | P29: =YEAR(VLOOKUP(L29,ПРИЦЕПЫ,7,0)) -> 2024 | Q29: =VLOOKUP(M29,матрица,16,0) -> 3150*1700*1070 | R29: =VLOOKUP(M29,матрица,17,0) -> 2000*1250*500 | S29: =VLOOKUP(O29,ОТТС!$A$2:$B$3,2,0) -> ТС KZ Е-KZ.0317.00251 от 28.02.2023 | T29: 320000 | U29: =VLOOKUP(L29,ПРИЦЕПЫ,9,0) -> Кокшетау
A30: 1189 | B30: =VLOOKUP(A30,'Реестр договоров'!$A$2:$D$55,2,0) -> 45467 | C30: =VLOOKUP(A30,Реестр_Договоров,3,0) -> Айтимов 1 | D30: =VLOOKUP(C30,Покупатели,2,0) -> Адилбек | E30: =VLOOKUP(C30,Покупатели,3,0) -> Исламбекович | F30: =VLOOKUP(C30,Покупатели,4,0) -> 039407719 | G30: =VLOOKUP(F30,Покупатели!$F$2:$N$762,2,0) -> 45467 | H30: =VLOOKUP(F30,Покупатели!$F$2:$N$762,3,0) -> МВД РК | I30: =VLOOKUP(C30,Покупатели!$C$2:$M$805,7,0) -> 830101305796 | J30: =IFERROR(__xludf.DUMMYFUNCTION("JOIN("" "", VLOOKUP(C30,Покупатели,8,0),VLOOKUP(C30,Покупатели,9,0),VLOOKUP(C30,Покупатели,10,0),VLOOKUP(C30,Покупатели,11,0))"),"Алматинская обл. Жамбылский район, г.Узынагаш ул. Парасат 13") -> Алматинская обл. Жамбылский район, г.Узынагаш ул. Парасат 13 | K30: =VLOOKUP(C30,Покупатели,12,0) -> 87477779783 | L30: =VLOOKUP(A30,Реестр_Договоров,4,0) -> MX4000002R0001462 | M30: =VLOOKUP(L30,ПРИЦЕПЫ,11,0) -> 002-2013E50Q13-OK | N30: =VLOOKUP(L30,ПРИЦЕПЫ,2,0) -> Прицеп 2,0*1,25 м (до 750 кг.) | O30: =VLOOKUP(L30,ПРИЦЕПЫ,10,0) -> 1 ось | P30: =YEAR(VLOOKUP(L30,ПРИЦЕПЫ,7,0)) -> 2024 | Q30: =VLOOKUP(M30,матрица,16,0) -> 3150*1700*1070 | R30: =VLOOKUP(M30,матрица,17,0) -> 2000*1250*500 | S30: =VLOOKUP(O30,ОТТС!$A$2:$B$3,2,0) -> ТС KZ Е-KZ.0317.00251 от 28.02.2023 | T30: 380000 | U30: =VLOOKUP(L30,ПРИЦЕПЫ,9,0) -> Алматы
A31: 1190 | B31: =VLOOKUP(A31,'Реестр договоров'!$A$2:$D$80,2,0) -> 45467 | C31: =VLOOKUP(A31,Реестр_Договоров,3,0) -> Сабитова | D31: =VLOOKUP(C31,Покупатели,2,0) -> Гульден | E31: =VLOOKUP(C31,Покупатели,3,0) -> Еспембетовна | F31: =VLOOKUP(C31,Покупатели,4,0) -> 018351765 | G31: =VLOOKUP(F31,Покупатели!$F$2:$N$762,2,0) -> 38621 | H31: =VLOOKUP(F31,Покупатели!$F$2:$N$762,3,0) -> МЮ РК | I31: =VLOOKUP(C31,Покупатели!$C$2:$M$805,7,0) -> 800319400632 | J31: =IFERROR(__xludf.DUMMYFUNCTION("JOIN("" "", VLOOKUP(C31,Покупатели,8,0),VLOOKUP(C31,Покупатели,9,0),VLOOKUP(C31,Покупатели,10,0),VLOOKUP(C31,Покупатели,11,0))"),"г. Астана р-н Алматы мкр. Юго-Восток, ул.Кенгир 16") -> г. Астана р-н Алматы мкр. Юго-Восток, ул.Кенгир 16 | K31: =VLOOKUP(C31,Покупатели,12,0) -> 87015141701 | L31: =VLOOKUP(A31,Реестр_Договоров,4,0) -> MX4000002R0001687 | M31: =VLOOKUP(L31,ПРИЦЕПЫ,11,0) -> 002-2013E50Q13-OK | N31: =VLOOKUP(L31,ПРИЦЕПЫ,2,0) -> Прицеп 2,0*1,25 м (до 750 кг.) | O31: =VLOOKUP(L31,ПРИЦЕПЫ,10,0) -> 1 ось | P31: =YEAR(VLOOKUP(L31,ПРИЦЕПЫ,7,0)) -> 2024 | Q31: =VLOOKUP(M31,матрица,16,0) -> 3150*1700*1070 | R31: =VLOOKUP(M31,матрица,17,0) -> 2000*1250*500 | S31: =VLOOKUP(O31,ОТТС!$A$2:$B$3,2,0) -> ТС KZ Е-KZ.0317.00251 от 28.02.2023 | T31: 380000 | U31: =VLOOKUP(L31,ПРИЦЕПЫ,9,0) -> Астана
A32: 1191 | B32: =VLOOKUP(A32,'Реестр договоров'!$A$2:$D$100,2,0) -> 45468 | C32: =VLOOKUP(A32,Реестр_Договоров,3,0) -> Тарбаков | D32: =VLOOKUP(C32,Покупатели,2,0) -> Дулат | E32: =VLOOKUP(C32,Покупатели,3,0) -> Жумабекович | F32: =VLOOKUP(C32,Покупатели,4,0) -> 048136170 | G32: =VLOOKUP(F32,Покупатели!$F$2:$N$762,2,0) -> 44008 | H32: =VLOOKUP(F32,Покупатели!$F$2:$N$762,3,0) -> МВД РК | I32: =VLOOKUP(C32,Покупатели!$C$2:$M$805,7,0) -> 650525350342 | J32: =IFERROR(__xludf.DUMMYFUNCTION("JOIN("" "", VLOOKUP(C32,Покупатели,8,0),VLOOKUP(C32,Покупатели,9,0),VLOOKUP(C32,Покупатели,10,0),VLOOKUP(C32,Покупатели,11,0))"),"Северо-Казахстанская область г.Тайынша ул.Астана 96") -> Северо-Казахстанская область г.Тайынша ул.Астана 96 | K32: =VLOOKUP(C32,Покупатели,12,0) -> 87011703270 | L32: =VLOOKUP(A32,Реестр_Договоров,4,0) -> MX4000002R0001698 | M32: =VLOOKUP(L32,ПРИЦЕПЫ,11,0) -> 002-2013E50Q13-OK | N32: =VLOOKUP(L32,ПРИЦЕПЫ,2,0) -> Прицеп 2,0*1,25 м (до 750 кг.) | O32: =VLOOKUP(L32,ПРИЦЕПЫ,10,0) -> 1 ось | P32: =YEAR(VLOOKUP(L32,ПРИЦЕПЫ,7,0)) -> 2024 | Q32: =VLOOKUP(M32,матрица,16,0) -> 3150*1700*1070 | R32: =VLOOKUP(M32,матрица,17,0) -> 2000*1250*500 | S32: =VLOOKUP(O32,ОТТС!$A$2:$B$3,2,0) -> ТС KZ Е-KZ.0317.00251 от 28.02.2023 | T32: 374000 | U32: =VLOOKUP(L32,ПРИЦЕПЫ,9,0) -> Кокшетау
A33: 1192 | B33: =VLOOKUP(A33,'Реестр договоров'!$A$2:$D$100,2,0) -> 45468 | C33: =VLOOKUP(A33,Реестр_Договоров,3,0) -> Широков | D33: =VLOOKUP(C33,Покупатели,2,0) -> Виктор | E33: =VLOOKUP(C33,Покупатели,3,0) -> Викторович | F33: =VLOOKUP(C33,Покупатели,4,0) -> 051982733 | G33: =VLOOKUP(F33,Покупатели!$F$2:$N$762,2,0) -> 44865 | H33: =VLOOKUP(F33,Покупатели!$F$2:$N$762,3,0) -> ҚР ІІМ | I33: =VLOOKUP(C33,Покупатели!$C$2:$M$805,7,0) -> 870716300280 | J33: =IFERROR(__xludf.DUMMYFUNCTION("JOIN("" "", VLOOKUP(C33,Покупатели,8,0),VLOOKUP(C33,Покупатели,9,0),VLOOKUP(C33,Покупатели,10,0),VLOOKUP(C33,Покупатели,11,0))"),"Алматинская обл. Енбекшиказахский район, Рахатский с.о., с.Орікті ул.Жетісу д.10A") -> Алматинская обл. Енбекшиказахский район, Рахатский с.о., с.Орікті ул.Жетісу д.10A | K33: =VLOOKUP(C33,Покупатели,12,0) -> 8777999600 | L33: =VLOOKUP(A33,Реестр_Договоров,4,0) -> MX4000002R0001519 | M33: =VLOOKUP(L33,ПРИЦЕПЫ,11,0) -> 002-2513E50Q13-OK | N33: =VLOOKUP(L33,ПРИЦЕПЫ,2,0) -> Прицеп 2,5*1,25 м (до 750 кг.) | O33: =VLOOKUP(L33,ПРИЦЕПЫ,10,0) -> 1 ось | P33: =YEAR(VLOOKUP(L33,ПРИЦЕПЫ,7,0)) -> 2024 | Q33: =VLOOKUP(M33,матрица,16,0) -> 3650*1700*1070 | R33: =VLOOKUP(M33,матрица,17,0) -> 2500*1250*500 | S33: =VLOOKUP(O33,ОТТС!$A$2:$B$3,2,0) -> ТС KZ Е-KZ.0317.00251 от 28.02.2023 | T33: 360000 | U33: =VLOOKUP(L33,ПРИЦЕПЫ,9,0) -> Алматы
A34: 1193 | B34: =VLOOKUP(A34,'Реестр договоров'!$A$2:$D$89,2,0) -> 45468 | C34: =VLOOKUP(A34,Реестр_Договоров,3,0) -> Каналимов | D34: =VLOOKUP(C34,Покупатели,2,0) -> Ермек | E34: =VLOOKUP(C34,Покупатели,3,0) -> Хасмзадович | F34: =VLOOKUP(C34,Покупатели,4,0) -> 037898794 | G34: =VLOOKUP(F34,Покупатели!$F$2:$N$762,2,0) -> 42016 | H34: =VLOOKUP(F34,Покупатели!$F$2:$N$762,3,0) -> МВД РК | I34: =VLOOKUP(C34,Покупатели!$C$2:$M$805,7,0) -> 610731300286 | J34: =IFERROR(__xludf.DUMMYFUNCTION("JOIN("" "", VLOOKUP(C34,Покупатели,8,0),VLOOKUP(C34,Покупатели,9,0),VLOOKUP(C34,Покупатели,10,0),VLOOKUP(C34,Покупатели,11,0))"),"г.Астана р-н Сарыарка ул. Айдархана Турлыбаева 6") -> г.Астана р-н Сарыарка ул. Айдархана Турлыбаева 6 | K34: =VLOOKUP(C34,Покупатели,12,0) -> 87014360348 | L34: =VLOOKUP(A34,Реестр_Договоров,4,0) -> MX4000002R0001650 | M34: =VLOOKUP(L34,ПРИЦЕПЫ,11,0) -> 002-2013E50Q13-OK | N34: =VLOOKUP(L34,ПРИЦЕПЫ,2,0) -> Прицеп 2,0*1,25 м (до 750 кг.) | O34: =VLOOKUP(L34,ПРИЦЕПЫ,10,0) -> 1 ось | P34: =YEAR(VLOOKUP(L34,ПРИЦЕПЫ,7,0)) -> 2024 | Q34: =VLOOKUP(M34,матрица,16,0) -> 3150*1700*1070 | R34: =VLOOKUP(M34,матрица,17,0) -> 2000*1250*500 | S34: =VLOOKUP(O34,ОТТС!$A$2:$B$3,2,0) -> ТС KZ Е-KZ.0317.00251 от 28.02.2023 | T34: 320000 | U34: =VLOOKUP(L34,ПРИЦЕПЫ,9,0) -> Астана
A35: 1194 | B35: =VLOOKUP(A35,'Реестр договоров'!$A$2:$D$55,2,0) -> 45468 | C35: =VLOOKUP(A35,Реестр_Договоров,3,0) -> Аргинбаев | D35: =VLOOKUP(C35,Покупатели,2,0) -> Куандык | E35: =VLOOKUP(C35,Покупатели,3,0) -> Кадырович | F35: =VLOOKUP(C35,Покупатели,4,0) -> 051050784 | G35: =VLOOKUP(F35,Покупатели!$F$2:$N$762,2,0) -> 44421 | H35: =VLOOKUP(F35,Покупатели!$F$2:$N$762,3,0) -> МВД РК | I35: =VLOOKUP(C35,Покупатели!$C$2:$M$805,7,0) -> 700907300849 | J35: =IFERROR(__xludf.DUMMYFUNCTION("JOIN("" "", VLOOKUP(C35,Покупатели,8,0),VLOOKUP(C35,Покупатели,9,0),VLOOKUP(C35,Покупатели,10,0),VLOOKUP(C35,Покупатели,11,0))"),"Акмолинская область Целиноградский район ул.Алькей Маргулана 59/4") -> Акмолинская область Целиноградский район ул.Алькей Маргулана 59/4 | K35: =VLOOKUP(C35,Покупатели,12,0) -> 87761510777 | L35: =VLOOKUP(A35,Реестр_Договоров,4,0) -> MX4000002R0001666 | M35: =VLOOKUP(L35,ПРИЦЕПЫ,11,0) -> 002-2013E30Q13-OK | N35: =VLOOKUP(L35,ПРИЦЕПЫ,2,0) -> Прицеп 2,0*1,25 м (до 750 кг.) | O35: =VLOOKUP(L35,ПРИЦЕПЫ,10,0) -> 1 ось | P35: =YEAR(VLOOKUP(L35,ПРИЦЕПЫ,7,0)) -> 2024 | Q35: =VLOOKUP(M35,матрица,16,0) -> 3150*1700*900 | R35: =VLOOKUP(M35,матрица,17,0) -> 2000*1250*300 | S35: =VLOOKUP(O35,ОТТС!$A$2:$B$3,2,0) -> ТС KZ Е-KZ.0317.00251 от 28.02.2023 | T35: 380000 | U35: =VLOOKUP(L35,ПРИЦЕПЫ,9,0) -> Астана
A36: 1195 | B36: =VLOOKUP(A36,'Реестр договоров'!$A$2:$D$55,2,0) -> 45468 | C36: =VLOOKUP(A36,Реестр_Договоров,3,0) -> Юлдабаева | D36: =VLOOKUP(C36,Покупатели,2,0) -> Диана | E36: =VLOOKUP(C36,Покупатели,3,0) -> Рафаильевна | F36: =VLOOKUP(C36,Покупатели,4,0) -> 049032417 | G36: =VLOOKUP(F36,Покупатели!$F$2:$N$762,2,0) -> 44432 | H36: =VLOOKUP(F36,Покупатели!$F$2:$N$762,3,0) -> МВД РК | I36: =VLOOKUP(C36,Покупатели!$C$2:$M$805,7,0) -> 950120401094 | J36: =IFERROR(__xludf.DUMMYFUNCTION("JOIN("" "", VLOOKUP(C36,Покупатели,8,0),VLOOKUP(C36,Покупатели,9,0),VLOOKUP(C36,Покупатели,10,0),VLOOKUP(C36,Покупатели,11,0))"),"г.Алматы Наурызбайский район Тау Самалы 4") -> г.Алматы Наурызбайский район Тау Самалы 4 | K36: =VLOOKUP(C36,Покупатели,12,0) -> 87474803452 | L36: =VLOOKUP(A36,Реестр_Договоров,4,0) -> MX4000002R0001459 | M36: =VLOOKUP(L36,ПРИЦЕПЫ,11,0) -> 002-2013E50Q13-OK | N36: =VLOOKUP(L36,ПРИЦЕПЫ,2,0) -> Прицеп 2,0*1,25 м (до 750 кг.) | O36: =VLOOKUP(L36,ПРИЦЕПЫ,10,0) -> 1 ось | P36: =YEAR(VLOOKUP(L36,ПРИЦЕПЫ,7,0)) -> 2024 | Q36: =VLOOKUP(M36,матрица,16,0) -> 3150*1700*1070 | R36: =VLOOKUP(M36,матрица,17,0) -> 2000*1250*500 | S36: =VLOOKUP(O36,ОТТС!$A$2:$B$3,2,0) -> ТС KZ Е-KZ.0317.00251 от 28.02.2023 | T36: 360000 | U36: =VLOOKUP(L36,ПРИЦЕПЫ,9,0) -> Астана
A37: 1196 | B37: =VLOOKUP(A37,'Реестр договоров'!$A$2:$D$89,2,0) -> 45468 | C37: =VLOOKUP(A37,Реестр_Договоров,3,0) -> Харламова 2 | D37: =VLOOKUP(C37,Покупатели,2,0) -> Никита | E37: =VLOOKUP(C37,Покупатели,3,0) -> Владимирович | F37: =VLOOKUP(C37,Покупатели,4,0) -> 050683269 | G37: =VLOOKUP(F37,Покупатели!$F$2:$N$762,2,0) -> 44692 | H37: =VLOOKUP(F37,Покупатели!$F$2:$N$762,3,0) -> МВД РК | I37: =VLOOKUP(C37,Покупатели!$C$2:$M$805,7,0) -> 870301301351 | J37: =IFERROR(__xludf.DUMMYFUNCTION("JOIN("" "", VLOOKUP(C37,Покупатели,8,0),VLOOKUP(C37,Покупатели,9,0),VLOOKUP(C37,Покупатели,10,0),VLOOKUP(C37,Покупатели,11,0))"),"г.Алматы Мкр. №8 д.1 кв.56") -> г.Алматы Мкр. №8 д.1 кв.56 | K37: =VLOOKUP(C37,Покупатели,12,0) -> 87018878757 | L37: =VLOOKUP(A37,Реестр_Договоров,4,0) -> MX4000002R0001634 | M37: =VLOOKUP(L37,ПРИЦЕПЫ,11,0) -> 002-2513E50Q13-OK | N37: =VLOOKUP(L37,ПРИЦЕПЫ,2,0) -> Прицеп 2,5*1,25 м (до 750 кг.) | O37: =VLOOKUP(L37,ПРИЦЕПЫ,10,0) -> 1 ось | P37: =YEAR(VLOOKUP(L37,ПРИЦЕПЫ,7,0)) -> 2024 | Q37: =VLOOKUP(M37,матрица,16,0) -> 3650*1700*1070 | R37: =VLOOKUP(M37,матрица,17,0) -> 2500*1250*500 | S37: =VLOOKUP(O37,ОТТС!$A$2:$B$3,2,0) -> ТС KZ Е-KZ.0317.00251 от 28.02.2023 | T37: 360000 | U37: =VLOOKUP(L37,ПРИЦЕПЫ,9,0) -> Алматы
A38: 1197 | B38: =VLOOKUP(A38,'Реестр договоров'!$A$2:$D$55,2,0) -> 45468 | C38: =VLOOKUP(A38,Реестр_Договоров,3,0) -> Берекетов | D38: =VLOOKUP(C38,Покупатели,2,0) -> Надим | E38: =VLOOKUP(C38,Покупатели,3,0) -> Койшыбекович | F38: =VLOOKUP(C38,Покупатели,4,0) -> 037554479 | G38: =VLOOKUP(F38,Покупатели!$F$2:$N$762,2,0) -> 42044 | H38: =VLOOKUP(F38,Покупатели!$F$2:$N$762,3,0) -> МВД РК | I38: =VLOOKUP(C38,Покупатели!$C$2:$M$805,7,0) -> 820113301251 | J38: =IFERROR(__xludf.DUMMYFUNCTION("JOIN("" "", VLOOKUP(C38,Покупатели,8,0),VLOOKUP(C38,Покупатели,9,0),VLOOKUP(C38,Покупатели,10,0),VLOOKUP(C38,Покупатели,11,0))"),"Алматинская обл. г.Кунаев ул.Дзержинского д.15, кв.5") -> Алматинская обл. г.Кунаев ул.Дзержинского д.15, кв.5 | K38: =VLOOKUP(C38,Покупатели,12,0) -> 87477873429 | L38: =VLOOKUP(A38,Реестр_Договоров,4,0) -> MX4000002R0001482 | M38: =VLOOKUP(L38,ПРИЦЕПЫ,11,0) -> 002-2013E30Q13-OK | N38: =VLOOKUP(L38,ПРИЦЕПЫ,2,0) -> Прицеп 2,0*1,25 м (до 750 кг.) | O38: =VLOOKUP(L38,ПРИЦЕПЫ,10,0) -> 1 ось | P38: =YEAR(VLOOKUP(L38,ПРИЦЕПЫ,7,0)) -> 2024 | Q38: =VLOOKUP(M38,матрица,16,0) -> 3150*1700*900 | R38: =VLOOKUP(M38,матрица,17,0) -> 2000*1250*300 | S38: =VLOOKUP(O38,ОТТС!$A$2:$B$3,2,0) -> ТС KZ Е-KZ.0317.00251 от 28.02.2023 | T38: =VLOOKUP(M38,матрица,15,0) -> 320000 | U38: =VLOOKUP(L38,ПРИЦЕПЫ,9,0) -> Алматы
A39: 1198 | B39: =VLOOKUP(A39,'Реестр договоров'!$A$2:$D$55,2,0) -> 45468 | C39: =VLOOKUP(A39,Реестр_Договоров,3,0) -> Мухамбетов | D39: =VLOOKUP(C39,Покупатели,2,0) -> Аскербек | E39: =VLOOKUP(C39,Покупатели,3,0) -> Кайрбаевич | F39: =VLOOKUP(C39,Покупатели,4,0) -> 051841732 | G39: =VLOOKUP(F39,Покупатели!$F$2:$N$762,2,0) -> 44550 | H39: =VLOOKUP(F39,Покупатели!$F$2:$N$762,3,0) -> МВД РК | I39: =VLOOKUP(C39,Покупатели!$C$2:$M$805,7,0) -> 731214301452 | J39: =IFERROR(__xludf.DUMMYFUNCTION("JOIN("" "", VLOOKUP(C39,Покупатели,8,0),VLOOKUP(C39,Покупатели,9,0),VLOOKUP(C39,Покупатели,10,0),VLOOKUP(C39,Покупатели,11,0))"),"Акмолинская обл. Целиноградский р-н, с.Караоткель ул.Ауезова 23") -> Акмолинская обл. Целиноградский р-н, с.Караоткель ул.Ауезова 23 | K39: =VLOOKUP(C39,Покупатели,12,0) -> 87750940527 | L39: =VLOOKUP(A39,Реестр_Договоров,4,0) -> MX4000002P0001445 | M39: =VLOOKUP(L39,ПРИЦЕПЫ,11,0) -> 002-2513E30Q13-OK | N39: =VLOOKUP(L39,ПРИЦЕПЫ,2,0) -> Прицеп 2,5*1,25 м (до 750 кг.) | O39: =VLOOKUP(L39,ПРИЦЕПЫ,10,0) -> 1 ось | P39: =YEAR(VLOOKUP(L39,ПРИЦЕПЫ,7,0)) -> 2024 | Q39: =VLOOKUP(M39,матрица,16,0) -> 3650*1700*900 | R39: =VLOOKUP(M39,матрица,17,0) -> 2500*1250*300 | S39: =VLOOKUP(O39,ОТТС!$A$2:$B$3,2,0) -> ТС KZ Е-KZ.0317.00251 от 28.02.2023 | T39: 430000 | U39: =VLOOKUP(L39,ПРИЦЕПЫ,9,0) -> Астана
A40: 1199 | B40: =VLOOKUP(A40,'Реестр договоров'!$A$2:$D$55,2,0) -> 45469 | C40: =VLOOKUP(A40,Реестр_Договоров,3,0) -> Асанов 1 | D40: =VLOOKUP(C40,Покупатели,2,0) -> Роман | E40: =VLOOKUP(C40,Покупатели,3,0) -> Борисович | F40: =VLOOKUP(C40,Покупатели,4,0) -> 048558697 | G40: =VLOOKUP(F40,Покупатели!$F$2:$N$762,2,0) -> 44354 | H40: =VLOOKUP(F40,Покупатели!$F$2:$N$762,3,0) -> МВД РК | I40: =VLOOKUP(C40,Покупатели!$C$2:$M$805,7,0) -> 820613300221 | J40: =IFERROR(__xludf.DUMMYFUNCTION("JOIN("" "", VLOOKUP(C40,Покупатели,8,0),VLOOKUP(C40,Покупатели,9,0),VLOOKUP(C40,Покупатели,10,0),VLOOKUP(C40,Покупатели,11,0))"),"Алматинская обл. г.Алматы ул.Потанина 400 корпус 1") -> Алматинская обл. г.Алматы ул.Потанина 400 корпус 1 | K40: =VLOOKUP(C40,Покупатели,12,0) -> 87054672383 | L40: =VLOOKUP(A40,Реестр_Договоров,4,0) -> MX4000002R0001503 | M40: =VLOOKUP(L40,ПРИЦЕПЫ,11,0) -> 002-2513E30Q13-OK | N40: =VLOOKUP(L40,ПРИЦЕПЫ,2,0) -> Прицеп 2,5*1,25 м (до 750 кг.) | O40: =VLOOKUP(L40,ПРИЦЕПЫ,10,0) -> 1 ось | P40: =YEAR(VLOOKUP(L40,ПРИЦЕПЫ,7,0)) -> 2024 | Q40: =VLOOKUP(M40,матрица,16,0) -> 3650*1700*900 | R40: =VLOOKUP(M40,матрица,17,0) -> 2500*1250*300 | S40: =VLOOKUP(O40,ОТТС!$A$2:$B$3,2,0) -> ТС KZ Е-KZ.0317.00251 от 28.02.2023 | T40: 430000 | U40: =VLOOKUP(L40,ПРИЦЕПЫ,9,0) -> Алматы
A41: 1200 | B41: =VLOOKUP(A41,'Реестр договоров'!$A$2:$D$55,2,0) -> 45469 | C41: =VLOOKUP(A41,Реестр_Договоров,3,0) -> Серикбек | D41: =VLOOKUP(C41,Покупатели,2,0) -> Еркебулан | E41: =VLOOKUP(C41,Покупатели,3,0) -> нет | F41: =VLOOKUP(C41,Покупатели,4,0) -> 049999592 | G41: =VLOOKUP(F41,Покупатели!$F$2:$N$762,2,0) -> 44267 | H41: =VLOOKUP(F41,Покупатели!$F$2:$N$762,3,0) -> МВД РК | I41: =VLOOKUP(C41,Покупатели!$C$2:$M$805,7,0) -> 890818399047 | J41: =IFERROR(__xludf.DUMMYFUNCTION("JOIN("" "", VLOOKUP(C41,Покупатели,8,0),VLOOKUP(C41,Покупатели,9,0),VLOOKUP(C41,Покупатели,10,0),VLOOKUP(C41,Покупатели,11,0))"),"Карагандинская обл. Оскааровский р-н ул.Караганды 59") -> Карагандинская обл. Оскааровский р-н ул.Караганды 59 | K41: =VLOOKUP(C41,Покупатели,12,0) -> 87755938926 | L41: =VLOOKUP(A41,Реестр_Договоров,4,0) -> MX4000004N0000934 | M41: =VLOOKUP(L41,ПРИЦЕПЫ,11,0) -> 004-2515E30Q13-OK | N41: =VLOOKUP(L41,ПРИЦЕПЫ,2,0) -> Прицеп 2,5*1,5 м (до 750 кг.) | O41: =VLOOKUP(L41,ПРИЦЕПЫ,10,0) -> 2 оси | P41: =YEAR(VLOOKUP(L41,ПРИЦЕПЫ,7,0)) -> 2022 | Q41: =VLOOKUP(M41,матрица,16,0) -> 3650*1950*900 | R41: =VLOOKUP(M41,матрица,17,0) -> 4000*1500*300 | S41: =VLOOKUP(O41,ОТТС!$A$2:$B$3,2,0) -> ТС KZ Е-KZ.0317.00219.П1 от 17.07.2025 | T41: 430000 | U41: =VLOOKUP(L41,ПРИЦЕПЫ,9,0) -> Астана
A42: 1201 | B42: =VLOOKUP(A42,'Реестр договоров'!$A$2:$D$55,2,0) -> 45469 | C42: =VLOOKUP(A42,Реестр_Договоров,3,0) -> Аубакиров | D42: =VLOOKUP(C42,Покупатели,2,0) -> Жаксыбек | E42: =VLOOKUP(C42,Покупатели,3,0) -> Солтанайұлы | F42: =VLOOKUP(C42,Покупатели,4,0) -> 039848815 | G42: =VLOOKUP(F42,Покупатели!$F$2:$N$762,2,0) -> 42432 | H42: =VLOOKUP(F42,Покупатели!$F$2:$N$762,3,0) -> ҚР ІІМ | I42: =VLOOKUP(C42,Покупатели!$C$2:$M$805,7,0) -> 910128401060 | J42: =IFERROR(__xludf.DUMMYFUNCTION("JOIN("" "", VLOOKUP(C42,Покупатели,8,0),VLOOKUP(C42,Покупатели,9,0),VLOOKUP(C42,Покупатели,10,0),VLOOKUP(C42,Покупатели,11,0))"),"Алматинская обл. Талгарский р-н, Нура ул. 8 Марта д.32 кв.1") -> Алматинская обл. Талгарский р-н, Нура ул. 8 Марта д.32 кв.1 | K42: =VLOOKUP(C42,Покупатели,12,0) -> 87010171101 | L42: =VLOOKUP(A42,Реестр_Договоров,4,0) -> MX4000002R0001483 | M42: =VLOOKUP(L42,ПРИЦЕПЫ,11,0) -> 002-2013E50Q13-OK | N42: =VLOOKUP(L42,ПРИЦЕПЫ,2,0) -> Прицеп 2,0*1,25 м (до 750 кг.) | O42: =VLOOKUP(L42,ПРИЦЕПЫ,10,0) -> 1 ось | P42: =YEAR(VLOOKUP(L42,ПРИЦЕПЫ,7,0)) -> 2024 | Q42: =VLOOKUP(M42,матрица,16,0) -> 3150*1700*1070 | R42: =VLOOKUP(M42,матрица,17,0) -> 2000*1250*500 | S42: =VLOOKUP(O42,ОТТС!$A$2:$B$3,2,0) -> ТС KZ Е-KZ.0317.00251 от 28.02.2023 | T42: 430000 | U42: =VLOOKUP(L42,ПРИЦЕПЫ,9,0) -> Алматы
A43: 1202 | B43: =VLOOKUP(A43,'Реестр договоров'!$A$2:$D$80,2,0) -> 45469 | C43: =VLOOKUP(A43,Реестр_Договоров,3,0) -> Новичихин | D43: =VLOOKUP(C43,Покупатели,2,0) -> Владимир | E43: =VLOOKUP(C43,Покупатели,3,0) -> Викторович | F43: =VLOOKUP(C43,Покупатели,4,0) -> 044971370 | G43: =VLOOKUP(F43,Покупатели!$F$2:$N$762,2,0) -> 43382 | H43: =VLOOKUP(F43,Покупатели!$F$2:$N$762,3,0) -> МВД РК | I43: =VLOOKUP(C43,Покупатели!$C$2:$M$805,7,0) -> 801218350775 | J43: =IFERROR(__xludf.DUMMYFUNCTION("JOIN("" "", VLOOKUP(C43,Покупатели,8,0),VLOOKUP(C43,Покупатели,9,0),VLOOKUP(C43,Покупатели,10,0),VLOOKUP(C43,Покупатели,11,0))"),"Акмолинская обл. г.Кокшетау ул.Сыздыкова 9") -> Акмолинская обл. г.Кокшетау ул.Сыздыкова 9 | K43: =VLOOKUP(C43,Покупатели,12,0) -> 87076277103 | L43: =VLOOKUP(A43,Реестр_Договоров,4,0) -> MX4000002R0001722 | M43: =VLOOKUP(L43,ПРИЦЕПЫ,11,0) -> 002-2013E50Q13-OK | N43: =VLOOKUP(L43,ПРИЦЕПЫ,2,0) -> Прицеп 2,0*1,25 м (до 750 кг.) | O43: =VLOOKUP(L43,ПРИЦЕПЫ,10,0) -> 1 ось | P43: =YEAR(VLOOKUP(L43,ПРИЦЕПЫ,7,0)) -> 2024 | Q43: =VLOOKUP(M43,матрица,16,0) -> 3150*1700*1070 | R43: =VLOOKUP(M43,матрица,17,0) -> 2000*1250*500 | S43: =VLOOKUP(O43,ОТТС!$A$2:$B$3,2,0) -> ТС KZ Е-KZ.0317.00251 от 28.02.2023 | T43: 380000 | U43: =VLOOKUP(L43,ПРИЦЕПЫ,9,0) -> Кокшетау
A44: 1203 | B44: =VLOOKUP(A44,'Реестр договоров'!$A$2:$D$55,2,0) -> 45469 | C44: =VLOOKUP(A44,Реестр_Договоров,3,0) -> Ахметов | D44: =VLOOKUP(C44,Покупатели,2,0) -> Бейбит | E44: =VLOOKUP(C44,Покупатели,3,0) -> Ерболович | F44: =VLOOKUP(C44,Покупатели,4,0) -> 037051895 | G44: =VLOOKUP(F44,Покупатели!$F$2:$N$762,2,0) -> 41912 | H44: =VLOOKUP(F44,Покупатели!$F$2:$N$762,3,0) -> МВД РК | I44: =VLOOKUP(C44,Покупатели!$C$2:$M$805,7,0) -> 800223302383 | J44: =IFERROR(__xludf.DUMMYFUNCTION("JOIN("" "", VLOOKUP(C44,Покупатели,8,0),VLOOKUP(C44,Покупатели,9,0),VLOOKUP(C44,Покупатели,10,0),VLOOKUP(C44,Покупатели,11,0))"),"область Жетысу г.Жаркент, с.Улкен шыган Сейфуллина 14") -> область Жетысу г.Жаркент, с.Улкен шыган Сейфуллина 14 | K44: =VLOOKUP(C44,Покупатели,12,0) -> 87016021980 | L44: =VLOOKUP(A44,Реестр_Договоров,4,0) -> MX4000002R0001638 | M44: =VLOOKUP(L44,ПРИЦЕПЫ,11,0) -> 002-2513E50Q13-OK | N44: =VLOOKUP(L44,ПРИЦЕПЫ,2,0) -> Прицеп 2,5*1,25 м (до 750 кг.) | O44: =VLOOKUP(L44,ПРИЦЕПЫ,10,0) -> 1 ось | P44: =YEAR(VLOOKUP(L44,ПРИЦЕПЫ,7,0)) -> 2024 | Q44: =VLOOKUP(M44,матрица,16,0) -> 3650*1700*1070 | R44: =VLOOKUP(M44,матрица,17,0) -> 2500*1250*500 | S44: =VLOOKUP(O44,ОТТС!$A$2:$B$3,2,0) -> ТС KZ Е-KZ.0317.00251 от 28.02.2023 | T44: =VLOOKUP(M44,матрица,15,0) -> 390000 | U44: =VLOOKUP(L44,ПРИЦЕПЫ,9,0) -> Алматы
A45: 1204 | B45: =VLOOKUP(A45,'Реестр договоров'!$A$2:$D$55,2,0) -> 45470 | C45: =VLOOKUP(A45,Реестр_Договоров,3,0) -> Юзликаев | D45: =VLOOKUP(C45,Покупатели,2,0) -> Артур | E45: =VLOOKUP(C45,Покупатели,3,0) -> Ильдарович | F45: =VLOOKUP(C45,Покупатели,4,0) -> 046657131 | G45: =VLOOKUP(F45,Покупатели!$F$2:$N$762,2,0) -> 44034 | H45: =VLOOKUP(F45,Покупатели!$F$2:$N$762,3,0) -> МВД РК | I45: =VLOOKUP(C45,Покупатели!$C$2:$M$805,7,0) -> 880424300255 | J45: =IFERROR(__xludf.DUMMYFUNCTION("JOIN("" "", VLOOKUP(C45,Покупатели,8,0),VLOOKUP(C45,Покупатели,9,0),VLOOKUP(C45,Покупатели,10,0),VLOOKUP(C45,Покупатели,11,0))"),"Алматинская область Карасайский район, пос.Жанатурмыс ул.Алтынсарина д.21") -> Алматинская область Карасайский район, пос.Жанатурмыс ул.Алтынсарина д.21 | K45: =VLOOKUP(C45,Покупатели,12,0) -> 87770334835 | L45: =VLOOKUP(A45,Реестр_Договоров,4,0) -> MX4000002R0001720 | M45: =VLOOKUP(L45,ПРИЦЕПЫ,11,0) -> 002-3515E30Q13-OK | N45: =VLOOKUP(L45,ПРИЦЕПЫ,2,0) -> Прицеп 3,5*1,5 м (до 750 кг.) | O45: =VLOOKUP(L45,ПРИЦЕПЫ,10,0) -> 1 ось | P45: =YEAR(VLOOKUP(L45,ПРИЦЕПЫ,7,0)) -> 2024 | Q45: =VLOOKUP(M45,матрица,16,0) -> 3800*1950*900 | R45: =VLOOKUP(M45,матрица,17,0) -> 3500*1500*300 | S45: =VLOOKUP(O45,ОТТС!$A$2:$B$3,2,0) -> ТС KZ Е-KZ.0317.00251 от 28.02.2023 | T45: 440000 | U45: =VLOOKUP(L45,ПРИЦЕПЫ,9,0) -> Алматы
A46: 1205 | B46: =VLOOKUP(A46,'Реестр договоров'!$A$2:$D$55,2,0) -> 45470 | C46: =VLOOKUP(A46,Реестр_Договоров,3,0) -> Сайранбек | D46: =VLOOKUP(C46,Покупатели,2,0) -> Гульзада | E46: =VLOOKUP(C46,Покупатели,3,0) -> 0 | F46: =VLOOKUP(C46,Покупатели,4,0) -> 053073062 | G46: =VLOOKUP(F46,Покупатели!$F$2:$N$762,2,0) -> 44727 | H46: =VLOOKUP(F46,Покупатели!$F$2:$N$762,3,0) -> МВД РК | I46: =VLOOKUP(C46,Покупатели!$C$2:$M$805,7,0) -> 960606451012 | J46: =IFERROR(__xludf.DUMMYFUNCTION("JOIN("" "", VLOOKUP(C46,Покупатели,8,0),VLOOKUP(C46,Покупатели,9,0),VLOOKUP(C46,Покупатели,10,0),VLOOKUP(C46,Покупатели,11,0))"),"г.Астана шамшыкалдаква 28 КВ 350 район Алматы Ш.Калдаякова д.28, кв.350") -> г.Астана шамшыкалдаква 28 КВ 350 район Алматы Ш.Калдаякова д.28, кв.350 | K46: =VLOOKUP(C46,Покупатели,12,0) -> 87007708568 | L46: =VLOOKUP(A46,Реестр_Договоров,4,0) -> MX4000004R0001721 | M46: =VLOOKUP(L46,ПРИЦЕПЫ,11,0) -> 004-3515E50Q13-OK150 | N46: =VLOOKUP(L46,ПРИЦЕПЫ,2,0) -> Прицеп 3,5*1,5 м (до 750 кг.) | O46: =VLOOKUP(L46,ПРИЦЕПЫ,10,0) -> 2 оси | P46: =YEAR(VLOOKUP(L46,ПРИЦЕПЫ,7,0)) -> 2024 | Q46: =VLOOKUP(M46,матрица,16,0) -> 0 | R46: =VLOOKUP(M46,матрица,17,0) -> 0 | S46: =VLOOKUP(O46,ОТТС!$A$2:$B$3,2,0) -> ТС KZ Е-KZ.0317.00219.П1 от 17.07.2025 | T46: 390000 | U46: =VLOOKUP(L46,ПРИЦЕПЫ,9,0) -> Кокшетау
A47: 1206 | B47: =VLOOKUP(A47,'Реестр договоров'!$A$2:$D$55,2,0) -> 45470 | C47: =VLOOKUP(A47,Реестр_Договоров,3,0) -> Гумарова | D47: =VLOOKUP(C47,Покупатели,2,0) -> Гаухар | E47: =VLOOKUP(C47,Покупатели,3,0) -> Наурызовна | F47: =VLOOKUP(C47,Покупатели,4,0) -> 022586181 | G47: =VLOOKUP(F47,Покупатели!$F$2:$N$762,2,0) -> 39749 | H47: =VLOOKUP(F47,Покупатели!$F$2:$N$762,3,0) -> МЮ РК | I47: =VLOOKUP(C47,Покупатели!$C$2:$M$805,7,0) -> 830921400323 | J47: =IFERROR(__xludf.DUMMYFUNCTION("JOIN("" "", VLOOKUP(C47,Покупатели,8,0),VLOOKUP(C47,Покупатели,9,0),VLOOKUP(C47,Покупатели,10,0),VLOOKUP(C47,Покупатели,11,0))"),"Акмолинская область Целиноградский район, с.Коянды учетный квартал 014") -> Акмолинская область Целиноградский район, с.Коянды учетный квартал 014 | K47: =VLOOKUP(C47,Покупатели,12,0) -> 87055176155 | L47: =VLOOKUP(A47,Реестр_Договоров,4,0) -> MX4000002R0001678 | M47: =VLOOKUP(L47,ПРИЦЕПЫ,11,0) -> 002-2013E50Q13-OK | N47: =VLOOKUP(L47,ПРИЦЕПЫ,2,0) -> Прицеп 2,0*1,25 м (до 750 кг.) | O47: =VLOOKUP(L47,ПРИЦЕПЫ,10,0) -> 1 ось | P47: =YEAR(VLOOKUP(L47,ПРИЦЕПЫ,7,0)) -> 2024 | Q47: =VLOOKUP(M47,матрица,16,0) -> 3150*1700*1070 | R47: =VLOOKUP(M47,матрица,17,0) -> 2000*1250*500 | S47: =VLOOKUP(O47,ОТТС!$A$2:$B$3,2,0) -> ТС KZ Е-KZ.0317.00251 от 28.02.2023 | T47: =VLOOKUP(M47,матрица,15,0) -> 340000 | U47: =VLOOKUP(L47,ПРИЦЕПЫ,9,0) -> Астана
A48: 1207 | B48: =VLOOKUP(A48,'Реестр договоров'!$A$2:$D$55,2,0) -> 45471 | C48: =VLOOKUP(A48,Реестр_Договоров,3,0) -> Курмангалиев | D48: =VLOOKUP(C48,Покупатели,2,0) -> Темиртас | E48: =VLOOKUP(C48,Покупатели,3,0) -> Тойкеевич | F48: =VLOOKUP(C48,Покупатели,4,0) -> 048426462 | G48: =VLOOKUP(F48,Покупатели!$F$2:$N$762,2,0) -> 44047 | H48: =VLOOKUP(F48,Покупатели!$F$2:$N$762,3,0) -> МВД РК | I48: =VLOOKUP(C48,Покупатели!$C$2:$M$805,7,0) -> 640729300115 | J48: =IFERROR(__xludf.DUMMYFUNCTION("JOIN("" "", VLOOKUP(C48,Покупатели,8,0),VLOOKUP(C48,Покупатели,9,0),VLOOKUP(C48,Покупатели,10,0),VLOOKUP(C48,Покупатели,11,0))"),"г.Астана р-н Сарыарка ул.Караменде би Шакаулы 64 ВП-4 ЖК Берекет") -> г.Астана р-н Сарыарка ул.Караменде би Шакаулы 64 ВП-4 ЖК Берекет | K48: =VLOOKUP(C48,Покупатели,12,0) -> 87785826900 | L48: =VLOOKUP(A48,Реестр_Договоров,4,0) -> MX4000002R0001656 | M48: =VLOOKUP(L48,ПРИЦЕПЫ,11,0) -> 002-2013E50Q13-OK | N48: =VLOOKUP(L48,ПРИЦЕПЫ,2,0) -> Прицеп 2,0*1,25 м (до 750 кг.) | O48: =VLOOKUP(L48,ПРИЦЕПЫ,10,0) -> 1 ось | P48: =YEAR(VLOOKUP(L48,ПРИЦЕПЫ,7,0)) -> 2024 | Q48: =VLOOKUP(M48,матрица,16,0) -> 3150*1700*1070 | R48: =VLOOKUP(M48,матрица,17,0) -> 2000*1250*500 | S48: =VLOOKUP(O48,ОТТС!$A$2:$B$3,2,0) -> ТС KZ Е-KZ.0317.00251 от 28.02.2023 | T48: 440000 | U48: =VLOOKUP(L48,ПРИЦЕПЫ,9,0) -> Астана
A49: 1208 | B49: =VLOOKUP(A49,'Реестр договоров'!$A$2:$D$55,2,0) -> 45471 | C49: =VLOOKUP(A49,Реестр_Договоров,3,0) -> Хусаинов1 | D49: =VLOOKUP(C49,Покупатели,2,0) -> Радмир | E49: =VLOOKUP(C49,Покупатели,3,0) -> Рашидович | F49: =VLOOKUP(C49,Покупатели,4,0) -> 050398837 | G49: =VLOOKUP(F49,Покупатели!$F$2:$N$762,2,0) -> 44652 | H49: =VLOOKUP(F49,Покупатели!$F$2:$N$762,3,0) -> МВД РК | I49: =VLOOKUP(C49,Покупатели!$C$2:$M$805,7,0) -> 870211300949 | J49: =IFERROR(__xludf.DUMMYFUNCTION("JOIN("" "", VLOOKUP(C49,Покупатели,8,0),VLOOKUP(C49,Покупатели,9,0),VLOOKUP(C49,Покупатели,10,0),VLOOKUP(C49,Покупатели,11,0))"),"Алматинская обл. Ескельдинский р-н, пос.Карабулак Ул.Лихачева Д.8 КВ.1") -> Алматинская обл. Ескельдинский р-н, пос.Карабулак Ул.Лихачева Д.8 КВ.1 | K49: =VLOOKUP(C49,Покупатели,12,0) -> 87051385679 | L49: =VLOOKUP(A49,Реестр_Договоров,4,0) -> MX4000002R0001464 | M49: =VLOOKUP(L49,ПРИЦЕПЫ,11,0) -> 002-2013E30Q13-OK | N49: =VLOOKUP(L49,ПРИЦЕПЫ,2,0) -> Прицеп 2,0*1,25 м (до 750 кг.) | O49: =VLOOKUP(L49,ПРИЦЕПЫ,10,0) -> 1 ось | P49: =YEAR(VLOOKUP(L49,ПРИЦЕПЫ,7,0)) -> 2024 | Q49: =VLOOKUP(M49,матрица,16,0) -> 3150*1700*900 | R49: =VLOOKUP(M49,матрица,17,0) -> 2000*1250*300 | S49: =VLOOKUP(O49,ОТТС!$A$2:$B$3,2,0) -> ТС KZ Е-KZ.0317.00251 от 28.02.2023 | T49: 430000 | U49: =VLOOKUP(L49,ПРИЦЕПЫ,9,0) -> Алматы
A50: 1209 | B50: =VLOOKUP(A50,'Реестр договоров'!$A$2:$D$55,2,0) -> 45471 | C50: =VLOOKUP(A50,Реестр_Договоров,3,0) -> Унгарбеков | D50: =VLOOKUP(C50,Покупатели,2,0) -> Думан | E50: =VLOOKUP(C50,Покупатели,3,0) -> Турдаханович | F50: =VLOOKUP(C50,Покупатели,4,0) -> 041753767 | G50: =VLOOKUP(C50,Покупатели,5,0) -> 42913 | H50: =VLOOKUP(F50,Покупатели!$F$2:$N$762,3,0) -> МВД РК | I50: =VLOOKUP(C50,Покупатели,7,0) -> 851019301704 | J50: =IFERROR(__xludf.DUMMYFUNCTION("JOIN("" "", VLOOKUP(C50,Покупатели,8,0),VLOOKUP(C50,Покупатели,9,0),VLOOKUP(C50,Покупатели,10,0),VLOOKUP(C50,Покупатели,11,0))"),"обл. Жетысу г. Жаркент, пос.Головацкий ул. Райымбек батыра д.8") -> обл. Жетысу г. Жаркент, пос.Головацкий ул. Райымбек батыра д.8 | K50: =VLOOKUP(C50,Покупатели,12,0) -> 87022914944 | L50: =VLOOKUP(A50,Реестр_Договоров,4,0) -> MX4000002R0001463 | M50: =VLOOKUP(L50,ПРИЦЕПЫ,11,0) -> 002-2013E50Q13-OK | N50: =VLOOKUP(L50,ПРИЦЕПЫ,2,0) -> Прицеп 2,0*1,25 м (до 750 кг.) | O50: =VLOOKUP(L50,ПРИЦЕПЫ,10,0) -> 1 ось | P50: =YEAR(VLOOKUP(L50,ПРИЦЕПЫ,7,0)) -> 2024 | Q50: =VLOOKUP(M50,матрица,16,0) -> 3150*1700*1070 | R50: =VLOOKUP(M50,матрица,17,0) -> 2000*1250*500 | S50: =VLOOKUP(O50,ОТТС!$A$2:$B$3,2,0) -> ТС KZ Е-KZ.0317.00251 от 28.02.2023 | T50: =VLOOKUP(M50,матрица,15,0) -> 340000 | U50: =VLOOKUP(L50,ПРИЦЕПЫ,9,0) -> Алматы
A51: 1210 | B51: =VLOOKUP(A51,'Реестр договоров'!$A$2:$D$55,2,0) -> 45474 | C51: =VLOOKUP(A51,Реестр_Договоров,3,0) -> Абдибеков | D51: =VLOOKUP(C51,Покупатели,2,0) -> Толеген | E51: =VLOOKUP(C51,Покупатели,3,0) -> Кудышович | F51: =VLOOKUP(C51,Покупатели,4,0) -> 054789131 | G51: =VLOOKUP(F51,Покупатели!$F$2:$N$762,2,0) -> 45233 | H51: =VLOOKUP(F51,Покупатели!$F$2:$N$762,3,0) -> МВД РК | I51: =VLOOKUP(C51,Покупатели!$C$2:$M$805,7,0) -> 540910300445 | J51: =IFERROR(__xludf.DUMMYFUNCTION("JOIN("" "", VLOOKUP(C51,Покупатели,8,0),VLOOKUP(C51,Покупатели,9,0),VLOOKUP(C51,Покупатели,10,0),VLOOKUP(C51,Покупатели,11,0))"),"Акмолинская обл. Сергеевский р-н, с.Кегень ул.Ш.Уалиханова 36") -> Акмолинская обл. Сергеевский р-н, с.Кегень ул.Ш.Уалиханова 36 | K51: =VLOOKUP(C51,Покупатели,12,0) -> 87058163108 | L51: =VLOOKUP(A51,Реестр_Договоров,4,0) -> MX4000002R0001633 | M51: =VLOOKUP(L51,ПРИЦЕПЫ,11,0) -> 002-2513E50Q13-OK | N51: =VLOOKUP(L51,ПРИЦЕПЫ,2,0) -> Прицеп 2,5*1,25 м (до 750 кг.) | O51: =VLOOKUP(L51,ПРИЦЕПЫ,10,0) -> 1 ось | P51: =YEAR(VLOOKUP(L51,ПРИЦЕПЫ,7,0)) -> 2024 | Q51: =VLOOKUP(M51,матрица,16,0) -> 3650*1700*1070 | R51: =VLOOKUP(M51,матрица,17,0) -> 2500*1250*500 | S51: =VLOOKUP(O51,ОТТС!$A$2:$B$3,2,0) -> ТС KZ Е-KZ.0317.00251 от 28.02.2023 | T51: 390000 | U51: =VLOOKUP(L51,ПРИЦЕПЫ,9,0) -> Кокшетау
A52: 1211 | B52: =VLOOKUP(A52,'Реестр договоров'!$A$2:$D$100,2,0) -> 45475 | C52: =VLOOKUP(A52,Реестр_Договоров,3,0) -> Дуйсеков | D52: =VLOOKUP(C52,Покупатели,2,0) -> Жумабек | E52: =VLOOKUP(C52,Покупатели,3,0) -> Сагынбаевич | F52: =VLOOKUP(C52,Покупатели,4,0) -> 047743091 | G52: =VLOOKUP(F52,Покупатели!$F$2:$N$762,2,0) -> 44221 | H52: =VLOOKUP(F52,Покупатели!$F$2:$N$762,3,0) -> МВД РК | I52: =VLOOKUP(C52,Покупатели!$C$2:$M$805,7,0) -> 690304302962 | J52: =IFERROR(__xludf.DUMMYFUNCTION("JOIN("" "", VLOOKUP(C52,Покупатели,8,0),VLOOKUP(C52,Покупатели,9,0),VLOOKUP(C52,Покупатели,10,0),VLOOKUP(C52,Покупатели,11,0))"),"Алматинская обл. Илийский р-н, с.Аксай, ПКСТ Кок Жиек, ул. 5-линия д.304А") -> Алматинская обл. Илийский р-н, с.Аксай, ПКСТ Кок Жиек, ул. 5-линия д.304А | K52: =VLOOKUP(C52,Покупатели,12,0) -> 87714089498 | L52: =VLOOKUP(A52,Реестр_Договоров,4,0) -> MX4000002R0001574 | M52: =VLOOKUP(L52,ПРИЦЕПЫ,11,0) -> 002-2013E50Q13-OK | N52: =VLOOKUP(L52,ПРИЦЕПЫ,2,0) -> Прицеп 2,0*1,25 м (до 750 кг.) | O52: =VLOOKUP(L52,ПРИЦЕПЫ,10,0) -> 1 ось | P52: =YEAR(VLOOKUP(L52,ПРИЦЕПЫ,7,0)) -> 2024 | Q52: =VLOOKUP(M52,матрица,16,0) -> 3150*1700*1070 | R52: =VLOOKUP(M52,матрица,17,0) -> 2000*1250*500 | S52: =VLOOKUP(O52,ОТТС!$A$2:$B$3,2,0) -> ТС KZ Е-KZ.0317.00251 от 28.02.2023 | T52: 320000 | U52: =VLOOKUP(L52,ПРИЦЕПЫ,9,0) -> Алматы
A53: 1212 | B53: =VLOOKUP(A53,'Реестр договоров'!$A$2:$D$80,2,0) -> 45475 | C53: =VLOOKUP(A53,Реестр_Договоров,3,0) -> Грабовский | D53: =VLOOKUP(C53,Покупатели,2,0) -> Павел | E53: =VLOOKUP(C53,Покупатели,3,0) -> Николаевич | F53: =VLOOKUP(C53,Покупатели,4,0) -> 054981954 | G53: =VLOOKUP(F53,Покупатели!$F$2:$N$762,2,0) -> 45015 | H53: =VLOOKUP(F53,Покупатели!$F$2:$N$762,3,0) -> МВД РК | I53: =VLOOKUP(C53,Покупатели!$C$2:$M$805,7,0) -> 680114350264 | J53: =IFERROR(__xludf.DUMMYFUNCTION("JOIN("" "", VLOOKUP(C53,Покупатели,8,0),VLOOKUP(C53,Покупатели,9,0),VLOOKUP(C53,Покупатели,10,0),VLOOKUP(C53,Покупатели,11,0))"),"Северо-Казахстанская обл. Тайыншинский р-н, с.Драгомировка ") -> Северо-Казахстанская обл. Тайыншинский р-н, с.Драгомировка | K53: =VLOOKUP(C53,Покупатели,12,0) -> 87713716005 | L53: =VLOOKUP(A53,Реестр_Договоров,4,0) -> MX4000002R0001663 | M53: =VLOOKUP(L53,ПРИЦЕПЫ,11,0) -> 002-2013E50Q13-OK | N53: =VLOOKUP(L53,ПРИЦЕПЫ,2,0) -> Прицеп 2,0*1,25 м (до 750 кг.) | O53: =VLOOKUP(L53,ПРИЦЕПЫ,10,0) -> 1 ось | P53: =YEAR(VLOOKUP(L53,ПРИЦЕПЫ,7,0)) -> 2024 | Q53: =VLOOKUP(M53,матрица,16,0) -> 3150*1700*1070 | R53: =VLOOKUP(M53,матрица,17,0) -> 2000*1250*500 | S53: =VLOOKUP(O53,ОТТС!$A$2:$B$3,2,0) -> ТС KZ Е-KZ.0317.00251 от 28.02.2023 | T53: 320000 | U53: =VLOOKUP(L53,ПРИЦЕПЫ,9,0) -> Кокшетау
A54: 1213 | B54: =VLOOKUP(A54,'Реестр договоров'!$A$2:$D$55,2,0) -> 45476 | C54: =VLOOKUP(A54,Реестр_Договоров,3,0) -> Пияшкин | D54: =VLOOKUP(C54,Покупатели,2,0) -> Николай | E54: =VLOOKUP(C54,Покупатели,3,0) -> Николаевич | F54: =VLOOKUP(C54,Покупатели,4,0) -> 017579341 | G54: =VLOOKUP(F54,Покупатели!$F$2:$N$762,2,0) -> 38544 | H54: =VLOOKUP(F54,Покупатели!$F$2:$N$762,3,0) -> МЮ РК | I54: =VLOOKUP(C54,Покупатели!$C$2:$M$805,7,0) -> 600630350255 | J54: =IFERROR(__xludf.DUMMYFUNCTION("JOIN("" "", VLOOKUP(C54,Покупатели,8,0),VLOOKUP(C54,Покупатели,9,0),VLOOKUP(C54,Покупатели,10,0),VLOOKUP(C54,Покупатели,11,0))"),"Акмолинская обл. г.Кокшетау ул.Назарбаева д.8, кв.151") -> Акмолинская обл. г.Кокшетау ул.Назарбаева д.8, кв.151 | K54: =VLOOKUP(C54,Покупатели,12,0) -> 87051361125 | L54: =VLOOKUP(A54,Реестр_Договоров,4,0) -> MX4000002R0001671 | M54: =VLOOKUP(L54,ПРИЦЕПЫ,11,0) -> 002-2013E30Q13-OK | N54: =VLOOKUP(L54,ПРИЦЕПЫ,2,0) -> Прицеп 2,0*1,25 м (до 750 кг.) | O54: =VLOOKUP(L54,ПРИЦЕПЫ,10,0) -> 1 ось | P54: =YEAR(VLOOKUP(L54,ПРИЦЕПЫ,7,0)) -> 2024 | Q54: =VLOOKUP(M54,матрица,16,0) -> 3150*1700*900 | R54: =VLOOKUP(M54,матрица,17,0) -> 2000*1250*300 | S54: =VLOOKUP(O54,ОТТС!$A$2:$B$3,2,0) -> ТС KZ Е-KZ.0317.00251 от 28.02.2023 | T54: 380000 | U54: =VLOOKUP(L54,ПРИЦЕПЫ,9,0) -> Кокшетау
A55: 1214 | B55: =VLOOKUP(A55,'Реестр договоров'!$A$2:$D$55,2,0) -> 45476 | C55: =VLOOKUP(A55,Реестр_Договоров,3,0) -> Жумангужина | D55: =VLOOKUP(C55,Покупатели,2,0) -> Гульмира | E55: =VLOOKUP(C55,Покупатели,3,0) -> Тюлюгеновна | F55: =VLOOKUP(C55,Покупатели,4,0) -> 019349306 | G55: =VLOOKUP(F55,Покупатели!$F$2:$N$762,2,0) -> 39038 | H55: =VLOOKUP(F55,Покупатели!$F$2:$N$762,3,0) -> МЮ РК | I55: =VLOOKUP(C55,Покупатели!$C$2:$M$805,7,0) -> 820228450162 | J55: =IFERROR(__xludf.DUMMYFUNCTION("JOIN("" "", VLOOKUP(C55,Покупатели,8,0),VLOOKUP(C55,Покупатели,9,0),VLOOKUP(C55,Покупатели,10,0),VLOOKUP(C55,Покупатели,11,0))"),"Акмолинская обл. Целиноградский р-н, пос.Караоткель ул.Ж.Жабаева д.38") -> Акмолинская обл. Целиноградский р-н, пос.Караоткель ул.Ж.Жабаева д.38 | K55: =VLOOKUP(C55,Покупатели,12,0) -> 87006081838 | L55: =VLOOKUP(A55,Реестр_Договоров,4,0) -> MX4000002R0001657 | M55: =VLOOKUP(L55,ПРИЦЕПЫ,11,0) -> 002-2013E30Q13-OK | N55: =VLOOKUP(L55,ПРИЦЕПЫ,2,0) -> Прицеп 2,0*1,25 м (до 750 кг.) | O55: =VLOOKUP(L55,ПРИЦЕПЫ,10,0) -> 1 ось | P55: =YEAR(VLOOKUP(L55,ПРИЦЕПЫ,7,0)) -> 2024 | Q55: =VLOOKUP(M55,матрица,16,0) -> 3150*1700*900 | R55: =VLOOKUP(M55,матрица,17,0) -> 2000*1250*300 | S55: =VLOOKUP(O55,ОТТС!$A$2:$B$3,2,0) -> ТС KZ Е-KZ.0317.00251 от 28.02.2023 | T55: 380000 | U55: =VLOOKUP(L55,ПРИЦЕПЫ,9,0) -> Астана
A56: 1215 | B56: =VLOOKUP(A56,'Реестр договоров'!$A$2:$D$298,2,0) -> 45476 | C56: =VLOOKUP(A56,Реестр_Договоров,3,0) -> Белгибаева | D56: =VLOOKUP(C56,Покупатели,2,0) -> Жасулан | E56: =VLOOKUP(C56,Покупатели,3,0) -> Дуйсенбекович | F56: =VLOOKUP(C56,Покупатели,4,0) -> 054651314 | G56: =VLOOKUP(F56,Покупатели!$F$2:$N$762,2,0) -> 44963 | H56: =VLOOKUP(F56,Покупатели!$F$2:$N$762,3,0) -> МВД РК | I56: =VLOOKUP(C56,Покупатели!$C$2:$M$805,7,0) -> 880127351394 | J56: =IFERROR(__xludf.DUMMYFUNCTION("JOIN("" "", VLOOKUP(C56,Покупатели,8,0),VLOOKUP(C56,Покупатели,9,0),VLOOKUP(C56,Покупатели,10,0),VLOOKUP(C56,Покупатели,11,0))"),"Костанайская область г. Аркалык ул. Абая 42/2") -> Костанайская область г. Аркалык ул. Абая 42/2 | K56: =VLOOKUP(C56,Покупатели,12,0) -> 87014019888 | L56: =VLOOKUP(A56,Реестр_Договоров,4,0) -> MX4000002R0001677 | M56: =VLOOKUP(L56,ПРИЦЕПЫ,11,0) -> 002-2013E50Q13-OK | N56: =VLOOKUP(L56,ПРИЦЕПЫ,2,0) -> Прицеп 2,0*1,25 м (до 750 кг.) | O56: =VLOOKUP(L56,ПРИЦЕПЫ,10,0) -> 1 ось | P56: =YEAR(VLOOKUP(L56,ПРИЦЕПЫ,7,0)) -> 2024 | Q56: =VLOOKUP(M56,матрица,16,0) -> 3150*1700*1070 | R56: =VLOOKUP(M56,матрица,17,0) -> 2000*1250*500 | S56: =VLOOKUP(O56,ОТТС!$A$2:$B$3,2,0) -> ТС KZ Е-KZ.0317.00251 от 28.02.2023 | T56: 340000 | U56: =VLOOKUP(L56,ПРИЦЕПЫ,9,0) -> Кокшетау
A57: 1216 | B57: =VLOOKUP(A57,'Реестр договоров'!$A$2:$D$298,2,0) -> 45476 | C57: =VLOOKUP(A57,Реестр_Договоров,3,0) -> Харламов 1 | D57: =VLOOKUP(C57,Покупатели,2,0) -> Георгий | E57: =VLOOKUP(C57,Покупатели,3,0) -> Александрович | F57: =VLOOKUP(C57,Покупатели,4,0) -> 046723901 | G57: =VLOOKUP(F57,Покупатели!$F$2:$N$762,2,0) -> 44046 | H57: =VLOOKUP(F57,Покупатели!$F$2:$N$762,3,0) -> МВД РК | I57: =VLOOKUP(C57,Покупатели!$C$2:$M$805,7,0) -> 911101301288 | J57: =IFERROR(__xludf.DUMMYFUNCTION("JOIN("" "", VLOOKUP(C57,Покупатели,8,0),VLOOKUP(C57,Покупатели,9,0),VLOOKUP(C57,Покупатели,10,0),VLOOKUP(C57,Покупатели,11,0))"),"г.Алматы мкр.Калкаман ул.Байтели батыра д.75") -> г.Алматы мкр.Калкаман ул.Байтели батыра д.75 | K57: =VLOOKUP(C57,Покупатели,12,0) -> 87073723655 | L57: =VLOOKUP(A57,Реестр_Договоров,4,0) -> MX4000002R0001509 | M57: =VLOOKUP(L57,ПРИЦЕПЫ,11,0) -> 002-2513E30Q13-OK | N57: =VLOOKUP(L57,ПРИЦЕПЫ,2,0) -> Прицеп 2,5*1,25 м (до 750 кг.) | O57: =VLOOKUP(L57,ПРИЦЕПЫ,10,0) -> 1 ось | P57: =YEAR(VLOOKUP(L57,ПРИЦЕПЫ,7,0)) -> 2024 | Q57: =VLOOKUP(M57,матрица,16,0) -> 3650*1700*900 | R57: =VLOOKUP(M57,матрица,17,0) -> 2500*1250*300 | S57: =VLOOKUP(O57,ОТТС!$A$2:$B$3,2,0) -> ТС KZ Е-KZ.0317.00251 от 28.02.2023 | T57: =VLOOKUP(M57,матрица,15,0) -> 380000 | U57: =VLOOKUP(L57,ПРИЦЕПЫ,9,0) -> Алматы
A58: 1217 | B58: =VLOOKUP(A58,'Реестр договоров'!$A$2:$D$298,2,0) -> 45477 | C58: =VLOOKUP(A58,Реестр_Договоров,3,0) -> Батяйкин | D58: =VLOOKUP(C58,Покупатели,2,0) -> Евгений | E58: =VLOOKUP(C58,Покупатели,3,0) -> Степанович | F58: =VLOOKUP(C58,Покупатели,4,0) -> 043275392 | G58: =VLOOKUP(F58,Покупатели!$F$2:$N$762,2,0) -> 42985 | H58: =VLOOKUP(F58,Покупатели!$F$2:$N$762,3,0) -> МВД РК | I58: =VLOOKUP(C58,Покупатели!$C$2:$M$805,7,0) -> 770402350635 | J58: =IFERROR(__xludf.DUMMYFUNCTION("JOIN("" "", VLOOKUP(C58,Покупатели,8,0),VLOOKUP(C58,Покупатели,9,0),VLOOKUP(C58,Покупатели,10,0),VLOOKUP(C58,Покупатели,11,0))"),"г.Астана мкр.Жастар пер.Ташенова д.8/1") -> г.Астана мкр.Жастар пер.Ташенова д.8/1 | K58: =VLOOKUP(C58,Покупатели,12,0) -> 87058091009 | L58: =VLOOKUP(A58,Реестр_Договоров,4,0) -> MX4000004R0001606 | M58: =VLOOKUP(L58,ПРИЦЕПЫ,11,0) -> 004-2513E30Q13-OK | N58: =VLOOKUP(L58,ПРИЦЕПЫ,2,0) -> Прицеп 2,5*1,25 м (до 750 кг.) | O58: =VLOOKUP(L58,ПРИЦЕПЫ,10,0) -> 2 оси | P58: =YEAR(VLOOKUP(L58,ПРИЦЕПЫ,7,0)) -> 2024 | Q58: 3650*1700*900 | R58: 2500*1250*300 | S58: =VLOOKUP(O58,ОТТС!$A$2:$B$3,2,0) -> ТС KZ Е-KZ.0317.00219.П1 от 17.07.2025 | T58: 680000 | U58: =VLOOKUP(L58,ПРИЦЕПЫ,9,0) -> Астана
A59: 1218 | B59: =VLOOKUP(A59,'Реестр договоров'!$A$2:$D$298,2,0) -> 45478 | C59: =VLOOKUP(A59,Реестр_Договоров,3,0) -> Волкова | D59: =VLOOKUP(C59,Покупатели,2,0) -> Константин | E59: =VLOOKUP(C59,Покупатели,3,0) -> Евгеньевич | F59: =VLOOKUP(C59,Покупатели,4,0) -> 041029217 | G59: =VLOOKUP(F59,Покупатели!$F$2:$N$762,2,0) -> 42733 | H59: =VLOOKUP(F59,Покупатели!$F$2:$N$762,3,0) -> МВД РК | I59: =VLOOKUP(C59,Покупатели!$C$2:$M$805,7,0) -> 720121302044 | J59: =IFERROR(__xludf.DUMMYFUNCTION("JOIN("" "", VLOOKUP(C59,Покупатели,8,0),VLOOKUP(C59,Покупатели,9,0),VLOOKUP(C59,Покупатели,10,0),VLOOKUP(C59,Покупатели,11,0))"),"Алматинская область Жетысуйский район Ул.Павлодарская 105") -> Алматинская область Жетысуйский район Ул.Павлодарская 105 | K59: =VLOOKUP(C59,Покупатели,12,0) -> 87772933366 | L59: =VLOOKUP(A59,Реестр_Договоров,4,0) -> MX4000002R0001560 | M59: =VLOOKUP(L59,ПРИЦЕПЫ,11,0) -> 002-2013E30Q13-OK | N59: =VLOOKUP(L59,ПРИЦЕПЫ,2,0) -> Прицеп 2,0*1,25 м (до 750 кг.) | O59: =VLOOKUP(L59,ПРИЦЕПЫ,10,0) -> 1 ось | P59: =YEAR(VLOOKUP(L59,ПРИЦЕПЫ,7,0)) -> 2024 | Q59: =VLOOKUP(M59,матрица,16,0) -> 3150*1700*900 | R59: =VLOOKUP(M59,матрица,17,0) -> 2000*1250*300 | S59: =VLOOKUP(O59,ОТТС!$A$2:$B$3,2,0) -> ТС KZ Е-KZ.0317.00251 от 28.02.2023 | T59: 360000 | U59: =VLOOKUP(L59,ПРИЦЕПЫ,9,0) -> Алматы
A60: 1219 | B60: =VLOOKUP(A60,'Реестр договоров'!$A$2:$D$298,2,0) -> 45478 | C60: =VLOOKUP(A60,Реестр_Договоров,3,0) -> Бопышев | D60: =VLOOKUP(C60,Покупатели,2,0) -> Нурбек | E60: =VLOOKUP(C60,Покупатели,3,0) -> Сулейманович | F60: =VLOOKUP(C60,Покупатели,4,0) -> 46777566 | G60: =VLOOKUP(F60,Покупатели!$F$2:$N$762,2,0) -> 43762 | H60: =VLOOKUP(F60,Покупатели!$F$2:$N$762,3,0) -> МВД РК | I60: =VLOOKUP(C60,Покупатели!$C$2:$M$805,7,0) -> 891218301505 | J60: =IFERROR(__xludf.DUMMYFUNCTION("JOIN("" "", VLOOKUP(C60,Покупатели,8,0),VLOOKUP(C60,Покупатели,9,0),VLOOKUP(C60,Покупатели,10,0),VLOOKUP(C60,Покупатели,11,0))"),"Акмолинская обл. Целиноградский р-н, пос. Коянды ул.Байтерек 113") -> Акмолинская обл. Целиноградский р-н, пос. Коянды ул.Байтерек 113 | K60: =VLOOKUP(C60,Покупатели,12,0) -> 87757369899 | L60: =VLOOKUP(A60,Реестр_Договоров,4,0) -> MX4000002R0001647 | M60: =VLOOKUP(L60,ПРИЦЕПЫ,11,0) -> 002-2513E50Q13-OK | N60: =VLOOKUP(L60,ПРИЦЕПЫ,2,0) -> Прицеп 2,5*1,25 м (до 750 кг.) | O60: =VLOOKUP(L60,ПРИЦЕПЫ,10,0) -> 1 ось | P60: =YEAR(VLOOKUP(L60,ПРИЦЕПЫ,7,0)) -> 2024 | Q60: =VLOOKUP(M60,матрица,16,0) -> 3650*1700*1070 | R60: =VLOOKUP(M60,матрица,17,0) -> 2500*1250*500 | S60: =VLOOKUP(O60,ОТТС!$A$2:$B$3,2,0) -> ТС KZ Е-KZ.0317.00251 от 28.02.2023 | T60: 320000 | U60: =VLOOKUP(L60,ПРИЦЕПЫ,9,0) -> Астана
A61: 1220 | B61: =VLOOKUP(A61,'Реестр договоров'!$A$2:$D$298,2,0) -> 45478 | C61: =VLOOKUP(A61,Реестр_Договоров,3,0) -> Дерюгин | D61: =VLOOKUP(C61,Покупатели,2,0) -> Алексей | E61: =VLOOKUP(C61,Покупатели,3,0) -> Александрович | F61: =VLOOKUP(C61,Покупатели,4,0) -> 039973227 | G61: =VLOOKUP(F61,Покупатели!$F$2:$N$762,2,0) -> 42468 | H61: =VLOOKUP(F61,Покупатели!$F$2:$N$762,3,0) -> МВД РК | I61: =VLOOKUP(C61,Покупатели!$C$2:$M$805,7,0) -> 910413300658 | J61: =IFERROR(__xludf.DUMMYFUNCTION("JOIN("" "", VLOOKUP(C61,Покупатели,8,0),VLOOKUP(C61,Покупатели,9,0),VLOOKUP(C61,Покупатели,10,0),VLOOKUP(C61,Покупатели,11,0))"),"Алматинская обл. Илийский р-н, пос.Жапек батыра ул.Алтаева 32") -> Алматинская обл. Илийский р-н, пос.Жапек батыра ул.Алтаева 32 | K61: =VLOOKUP(C61,Покупатели,12,0) -> 87072677383 | L61: =VLOOKUP(A61,Реестр_Договоров,4,0) -> MX4000002R0001460 | M61: =VLOOKUP(L61,ПРИЦЕПЫ,11,0) -> 002-2013E50Q13-OK | N61: =VLOOKUP(L61,ПРИЦЕПЫ,2,0) -> Прицеп 2,0*1,25 м (до 750 кг.) | O61: =VLOOKUP(L61,ПРИЦЕПЫ,10,0) -> 1 ось | P61: =YEAR(VLOOKUP(L61,ПРИЦЕПЫ,7,0)) -> 2024 | Q61: =VLOOKUP(M61,матрица,16,0) -> 3150*1700*1070 | R61: =VLOOKUP(M61,матрица,17,0) -> 2000*1250*500 | S61: =VLOOKUP(O61,ОТТС!$A$2:$B$3,2,0) -> ТС KZ Е-KZ.0317.00251 от 28.02.2023 | T61: 320000 | U61: =VLOOKUP(L61,ПРИЦЕПЫ,9,0) -> Алматы
A62: 1221 | B62: =VLOOKUP(A62,'Реестр договоров'!$A$2:$D$298,2,0) -> 45479 | C62: =VLOOKUP(A62,Реестр_Договоров,3,0) -> Туртаева | D62: =VLOOKUP(C62,Покупатели,2,0) -> Айнур | E62: =VLOOKUP(C62,Покупатели,3,0) -> Абылкановна | F62: =VLOOKUP(C62,Покупатели,4,0) -> 052907329 | G62: =VLOOKUP(F62,Покупатели!$F$2:$N$762,2,0) -> 45009 | H62: =VLOOKUP(F62,Покупатели!$F$2:$N$762,3,0) -> МВД РК | I62: =VLOOKUP(C62,Покупатели!$C$2:$M$805,7,0) -> 910903400937 | J62: =IFERROR(__xludf.DUMMYFUNCTION("JOIN("" "", VLOOKUP(C62,Покупатели,8,0),VLOOKUP(C62,Покупатели,9,0),VLOOKUP(C62,Покупатели,10,0),VLOOKUP(C62,Покупатели,11,0))"),"обл.Жетысу г.Талдыкорган, р-н Северо-Западный ул.Жексенбекова 34") -> обл.Жетысу г.Талдыкорган, р-н Северо-Западный ул.Жексенбекова 34 | K62: =VLOOKUP(C62,Покупатели,12,0) -> 87077329280 | L62: =VLOOKUP(A62,Реестр_Договоров,4,0) -> MX4000002R0001456 | M62: =VLOOKUP(L62,ПРИЦЕПЫ,11,0) -> 002-2013E30Q13-OK | N62: =VLOOKUP(L62,ПРИЦЕПЫ,2,0) -> Прицеп 2,0*1,25 м (до 750 кг.) | O62: =VLOOKUP(L62,ПРИЦЕПЫ,10,0) -> 1 ось | P62: =YEAR(VLOOKUP(L62,ПРИЦЕПЫ,7,0)) -> 2024 | Q62: =VLOOKUP(M62,матрица,16,0) -> 3150*1700*900 | R62: =VLOOKUP(M62,матрица,17,0) -> 2000*1250*300 | S62: =VLOOKUP(O62,ОТТС!$A$2:$B$3,2,0) -> ТС KZ Е-KZ.0317.00251 от 28.02.2023 | T62: 380000 | U62: =VLOOKUP(L62,ПРИЦЕПЫ,9,0) -> Алматы
A63: 1223 | B63: =VLOOKUP(A63,'Реестр договоров'!$A$2:$D$298,2,0) -> 45481 | C63: =VLOOKUP(A63,Реестр_Договоров,3,0) -> Ворошилов | D63: =VLOOKUP(C63,Покупатели,2,0) -> Сергей | E63: =VLOOKUP(C63,Покупатели,3,0) -> Николаевич | F63: =VLOOKUP(C63,Покупатели,4,0) -> 049476905 | G63: =VLOOKUP(F63,Покупатели!$F$2:$N$762,2,0) -> 44502 | H63: =VLOOKUP(F63,Покупатели!$F$2:$N$762,3,0) -> МВД РК | I63: =VLOOKUP(C63,Покупатели!$C$2:$M$805,7,0) -> 850302302788 | J63: =IFERROR(__xludf.DUMMYFUNCTION("JOIN("" "", VLOOKUP(C63,Покупатели,8,0),VLOOKUP(C63,Покупатели,9,0),VLOOKUP(C63,Покупатели,10,0),VLOOKUP(C63,Покупатели,11,0))"),"г.Алматы мкр.Кемел, ул.Даурен Кудабайулы д.123") -> г.Алматы мкр.Кемел, ул.Даурен Кудабайулы д.123 | K63: =VLOOKUP(C63,Покупатели,12,0) -> 87071080444 | L63: =VLOOKUP(A63,Реестр_Договоров,4,0) -> MX4000002R0001484 | M63: =VLOOKUP(L63,ПРИЦЕПЫ,11,0) -> 002-2013E50Q13-OK | N63: =VLOOKUP(L63,ПРИЦЕПЫ,2,0) -> Прицеп 2,0*1,25 м (до 750 кг.) | O63: =VLOOKUP(L63,ПРИЦЕПЫ,10,0) -> 1 ось | P63: =YEAR(VLOOKUP(L63,ПРИЦЕПЫ,7,0)) -> 2024 | Q63: =VLOOKUP(M63,матрица,16,0) -> 3150*1700*1070 | R63: =VLOOKUP(M63,матрица,17,0) -> 2000*1250*500 | S63: =VLOOKUP(O63,ОТТС!$A$2:$B$3,2,0) -> ТС KZ Е-KZ.0317.00251 от 28.02.2023 | T63: 370000 | U63: =VLOOKUP(L63,ПРИЦЕПЫ,9,0) -> Алматы
A64: 1224 | B64: =VLOOKUP(A64,'Реестр договоров'!$A$2:$D$298,2,0) -> 45481 | C64: =VLOOKUP(A64,Реестр_Договоров,3,0) -> Куликова | D64: =VLOOKUP(C64,Покупатели,2,0) -> Светлана | E64: =VLOOKUP(C64,Покупатели,3,0) -> Евгеньевна | F64: =VLOOKUP(C64,Покупатели,4,0) -> 038128498 | G64: =VLOOKUP(F64,Покупатели!$F$2:$N$762,2,0) -> 42062 | H64: =VLOOKUP(F64,Покупатели!$F$2:$N$762,3,0) -> МВД РК | I64: =VLOOKUP(C64,Покупатели!$C$2:$M$805,7,0) -> 900303450494 | J64: =IFERROR(__xludf.DUMMYFUNCTION("JOIN("" "", VLOOKUP(C64,Покупатели,8,0),VLOOKUP(C64,Покупатели,9,0),VLOOKUP(C64,Покупатели,10,0),VLOOKUP(C64,Покупатели,11,0))"),"г. Алматы Турксибский р-н пр-т Суюнбая д.231а") -> г. Алматы Турксибский р-н пр-т Суюнбая д.231а | K64: =VLOOKUP(C64,Покупатели,12,0) -> 87725553569 | L64: =VLOOKUP(A64,Реестр_Договоров,4,0) -> MX4000002R0001578 | M64: =VLOOKUP(L64,ПРИЦЕПЫ,11,0) -> 002-2013E30Q13-OK | N64: =VLOOKUP(L64,ПРИЦЕПЫ,2,0) -> Прицеп 2,0*1,25 м (до 750 кг.) | O64: =VLOOKUP(L64,ПРИЦЕПЫ,10,0) -> 1 ось | P64: =YEAR(VLOOKUP(L64,ПРИЦЕПЫ,7,0)) -> 2024 | Q64: =VLOOKUP(M64,матрица,16,0) -> 3150*1700*900 | R64: =VLOOKUP(M64,матрица,17,0) -> 2000*1250*300 | S64: =VLOOKUP(O64,ОТТС!$A$2:$B$3,2,0) -> ТС KZ Е-KZ.0317.00251 от 28.02.2023 | T64: 320000 | U64: =VLOOKUP(L64,ПРИЦЕПЫ,9,0) -> Алматы
A65: 1225 | B65: =VLOOKUP(A65,'Реестр договоров'!$A$2:$D$298,2,0) -> 45482 | C65: =VLOOKUP(A65,Реестр_Договоров,3,0) -> Мусаинов | D65: =VLOOKUP(C65,Покупатели,2,0) -> Бауржан | E65: =VLOOKUP(C65,Покупатели,3,0) -> Нурланович | F65: =VLOOKUP(C65,Покупатели,4,0) -> 049536867 | G65: =VLOOKUP(F65,Покупатели!$F$2:$N$762,2,0) -> 44511 | H65: =VLOOKUP(F65,Покупатели!$F$2:$N$762,3,0) -> МВД РК | I65: =VLOOKUP(C65,Покупатели!$C$2:$M$805,7,0) -> 830921350343 | J65: =IFERROR(__xludf.DUMMYFUNCTION("JOIN("" "", VLOOKUP(C65,Покупатели,8,0),VLOOKUP(C65,Покупатели,9,0),VLOOKUP(C65,Покупатели,10,0),VLOOKUP(C65,Покупатели,11,0))"),"г.Алматы Алатауский р-н, мкр.Мадениет ул.Майтобе д.3") -> г.Алматы Алатауский р-н, мкр.Мадениет ул.Майтобе д.3 | K65: =VLOOKUP(C65,Покупатели,12,0) -> 87074141877 | L65: =VLOOKUP(A65,Реестр_Договоров,4,0) -> MX4000002R0001475 | M65: =VLOOKUP(L65,ПРИЦЕПЫ,11,0) -> 002-2013E50Q13-OK | N65: =VLOOKUP(L65,ПРИЦЕПЫ,2,0) -> Прицеп 2,0*1,25 м (до 750 кг.) | O65: =VLOOKUP(L65,ПРИЦЕПЫ,10,0) -> 1 ось | P65: =YEAR(VLOOKUP(L65,ПРИЦЕПЫ,7,0)) -> 2024 | Q65: =VLOOKUP(M65,матрица,16,0) -> 3150*1700*1070 | R65: =VLOOKUP(M65,матрица,17,0) -> 2000*1250*500 | S65: =VLOOKUP(O65,ОТТС!$A$2:$B$3,2,0) -> ТС KZ Е-KZ.0317.00251 от 28.02.2023 | T65: 340000 | U65: =VLOOKUP(L65,ПРИЦЕПЫ,9,0) -> Алматы
A66: 1226 | B66: =VLOOKUP(A66,'Реестр договоров'!$A$2:$D$298,2,0) -> 45482 | C66: =VLOOKUP(A66,Реестр_Договоров,3,0) -> Кенжеахмет | D66: =VLOOKUP(C66,Покупатели,2,0) -> Жасұлан | E66: =VLOOKUP(C66,Покупатели,3,0) -> Сейітұлы | F66: =VLOOKUP(C66,Покупатели,4,0) -> 056848874 | G66: =VLOOKUP(F66,Покупатели!$F$2:$N$762,2,0) -> 45272 | H66: =VLOOKUP(F66,Покупатели!$F$2:$N$762,3,0) -> ҚР ІІМ | I66: =VLOOKUP(C66,Покупатели!$C$2:$M$805,7,0) -> 641120350143 | J66: =IFERROR(__xludf.DUMMYFUNCTION("JOIN("" "", VLOOKUP(C66,Покупатели,8,0),VLOOKUP(C66,Покупатели,9,0),VLOOKUP(C66,Покупатели,10,0),VLOOKUP(C66,Покупатели,11,0))"),"г.Астана р-н Есиль ул.Казыбек би д.5а, кв.585") -> г.Астана р-н Есиль ул.Казыбек би д.5а, кв.585 | K66: =VLOOKUP(C66,Покупатели,12,0) -> 87711103283 | L66: =VLOOKUP(A66,Реестр_Договоров,4,0) -> MX4000002R0001646 | M66: =VLOOKUP(L66,ПРИЦЕПЫ,11,0) -> 002-2513E30Q13-OK | N66: =VLOOKUP(L66,ПРИЦЕПЫ,2,0) -> Прицеп 2,5*1,25 м (до 750 кг.) | O66: =VLOOKUP(L66,ПРИЦЕПЫ,10,0) -> 1 ось | P66: =YEAR(VLOOKUP(L66,ПРИЦЕПЫ,7,0)) -> 2024 | Q66: =VLOOKUP(M66,матрица,16,0) -> 3650*1700*900 | R66: =VLOOKUP(M66,матрица,17,0) -> 2500*1250*300 | S66: =VLOOKUP(O66,ОТТС!$A$2:$B$3,2,0) -> ТС KZ Е-KZ.0317.00251 от 28.02.2023 | T66: 380000 | U66: =VLOOKUP(L66,ПРИЦЕПЫ,9,0) -> Астана
A67: 1227 | B67: =VLOOKUP(A67,'Реестр договоров'!$A$2:$D$298,2,0) -> 45484 | C67: =VLOOKUP(A67,Реестр_Договоров,3,0) -> Сатыбаев | D67: =VLOOKUP(C67,Покупатели,2,0) -> Мереке | E67: =VLOOKUP(C67,Покупатели,3,0) -> Серикович | F67: =VLOOKUP(C67,Покупатели,4,0) -> 043353420 | G67: =VLOOKUP(F67,Покупатели!$F$2:$N$762,2,0) -> 43003 | H67: =VLOOKUP(F67,Покупатели!$F$2:$N$762,3,0) -> МВД РК | I67: =VLOOKUP(C67,Покупатели!$C$2:$M$805,7,0) -> 800501300358 | J67: =IFERROR(__xludf.DUMMYFUNCTION("JOIN("" "", VLOOKUP(C67,Покупатели,8,0),VLOOKUP(C67,Покупатели,9,0),VLOOKUP(C67,Покупатели,10,0),VLOOKUP(C67,Покупатели,11,0))"),"Акмолиснкая с. Зеренда ул. Красноармейская 42") -> Акмолиснкая с. Зеренда ул. Красноармейская 42 | K67: =VLOOKUP(C67,Покупатели,12,0) -> 87719096487 | L67: =VLOOKUP(A67,Реестр_Договоров,4,0) -> MX4000002R0001711 | M67: =VLOOKUP(L67,ПРИЦЕПЫ,11,0) -> 002-2513E50Q13-OK90 | N67: =VLOOKUP(L67,ПРИЦЕПЫ,2,0) -> Прицеп 2,5*1,25 м (до 750 кг.) | O67: =VLOOKUP(L67,ПРИЦЕПЫ,10,0) -> 1 ось | P67: =YEAR(VLOOKUP(L67,ПРИЦЕПЫ,7,0)) -> 2024 | Q67: =VLOOKUP(M67,матрица,16,0) -> 3650*1700*1070 | R67: =VLOOKUP(M67,матрица,17,0) -> 2500*1250*500 | S67: =VLOOKUP(O67,ОТТС!$A$2:$B$3,2,0) -> ТС KZ Е-KZ.0317.00251 от 28.02.2023 | T67: 380000 | U67: =VLOOKUP(L67,ПРИЦЕПЫ,9,0) -> Кокшетау
A68: 1228 | B68: =VLOOKUP(A68,'Реестр договоров'!$A$2:$D$298,2,0) -> 45484 | C68: =VLOOKUP(A68,Реестр_Договоров,3,0) -> Мускеев | D68: =VLOOKUP(C68,Покупатели,2,0) -> Саид | E68: =VLOOKUP(C68,Покупатели,3,0) -> Малсакович | F68: =VLOOKUP(C68,Покупатели,4,0) -> 045227430 | G68: =VLOOKUP(F68,Покупатели!$F$2:$N$762,2,0) -> 43448 | H68: =VLOOKUP(F68,Покупатели!$F$2:$N$762,3,0) -> МВД РК | I68: =VLOOKUP(C68,Покупатели!$C$2:$M$805,7,0) -> 850207351323 | J68: =IFERROR(__xludf.DUMMYFUNCTION("JOIN("" "", VLOOKUP(C68,Покупатели,8,0),VLOOKUP(C68,Покупатели,9,0),VLOOKUP(C68,Покупатели,10,0),VLOOKUP(C68,Покупатели,11,0))"),"г.Астана р-н Сарыарка ул.Агыбай батыра д.20") -> г.Астана р-н Сарыарка ул.Агыбай батыра д.20 | K68: =VLOOKUP(C68,Покупатели,12,0) -> 87025555565 | L68: =VLOOKUP(A68,Реестр_Договоров,4,0) -> MX4000002R0001689 | M68: =VLOOKUP(L68,ПРИЦЕПЫ,11,0) -> 002-2013E30Q13-OK | N68: =VLOOKUP(L68,ПРИЦЕПЫ,2,0) -> Прицеп 2,0*1,25 м (до 750 кг.) | O68: =VLOOKUP(L68,ПРИЦЕПЫ,10,0) -> 1 ось | P68: =YEAR(VLOOKUP(L68,ПРИЦЕПЫ,7,0)) -> 2024 | Q68: =VLOOKUP(M68,матрица,16,0) -> 3150*1700*900 | R68: =VLOOKUP(M68,матрица,17,0) -> 2000*1250*300 | S68: =VLOOKUP(O68,ОТТС!$A$2:$B$3,2,0) -> ТС KZ Е-KZ.0317.00251 от 28.02.2023 | T68: 440000 | U68: =VLOOKUP(L68,ПРИЦЕПЫ,9,0) -> Кокшетау
A69: 1229 | B69: =VLOOKUP(A69,'Реестр договоров'!$A$2:$D$298,2,0) -> 45484 | C69: =VLOOKUP(A69,Реестр_Договоров,3,0) -> Жакупов | D69: =VLOOKUP(C69,Покупатели,2,0) -> Валихан | E69: =VLOOKUP(C69,Покупатели,3,0) -> Жумабекович | F69: =VLOOKUP(C69,Покупатели,4,0) -> 040389962 | G69: =VLOOKUP(F69,Покупатели!$F$2:$N$762,2,0) -> 42362 | H69: =VLOOKUP(F69,Покупатели!$F$2:$N$762,3,0) -> МВД РК | I69: =VLOOKUP(C69,Покупатели!$C$2:$M$805,7,0) -> 790521302140 | J69: =IFERROR(__xludf.DUMMYFUNCTION("JOIN("" "", VLOOKUP(C69,Покупатели,8,0),VLOOKUP(C69,Покупатели,9,0),VLOOKUP(C69,Покупатели,10,0),VLOOKUP(C69,Покупатели,11,0))"),"Акмолинская область г. Атбасар ул. Лукобелаж 39/1") -> Акмолинская область г. Атбасар ул. Лукобелаж 39/1 | K69: =VLOOKUP(C69,Покупатели,12,0) -> 87775198432 | L69: =VLOOKUP(A69,Реестр_Договоров,4,0) -> MX4000002R0001670 | M69: =VLOOKUP(L69,ПРИЦЕПЫ,11,0) -> 002-2013E50Q13-OK30 | N69: =VLOOKUP(L69,ПРИЦЕПЫ,2,0) -> Прицеп 2,0*1,25 м (до 750 кг.) | O69: =VLOOKUP(L69,ПРИЦЕПЫ,10,0) -> 1 ось | P69: =YEAR(VLOOKUP(L69,ПРИЦЕПЫ,7,0)) -> 2024 | Q69: =VLOOKUP(M69,матрица,16,0) -> 3150*1700*1070 | R69: =VLOOKUP(M69,матрица,17,0) -> 2000*1250*500 | S69: =VLOOKUP(O69,ОТТС!$A$2:$B$3,2,0) -> ТС KZ Е-KZ.0317.00251 от 28.02.2023 | T69: 350000 | U69: =VLOOKUP(L69,ПРИЦЕПЫ,9,0) -> Кокшетау
A70: 1230 | B70: =VLOOKUP(A70,'Реестр договоров'!$A$2:$D$298,2,0) -> 45485 | C70: =VLOOKUP(A70,Реестр_Договоров,3,0) -> Досболов | D70: =VLOOKUP(C70,Покупатели,2,0) -> Муслим | E70: =VLOOKUP(C70,Покупатели,3,0) -> Шабденұлы | F70: =VLOOKUP(C70,Покупатели,4,0) -> 038534703 | G70: =VLOOKUP(F70,Покупатели!$F$2:$N$762,2,0) -> 42249 | H70: =VLOOKUP(F70,Покупатели!$F$2:$N$762,3,0) -> ҚР ІІМ | I70: =VLOOKUP(C70,Покупатели!$C$2:$M$805,7,0) -> 770215301244 | J70: =IFERROR(__xludf.DUMMYFUNCTION("JOIN("" "", VLOOKUP(C70,Покупатели,8,0),VLOOKUP(C70,Покупатели,9,0),VLOOKUP(C70,Покупатели,10,0),VLOOKUP(C70,Покупатели,11,0))"),"Алматинская обл. г.Конаев ул.Илийская д.30") -> Алматинская обл. г.Конаев ул.Илийская д.30 | K70: =VLOOKUP(C70,Покупатели,12,0) -> 87012993389 | L70: =VLOOKUP(A70,Реестр_Договоров,4,0) -> MX4000002R0001470 | M70: =VLOOKUP(L70,ПРИЦЕПЫ,11,0) -> 002-2013E50Q13-OK | N70: =VLOOKUP(L70,ПРИЦЕПЫ,2,0) -> Прицеп 2,0*1,25 м (до 750 кг.) | O70: =VLOOKUP(L70,ПРИЦЕПЫ,10,0) -> 1 ось | P70: =YEAR(VLOOKUP(L70,ПРИЦЕПЫ,7,0)) -> 2024 | Q70: =VLOOKUP(M70,матрица,16,0) -> 3150*1700*1070 | R70: =VLOOKUP(M70,матрица,17,0) -> 2000*1250*500 | S70: =VLOOKUP(O70,ОТТС!$A$2:$B$3,2,0) -> ТС KZ Е-KZ.0317.00251 от 28.02.2023 | T70: 380000 | U70: =VLOOKUP(L70,ПРИЦЕПЫ,9,0) -> Алматы
A71: 1231 | B71: =VLOOKUP(A71,'Реестр договоров'!$A$2:$D$298,2,0) -> 45485 | C71: =VLOOKUP(A71,Реестр_Договоров,3,0) -> Веретенников | D71: =VLOOKUP(C71,Покупатели,2,0) -> Николай | E71: =VLOOKUP(C71,Покупатели,3,0) -> Викторович | F71: =VLOOKUP(C71,Покупатели,4,0) -> 049794021 | G71: =VLOOKUP(F71,Покупатели!$F$2:$N$762,2,0) -> 44557 | H71: =VLOOKUP(F71,Покупатели!$F$2:$N$762,3,0) -> МВД РК | I71: =VLOOKUP(C71,Покупатели!$C$2:$M$805,7,0) -> 670204302152 | J71: =IFERROR(__xludf.DUMMYFUNCTION("JOIN("" "", VLOOKUP(C71,Покупатели,8,0),VLOOKUP(C71,Покупатели,9,0),VLOOKUP(C71,Покупатели,10,0),VLOOKUP(C71,Покупатели,11,0))"),"Алматинская обл. Илийский р-н, пос.Бурундай ул.Устаздар д.4А") -> Алматинская обл. Илийский р-н, пос.Бурундай ул.Устаздар д.4А | K71: =VLOOKUP(C71,Покупатели,12,0) -> 87714078351 | L71: =VLOOKUP(A71,Реестр_Договоров,4,0) -> MX4000002R0001472 | M71: =VLOOKUP(L71,ПРИЦЕПЫ,11,0) -> 002-2013E50Q13-OK | N71: =VLOOKUP(L71,ПРИЦЕПЫ,2,0) -> Прицеп 2,0*1,25 м (до 750 кг.) | O71: =VLOOKUP(L71,ПРИЦЕПЫ,10,0) -> 1 ось | P71: =YEAR(VLOOKUP(L71,ПРИЦЕПЫ,7,0)) -> 2024 | Q71: =VLOOKUP(M71,матрица,16,0) -> 3150*1700*1070 | R71: =VLOOKUP(M71,матрица,17,0) -> 2000*1250*500 | S71: =VLOOKUP(O71,ОТТС!$A$2:$B$3,2,0) -> ТС KZ Е-KZ.0317.00251 от 28.02.2023 | T71: 380000 | U71: =VLOOKUP(L71,ПРИЦЕПЫ,9,0) -> Алматы
A72: 1233 | B72: =VLOOKUP(A72,'Реестр договоров'!$A$2:$D$298,2,0) -> 45488 | C72: =VLOOKUP(A72,Реестр_Договоров,3,0) -> Тимкина | D72: =VLOOKUP(C72,Покупатели,2,0) -> Ольга | E72: =VLOOKUP(C72,Покупатели,3,0) -> Викторовна | F72: =VLOOKUP(C72,Покупатели,4,0) -> 037265241 | G72: =VLOOKUP(F72,Покупатели!$F$2:$N$762,2,0) -> 41969 | H72: =VLOOKUP(F72,Покупатели!$F$2:$N$762,3,0) -> МВД РК | I72: =VLOOKUP(C72,Покупатели!$C$2:$M$805,7,0) -> 691129402455 | J72: =IFERROR(__xludf.DUMMYFUNCTION("JOIN("" "", VLOOKUP(C72,Покупатели,8,0),VLOOKUP(C72,Покупатели,9,0),VLOOKUP(C72,Покупатели,10,0),VLOOKUP(C72,Покупатели,11,0))"),"Алматинская обл. Жамбылский р-н, с.Узынагаш ул.Азербаева д.30") -> Алматинская обл. Жамбылский р-н, с.Узынагаш ул.Азербаева д.30 | K72: =VLOOKUP(C72,Покупатели,12,0) -> 87078776892 | L72: =VLOOKUP(A72,Реестр_Договоров,4,0) -> MX4000002R0001622 | M72: =VLOOKUP(L72,ПРИЦЕПЫ,11,0) -> 002-2513E50Q13-OK | N72: =VLOOKUP(L72,ПРИЦЕПЫ,2,0) -> Прицеп 2,5*1,25 м (до 750 кг.) | O72: =VLOOKUP(L72,ПРИЦЕПЫ,10,0) -> 1 ось | P72: =YEAR(VLOOKUP(L72,ПРИЦЕПЫ,7,0)) -> 2024 | Q72: =VLOOKUP(M72,матрица,16,0) -> 3650*1700*1070 | R72: =VLOOKUP(M72,матрица,17,0) -> 2500*1250*500 | S72: =VLOOKUP(O72,ОТТС!$A$2:$B$3,2,0) -> ТС KZ Е-KZ.0317.00251 от 28.02.2023 | T72: 370000 | U72: =VLOOKUP(L72,ПРИЦЕПЫ,9,0) -> Алматы
A73: 1234 | B73: =VLOOKUP(A73,'Реестр договоров'!$A$2:$D$298,2,0) -> 45489 | C73: =VLOOKUP(A73,Реестр_Договоров,3,0) -> Джунуспеков | D73: =VLOOKUP(C73,Покупатели,2,0) -> Серик | E73: =VLOOKUP(C73,Покупатели,3,0) -> Ахметович | F73: =VLOOKUP(C73,Покупатели,4,0) -> 044734838 | G73: =VLOOKUP(F73,Покупатели!$F$2:$N$762,2,0) -> 43320 | H73: =VLOOKUP(F73,Покупатели!$F$2:$N$762,3,0) -> МВД РК | I73: =VLOOKUP(C73,Покупатели!$C$2:$M$805,7,0) -> 730827350341 | J73: =IFERROR(__xludf.DUMMYFUNCTION("JOIN("" "", VLOOKUP(C73,Покупатели,8,0),VLOOKUP(C73,Покупатели,9,0),VLOOKUP(C73,Покупатели,10,0),VLOOKUP(C73,Покупатели,11,0))"),"Акмолинская обл. г.Ерементау ул.Мукатова д.1") -> Акмолинская обл. г.Ерементау ул.Мукатова д.1 | K73: =VLOOKUP(C73,Покупатели,12,0) -> 87774953031 | L73: =VLOOKUP(A73,Реестр_Договоров,4,0) -> MX4000002R0001672 | M73: =VLOOKUP(L73,ПРИЦЕПЫ,11,0) -> 002-2013E50Q13-OK | N73: =VLOOKUP(L73,ПРИЦЕПЫ,2,0) -> Прицеп 2,0*1,25 м (до 750 кг.) | O73: =VLOOKUP(L73,ПРИЦЕПЫ,10,0) -> 1 ось | P73: =YEAR(VLOOKUP(L73,ПРИЦЕПЫ,7,0)) -> 2024 | Q73: =VLOOKUP(M73,матрица,16,0) -> 3150*1700*1070 | R73: =VLOOKUP(M73,матрица,17,0) -> 2000*1250*500 | S73: =VLOOKUP(O73,ОТТС!$A$2:$B$3,2,0) -> ТС KZ Е-KZ.0317.00251 от 28.02.2023 | T73: 450000 | U73: =VLOOKUP(L73,ПРИЦЕПЫ,9,0) -> Астана
A74: 1235 | B74: =VLOOKUP(A74,'Реестр договоров'!$A$2:$D$298,2,0) -> 45489 | C74: =VLOOKUP(A74,Реестр_Договоров,3,0) -> Жакаев | D74: =VLOOKUP(C74,Покупатели,2,0) -> Дулат | E74: =VLOOKUP(C74,Покупатели,3,0) -> Урикович | F74: =VLOOKUP(C74,Покупатели,4,0) -> 045260008 | G74: =VLOOKUP(F74,Покупатели!$F$2:$N$762,2,0) -> 43458 | H74: =VLOOKUP(F74,Покупатели!$F$2:$N$762,3,0) -> МВД РК | I74: =VLOOKUP(C74,Покупатели!$C$2:$M$805,7,0) -> 770510350147 | J74: =IFERROR(__xludf.DUMMYFUNCTION("JOIN("" "", VLOOKUP(C74,Покупатели,8,0),VLOOKUP(C74,Покупатели,9,0),VLOOKUP(C74,Покупатели,10,0),VLOOKUP(C74,Покупатели,11,0))"),"г.Астана р-н Алматы ул.Жумабаева д.9/2, кв.40") -> г.Астана р-н Алматы ул.Жумабаева д.9/2, кв.40 | K74: =VLOOKUP(C74,Покупатели,12,0) -> 87056317256 | L74: =VLOOKUP(A74,Реестр_Договоров,4,0) -> MX4000002R0001675 | M74: =VLOOKUP(L74,ПРИЦЕПЫ,11,0) -> 002-2013E50Q13-OK | N74: =VLOOKUP(L74,ПРИЦЕПЫ,2,0) -> Прицеп 2,0*1,25 м (до 750 кг.) | O74: =VLOOKUP(L74,ПРИЦЕПЫ,10,0) -> 1 ось | P74: =YEAR(VLOOKUP(L74,ПРИЦЕПЫ,7,0)) -> 2024 | Q74: =VLOOKUP(M74,матрица,16,0) -> 3150*1700*1070 | R74: =VLOOKUP(M74,матрица,17,0) -> 2000*1250*500 | S74: =VLOOKUP(O74,ОТТС!$A$2:$B$3,2,0) -> ТС KZ Е-KZ.0317.00251 от 28.02.2023 | T74: 390000 | U74: =VLOOKUP(L74,ПРИЦЕПЫ,9,0) -> Астана
A75: 1236 | B75: =VLOOKUP(A75,'Реестр договоров'!$A$2:$D$298,2,0) -> 45491 | C75: =VLOOKUP(A75,Реестр_Договоров,3,0) -> Казиханов | D75: =VLOOKUP(C75,Покупатели,2,0) -> Тасбулат | E75: =VLOOKUP(C75,Покупатели,3,0) -> Таупбекович | F75: =VLOOKUP(C75,Покупатели,4,0) -> 054371240 | G75: =VLOOKUP(F75,Покупатели!$F$2:$N$762,2,0) -> 44935 | H75: =VLOOKUP(F75,Покупатели!$F$2:$N$762,3,0) -> МВД РК | I75: =VLOOKUP(C75,Покупатели!$C$2:$M$805,7,0) -> 961216350469 | J75: =IFERROR(__xludf.DUMMYFUNCTION("JOIN("" "", VLOOKUP(C75,Покупатели,8,0),VLOOKUP(C75,Покупатели,9,0),VLOOKUP(C75,Покупатели,10,0),VLOOKUP(C75,Покупатели,11,0))"),"г.Астана р-н Алматы ул.Тауелсиздик д.12/1 кв.28") -> г.Астана р-н Алматы ул.Тауелсиздик д.12/1 кв.28 | K75: =VLOOKUP(C75,Покупатели,12,0) -> 87082146316 | L75: =VLOOKUP(A75,Реестр_Договоров,4,0) -> MX4000002R0001682 | M75: =VLOOKUP(L75,ПРИЦЕПЫ,11,0) -> 002-2013E50Q13-OK | N75: =VLOOKUP(L75,ПРИЦЕПЫ,2,0) -> Прицеп 2,0*1,25 м (до 750 кг.) | O75: =VLOOKUP(L75,ПРИЦЕПЫ,10,0) -> 1 ось | P75: =YEAR(VLOOKUP(L75,ПРИЦЕПЫ,7,0)) -> 2024 | Q75: =VLOOKUP(M75,матрица,16,0) -> 3150*1700*1070 | R75: =VLOOKUP(M75,матрица,17,0) -> 2000*1250*500 | S75: =VLOOKUP(O75,ОТТС!$A$2:$B$3,2,0) -> ТС KZ Е-KZ.0317.00251 от 28.02.2023 | T75: 380000 | U75: =VLOOKUP(L75,ПРИЦЕПЫ,9,0) -> Астана
A76: 1237 | B76: =VLOOKUP(A76,'Реестр договоров'!$A$2:$D$298,2,0) -> 45491 | C76: =VLOOKUP(A76,Реестр_Договоров,3,0) -> Кобжасаров | D76: =VLOOKUP(C76,Покупатели,2,0) -> Асет | E76: =VLOOKUP(C76,Покупатели,3,0) -> Оразбекович | F76: =VLOOKUP(C76,Покупатели,4,0) -> 056052474 | G76: =VLOOKUP(F76,Покупатели!$F$2:$N$762,2,0) -> 45141 | H76: =VLOOKUP(F76,Покупатели!$F$2:$N$762,3,0) -> МВД РК | I76: =VLOOKUP(C76,Покупатели!$C$2:$M$805,7,0) -> 840512351042 | J76: =IFERROR(__xludf.DUMMYFUNCTION("JOIN("" "", VLOOKUP(C76,Покупатели,8,0),VLOOKUP(C76,Покупатели,9,0),VLOOKUP(C76,Покупатели,10,0),VLOOKUP(C76,Покупатели,11,0))"),"СКО р-н им. Габита Мусрепова, с Рузаевка ул. Степная 42/1") -> СКО р-н им. Габита Мусрепова, с Рузаевка ул. Степная 42/1 | K76: =VLOOKUP(C76,Покупатели,12,0) -> 87018186335 | L76: =VLOOKUP(A76,Реестр_Договоров,4,0) -> MX4000002R0001661 | M76: =VLOOKUP(L76,ПРИЦЕПЫ,11,0) -> 002-2013E50Q13-OK30 | N76: =VLOOKUP(L76,ПРИЦЕПЫ,2,0) -> Прицеп 2,0*1,25 м (до 750 кг.) | O76: =VLOOKUP(L76,ПРИЦЕПЫ,10,0) -> 1 ось | P76: =YEAR(VLOOKUP(L76,ПРИЦЕПЫ,7,0)) -> 2024 | Q76: =VLOOKUP(M76,матрица,16,0) -> 3150*1700*1070 | R76: =VLOOKUP(M76,матрица,17,0) -> 2000*1250*500 | S76: =VLOOKUP(O76,ОТТС!$A$2:$B$3,2,0) -> ТС KZ Е-KZ.0317.00251 от 28.02.2023 | T76: 380000 | U76: =VLOOKUP(L76,ПРИЦЕПЫ,9,0) -> Кокшетау
A77: 1238 | B77: =VLOOKUP(A77,'Реестр договоров'!$A$2:$D$298,2,0) -> 45491 | C77: =VLOOKUP(A77,Реестр_Договоров,3,0) -> Токтагулов | D77: =VLOOKUP(C77,Покупатели,2,0) -> Даурен | E77: =VLOOKUP(C77,Покупатели,3,0) -> Токтагулулы | F77: =VLOOKUP(C77,Покупатели,4,0) -> 021484601 | G77: =VLOOKUP(F77,Покупатели!$F$2:$N$762,2,0) -> 39379 | H77: =VLOOKUP(F77,Покупатели!$F$2:$N$762,3,0) -> МЮ РК | I77: =VLOOKUP(C77,Покупатели!$C$2:$M$805,7,0) -> 820612301006 | J77: =IFERROR(__xludf.DUMMYFUNCTION("JOIN("" "", VLOOKUP(C77,Покупатели,8,0),VLOOKUP(C77,Покупатели,9,0),VLOOKUP(C77,Покупатели,10,0),VLOOKUP(C77,Покупатели,11,0))"),"г.Алматы Турксибский р-н ул.Кызылординская д.4/1") -> г.Алматы Турксибский р-н ул.Кызылординская д.4/1 | K77: =VLOOKUP(C77,Покупатели,12,0) -> 87762230282 | L77: =VLOOKUP(A77,Реестр_Договоров,4,0) -> MX4000002R0001467 | M77: =VLOOKUP(L77,ПРИЦЕПЫ,11,0) -> 002-2013E30Q13-OK30 | N77: =VLOOKUP(L77,ПРИЦЕПЫ,2,0) -> Прицеп 2,0*1,25 м (до 750 кг.) | O77: =VLOOKUP(L77,ПРИЦЕПЫ,10,0) -> 1 ось | P77: =YEAR(VLOOKUP(L77,ПРИЦЕПЫ,7,0)) -> 2024 | Q77: =VLOOKUP(M77,матрица,16,0) -> 3150*1700*900 | R77: =VLOOKUP(M77,матрица,17,0) -> 2000*1250*300 | S77: =VLOOKUP(O77,ОТТС!$A$2:$B$3,2,0) -> ТС KZ Е-KZ.0317.00251 от 28.02.2023 | T77: 390000 | U77: =VLOOKUP(L77,ПРИЦЕПЫ,9,0) -> Алматы
A78: 1239 | B78: =VLOOKUP(A78,'Реестр договоров'!$A$2:$D$298,2,0) -> 45492 | C78: =VLOOKUP(A78,Реестр_Договоров,3,0) -> Кальтенбергер | D78: =VLOOKUP(C78,Покупатели,2,0) -> Александр | E78: =VLOOKUP(C78,Покупатели,3,0) -> Викторович | F78: =VLOOKUP(C78,Покупатели,4,0) -> 054705124 | G78: =VLOOKUP(F78,Покупатели!$F$2:$N$762,2,0) -> 44964 | H78: =VLOOKUP(F78,Покупатели!$F$2:$N$762,3,0) -> МВД РК | I78: =VLOOKUP(C78,Покупатели!$C$2:$M$805,7,0) -> 970125350851 | J78: =IFERROR(__xludf.DUMMYFUNCTION("JOIN("" "", VLOOKUP(C78,Покупатели,8,0),VLOOKUP(C78,Покупатели,9,0),VLOOKUP(C78,Покупатели,10,0),VLOOKUP(C78,Покупатели,11,0))"),"СКО Уалихановский район, село Кишкенеколь ул. Сейфулина 32") -> СКО Уалихановский район, село Кишкенеколь ул. Сейфулина 32 | K78: =VLOOKUP(C78,Покупатели,12,0) -> 87054053900 | L78: =VLOOKUP(A78,Реестр_Договоров,4,0) -> MX4000002R0001667 | M78: =VLOOKUP(L78,ПРИЦЕПЫ,11,0) -> 002-2013E50Q13-OK | N78: =VLOOKUP(L78,ПРИЦЕПЫ,2,0) -> Прицеп 2,0*1,25 м (до 750 кг.) | O78: =VLOOKUP(L78,ПРИЦЕПЫ,10,0) -> 1 ось | P78: =YEAR(VLOOKUP(L78,ПРИЦЕПЫ,7,0)) -> 2024 | Q78: =VLOOKUP(M78,матрица,16,0) -> 3150*1700*1070 | R78: =VLOOKUP(M78,матрица,17,0) -> 2000*1250*500 | S78: =VLOOKUP(O78,ОТТС!$A$2:$B$3,2,0) -> ТС KZ Е-KZ.0317.00251 от 28.02.2023 | T78: 380000 | U78: =VLOOKUP(L78,ПРИЦЕПЫ,9,0) -> Кокшетау
A79: 1240 | B79: =VLOOKUP(A79,'Реестр договоров'!$A$2:$D$298,2,0) -> 45492 | C79: =VLOOKUP(A79,Реестр_Договоров,3,0) -> Ли | D79: =VLOOKUP(C79,Покупатели,2,0) -> Вадим | E79: =VLOOKUP(C79,Покупатели,3,0) -> Николаевич | F79: =VLOOKUP(C79,Покупатели,4,0) -> 045459103 | G79: =VLOOKUP(F79,Покупатели!$F$2:$N$762,2,0) -> 43810 | H79: =VLOOKUP(F79,Покупатели!$F$2:$N$762,3,0) -> МВД РК | I79: =VLOOKUP(C79,Покупатели!$C$2:$M$805,7,0) -> 750706302159 | J79: =IFERROR(__xludf.DUMMYFUNCTION("JOIN("" "", VLOOKUP(C79,Покупатели,8,0),VLOOKUP(C79,Покупатели,9,0),VLOOKUP(C79,Покупатели,10,0),VLOOKUP(C79,Покупатели,11,0))"),"Алматинская обл. г.Талдыкорган ул.Аксуйская д.9, кв.2") -> Алматинская обл. г.Талдыкорган ул.Аксуйская д.9, кв.2 | K79: =VLOOKUP(C79,Покупатели,12,0) -> 87075009091 | L79: =VLOOKUP(A79,Реестр_Договоров,4,0) -> MX4000002R0001469 | M79: =VLOOKUP(L79,ПРИЦЕПЫ,11,0) -> 002-2013E50Q13-OK | N79: =VLOOKUP(L79,ПРИЦЕПЫ,2,0) -> Прицеп 2,0*1,25 м (до 750 кг.) | O79: =VLOOKUP(L79,ПРИЦЕПЫ,10,0) -> 1 ось | P79: =YEAR(VLOOKUP(L79,ПРИЦЕПЫ,7,0)) -> 2024 | Q79: =VLOOKUP(M79,матрица,16,0) -> 3150*1700*1070 | R79: =VLOOKUP(M79,матрица,17,0) -> 2000*1250*500 | S79: =VLOOKUP(O79,ОТТС!$A$2:$B$3,2,0) -> ТС KZ Е-KZ.0317.00251 от 28.02.2023 | T79: 360000 | U79: =VLOOKUP(L79,ПРИЦЕПЫ,9,0) -> Алматы
A80: 1241 | B80: =VLOOKUP(A80,'Реестр договоров'!$A$2:$D$298,2,0) -> 45496 | C80: =VLOOKUP(A80,Реестр_Договоров,3,0) -> Кондратьев | D80: =VLOOKUP(C80,Покупатели,2,0) -> Сергей | E80: =VLOOKUP(C80,Покупатели,3,0) -> Николаевич | F80: =VLOOKUP(C80,Покупатели,4,0) -> 057007005 | G80: =VLOOKUP(F80,Покупатели!$F$2:$N$762,2,0) -> 45470 | H80: =VLOOKUP(F80,Покупатели!$F$2:$N$762,3,0) -> МВД РК | I80: =VLOOKUP(C80,Покупатели!$C$2:$M$805,7,0) -> 870531300840 | J80: =IFERROR(__xludf.DUMMYFUNCTION("JOIN("" "", VLOOKUP(C80,Покупатели,8,0),VLOOKUP(C80,Покупатели,9,0),VLOOKUP(C80,Покупатели,10,0),VLOOKUP(C80,Покупатели,11,0))"),"Алматинская обл. Талгарский р-н ул. Гулдана Наурызбай батыра 24") -> Алматинская обл. Талгарский р-н ул. Гулдана Наурызбай батыра 24 | K80: =VLOOKUP(C80,Покупатели,12,0) -> 87081037831 | L80: =VLOOKUP(A80,Реестр_Договоров,4,0) -> MX4000002R0001478 | M80: =VLOOKUP(L80,ПРИЦЕПЫ,11,0) -> 002-2013E30Q13-OK | N80: =VLOOKUP(L80,ПРИЦЕПЫ,2,0) -> Прицеп 2,0*1,25 м (до 750 кг.) | O80: =VLOOKUP(L80,ПРИЦЕПЫ,10,0) -> 1 ось | P80: =YEAR(VLOOKUP(L80,ПРИЦЕПЫ,7,0)) -> 2024 | Q80: =VLOOKUP(M80,матрица,16,0) -> 3150*1700*900 | R80: =VLOOKUP(M80,матрица,17,0) -> 2000*1250*300 | S80: =VLOOKUP(O80,ОТТС!$A$2:$B$3,2,0) -> ТС KZ Е-KZ.0317.00251 от 28.02.2023 | T80: 380000 | U80: =VLOOKUP(L80,ПРИЦЕПЫ,9,0) -> Алматы
A81: 1242 | B81: =VLOOKUP(A81,'Реестр договоров'!$A$2:$D$298,2,0) -> 45496 | C81: =VLOOKUP(A81,Реестр_Договоров,3,0) -> Жаксыбаев | D81: =VLOOKUP(C81,Покупатели,2,0) -> Магауия | E81: =VLOOKUP(C81,Покупатели,3,0) -> Муратович | F81: =VLOOKUP(C81,Покупатели,4,0) -> 054355863 | G81: =VLOOKUP(F81,Покупатели!$F$2:$N$762,2,0) -> 45173 | H81: =VLOOKUP(F81,Покупатели!$F$2:$N$762,3,0) -> МВД РК | I81: =VLOOKUP(C81,Покупатели!$C$2:$M$805,7,0) -> 880914301306 | J81: =IFERROR(__xludf.DUMMYFUNCTION("JOIN("" "", VLOOKUP(C81,Покупатели,8,0),VLOOKUP(C81,Покупатели,9,0),VLOOKUP(C81,Покупатели,10,0),VLOOKUP(C81,Покупатели,11,0))")," Алматы облысы Жамбыл ауданы Жандос 7") -> Алматы облысы Жамбыл ауданы Жандос 7 | K81: =VLOOKUP(C81,Покупатели,12,0) -> 87018196189 | L81: =VLOOKUP(A81,Реестр_Договоров,4,0) -> MX4000002R0001501 | M81: =VLOOKUP(L81,ПРИЦЕПЫ,11,0) -> 002-2013E30Q13-OK | N81: =VLOOKUP(L81,ПРИЦЕПЫ,2,0) -> Прицеп 2,0*1,25 м (до 750 кг.) | O81: =VLOOKUP(L81,ПРИЦЕПЫ,10,0) -> 1 ось | P81: =YEAR(VLOOKUP(L81,ПРИЦЕПЫ,7,0)) -> 2024 | Q81: =VLOOKUP(M81,матрица,16,0) -> 3150*1700*900 | R81: =VLOOKUP(M81,матрица,17,0) -> 2000*1250*300 | S81: =VLOOKUP(O81,ОТТС!$A$2:$B$3,2,0) -> ТС KZ Е-KZ.0317.00251 от 28.02.2023 | T81: 390000 | U81: Алматы
A82: 1243 | B82: =VLOOKUP(A82,'Реестр договоров'!$A$2:$D$298,2,0) -> 45496 | C82: =VLOOKUP(A82,Реестр_Договоров,3,0) -> Хомидов | D82: =VLOOKUP(C82,Покупатели,2,0) -> Жавлон | E82: =VLOOKUP(C82,Покупатели,3,0) -> Норбоевич | F82: =VLOOKUP(C82,Покупатели,4,0) -> 056411413 | G82: =VLOOKUP(F82,Покупатели!$F$2:$N$762,2,0) -> 45414 | H82: =VLOOKUP(F82,Покупатели!$F$2:$N$762,3,0) -> МВД РК | I82: =VLOOKUP(C82,Покупатели!$C$2:$M$805,7,0) -> 860307000147 | J82: =IFERROR(__xludf.DUMMYFUNCTION("JOIN("" "", VLOOKUP(C82,Покупатели,8,0),VLOOKUP(C82,Покупатели,9,0),VLOOKUP(C82,Покупатели,10,0),VLOOKUP(C82,Покупатели,11,0))"),"Алматинская область Илийский район, с. Байсерке Механизатор УМР д.78") -> Алматинская область Илийский район, с. Байсерке Механизатор УМР д.78 | K82: =VLOOKUP(C82,Покупатели,12,0) -> 87073447308 | L82: =VLOOKUP(A82,Реестр_Договоров,4,0) -> MX4000002R0001477 | M82: =VLOOKUP(L82,ПРИЦЕПЫ,11,0) -> 002-2013E30Q13-OK | N82: =VLOOKUP(L82,ПРИЦЕПЫ,2,0) -> Прицеп 2,0*1,25 м (до 750 кг.) | O82: =VLOOKUP(L82,ПРИЦЕПЫ,10,0) -> 1 ось | P82: =YEAR(VLOOKUP(L82,ПРИЦЕПЫ,7,0)) -> 2024 | Q82: =VLOOKUP(M82,матрица,16,0) -> 3150*1700*900 | R82: =VLOOKUP(M82,матрица,17,0) -> 2000*1250*300 | S82: =VLOOKUP(O82,ОТТС!$A$2:$B$3,2,0) -> ТС KZ Е-KZ.0317.00251 от 28.02.2023 | T82: 440000 | U82: =VLOOKUP(L82,ПРИЦЕПЫ,9,0) -> Алматы
A83: 1244 | B83: =VLOOKUP(A83,'Реестр договоров'!$A$2:$D$298,2,0) -> 45497 | C83: =VLOOKUP(A83,Реестр_Договоров,3,0) -> Зоркальцева | D83: =VLOOKUP(C83,Покупатели,2,0) -> Екатерина | E83: =VLOOKUP(C83,Покупатели,3,0) -> Ивановна | F83: =VLOOKUP(C83,Покупатели,4,0) -> 056674588 | G83: =VLOOKUP(F83,Покупатели!$F$2:$N$762,2,0) -> 45243 | H83: =VLOOKUP(F83,Покупатели!$F$2:$N$762,3,0) -> МВД РК | I83: =VLOOKUP(C83,Покупатели!$C$2:$M$805,7,0) -> 870207450305 | J83: =IFERROR(__xludf.DUMMYFUNCTION("JOIN("" "", VLOOKUP(C83,Покупатели,8,0),VLOOKUP(C83,Покупатели,9,0),VLOOKUP(C83,Покупатели,10,0),VLOOKUP(C83,Покупатели,11,0))"),"Акмолинская обл. Шортандинский р-н, пос.Шортанды ул.Лермонтова д.16 кв.15") -> Акмолинская обл. Шортандинский р-н, пос.Шортанды ул.Лермонтова д.16 кв.15 | K83: =VLOOKUP(C83,Покупатели,12,0) -> 87784547810 | L83: =VLOOKUP(A83,Реестр_Договоров,4,0) -> MX4000002R0001693 | M83: =VLOOKUP(L83,ПРИЦЕПЫ,11,0) -> 002-2013E50Q13-OK | N83: =VLOOKUP(L83,ПРИЦЕПЫ,2,0) -> Прицеп 2,0*1,25 м (до 750 кг.) | O83: =VLOOKUP(L83,ПРИЦЕПЫ,10,0) -> 1 ось | P83: =YEAR(VLOOKUP(L83,ПРИЦЕПЫ,7,0)) -> 2024 | Q83: =VLOOKUP(M83,матрица,16,0) -> 3150*1700*1070 | R83: =VLOOKUP(M83,матрица,17,0) -> 2000*1250*500 | S83: =VLOOKUP(O83,ОТТС!$A$2:$B$3,2,0) -> ТС KZ Е-KZ.0317.00251 от 28.02.2023 | T83: 380000 | U83: =VLOOKUP(L83,ПРИЦЕПЫ,9,0) -> Астана
A84: 1245 | B84: =VLOOKUP(A84,'Реестр договоров'!$A$2:$D$298,2,0) -> 45497 | C84: =VLOOKUP(A84,Реестр_Договоров,3,0) -> Нусипов | D84: =VLOOKUP(C84,Покупатели,2,0) -> Бакытжан | E84: =VLOOKUP(C84,Покупатели,3,0) -> Танибергенович | F84: =VLOOKUP(C84,Покупатели,4,0) -> 0 | G84: =VLOOKUP(F84,Покупатели!$F$2:$N$762,2,0) -> 45497 | H84: =VLOOKUP(F84,Покупатели!$F$2:$N$762,3,0) -> МВД РК | I84: =VLOOKUP(C84,Покупатели!$C$2:$M$805,7,0) -> 880220300157 | J84: =IFERROR(__xludf.DUMMYFUNCTION("JOIN("" "", VLOOKUP(C84,Покупатели,8,0),VLOOKUP(C84,Покупатели,9,0),VLOOKUP(C84,Покупатели,10,0),VLOOKUP(C84,Покупатели,11,0))"),"0 0 0 0") -> 0 0 0 0 | K84: =VLOOKUP(C84,Покупатели,12,0) -> 0 | L84: =VLOOKUP(A84,Реестр_Договоров,4,0) -> MX4000002R0001495 | M84: =VLOOKUP(L84,ПРИЦЕПЫ,11,0) -> 002-2013E30Q13-OK | N84: =VLOOKUP(L84,ПРИЦЕПЫ,2,0) -> Прицеп 2,0*1,25 м (до 750 кг.) | O84: =VLOOKUP(L84,ПРИЦЕПЫ,10,0) -> 1 ось | P84: =YEAR(VLOOKUP(L84,ПРИЦЕПЫ,7,0)) -> 2024 | Q84: =VLOOKUP(M84,матрица,16,0) -> 3150*1700*900 | R84: =VLOOKUP(M84,матрица,17,0) -> 2000*1250*300 | S84: =VLOOKUP(O84,ОТТС!$A$2:$B$3,2,0) -> ТС KZ Е-KZ.0317.00251 от 28.02.2023 | T84: 440000 | U84: =VLOOKUP(L84,ПРИЦЕПЫ,9,0) -> Алматы
A85: 1246 | B85: =VLOOKUP(A85,'Реестр договоров'!$A$2:$D$298,2,0) -> 45497 | C85: =VLOOKUP(A85,Реестр_Договоров,3,0) -> Мусалиев | D85: =VLOOKUP(C85,Покупатели,2,0) -> Валерий | E85: =VLOOKUP(C85,Покупатели,3,0) -> Мукашевич | F85: =VLOOKUP(C85,Покупатели,4,0) -> 054731344 | G85: =VLOOKUP(F85,Покупатели!$F$2:$N$762,2,0) -> 44973 | H85: =VLOOKUP(F85,Покупатели!$F$2:$N$762,3,0) -> МВД РК | I85: =VLOOKUP(C85,Покупатели!$C$2:$M$805,7,0) -> 630614301681 | J85: =IFERROR(__xludf.DUMMYFUNCTION("JOIN("" "", VLOOKUP(C85,Покупатели,8,0),VLOOKUP(C85,Покупатели,9,0),VLOOKUP(C85,Покупатели,10,0),VLOOKUP(C85,Покупатели,11,0))"),"г.Астана Алматинский р-н ул.Ш.Калдаякова д.11, кв.196") -> г.Астана Алматинский р-н ул.Ш.Калдаякова д.11, кв.196 | K85: =VLOOKUP(C85,Покупатели,12,0) -> 87026008836 | L85: =VLOOKUP(A85,Реестр_Договоров,4,0) -> MX4000002R0001674 | M85: =VLOOKUP(L85,ПРИЦЕПЫ,11,0) -> 002-2013E30Q13-OK | N85: =VLOOKUP(L85,ПРИЦЕПЫ,2,0) -> Прицеп 2,0*1,25 м (до 750 кг.) | O85: =VLOOKUP(L85,ПРИЦЕПЫ,10,0) -> 1 ось | P85: =YEAR(VLOOKUP(L85,ПРИЦЕПЫ,7,0)) -> 2024 | Q85: =VLOOKUP(M85,матрица,16,0) -> 3150*1700*900 | R85: =VLOOKUP(M85,матрица,17,0) -> 2000*1250*300 | S85: =VLOOKUP(O85,ОТТС!$A$2:$B$3,2,0) -> ТС KZ Е-KZ.0317.00251 от 28.02.2023 | T85: 430000 | U85: =VLOOKUP(L85,ПРИЦЕПЫ,9,0) -> Астана
A86: 1248 | B86: =VLOOKUP(A86,'Реестр договоров'!$A$2:$D$298,2,0) -> 45498 | C86: =VLOOKUP(A86,Реестр_Договоров,3,0) -> Хусуров | D86: =VLOOKUP(C86,Покупатели,2,0) -> Дильмурат | E86: =VLOOKUP(C86,Покупатели,3,0) -> Марсович | F86: =VLOOKUP(C86,Покупатели,4,0) -> 049161307 | G86: =VLOOKUP(F86,Покупатели!$F$2:$N$762,2,0) -> 44452 | H86: =VLOOKUP(F86,Покупатели!$F$2:$N$762,3,0) -> МВД РК | I86: =VLOOKUP(C86,Покупатели!$C$2:$M$805,7,0) -> 860811301104 | J86: =IFERROR(__xludf.DUMMYFUNCTION("JOIN("" "", VLOOKUP(C86,Покупатели,8,0),VLOOKUP(C86,Покупатели,9,0),VLOOKUP(C86,Покупатели,10,0),VLOOKUP(C86,Покупатели,11,0))"),"г.Алматы Алмалинский р-н ул.Наурызбай батыра д.99/1, кв.35") -> г.Алматы Алмалинский р-н ул.Наурызбай батыра д.99/1, кв.35 | K86: =VLOOKUP(C86,Покупатели,12,0) -> 87058796172 | L86: =VLOOKUP(A86,Реестр_Договоров,4,0) -> MX4000002P0001412 | M86: =VLOOKUP(L86,ПРИЦЕПЫ,11,0) -> 002-2515E30Q13-OK | N86: =VLOOKUP(L86,ПРИЦЕПЫ,2,0) -> Прицеп 2,5*1,5 м (до 750 кг.) | O86: =VLOOKUP(L86,ПРИЦЕПЫ,10,0) -> 1 ось | P86: =YEAR(VLOOKUP(L86,ПРИЦЕПЫ,7,0)) -> 2023 | Q86: =VLOOKUP(M86,матрица,16,0) -> 3650*1950*900 | R86: =VLOOKUP(M86,матрица,17,0) -> 2500*1500*300 | S86: =VLOOKUP(O86,ОТТС!$A$2:$B$3,2,0) -> ТС KZ Е-KZ.0317.00251 от 28.02.2023 | T86: 440000 | U86: =VLOOKUP(L86,ПРИЦЕПЫ,9,0) -> Астана
A87: 1249 | B87: =VLOOKUP(A87,'Реестр договоров'!$A$2:$D$298,2,0) -> 45499 | C87: =VLOOKUP(A87,Реестр_Договоров,3,0) -> Мошков | D87: =VLOOKUP(C87,Покупатели,2,0) -> Сергей | E87: =VLOOKUP(C87,Покупатели,3,0) -> Николаевич | F87: =VLOOKUP(C87,Покупатели,4,0) -> 041746930 | G87: =VLOOKUP(F87,Покупатели!$F$2:$N$762,2,0) -> 42628 | H87: =VLOOKUP(F87,Покупатели!$F$2:$N$762,3,0) -> МВД РК | I87: =VLOOKUP(C87,Покупатели!$C$2:$M$805,7,0) -> 711001301371 | J87: =IFERROR(__xludf.DUMMYFUNCTION("JOIN("" "", VLOOKUP(C87,Покупатели,8,0),VLOOKUP(C87,Покупатели,9,0),VLOOKUP(C87,Покупатели,10,0),VLOOKUP(C87,Покупатели,11,0))"),"Акмолинская область г. Атбасар ул. Молдагулова 21А, кв. 9") -> Акмолинская область г. Атбасар ул. Молдагулова 21А, кв. 9 | K87: =VLOOKUP(C87,Покупатели,12,0) -> 87718325882 | L87: =VLOOKUP(A87,Реестр_Договоров,4,0) -> MX4000002R0001662 | M87: =VLOOKUP(L87,ПРИЦЕПЫ,11,0) -> 002-2013E50Q13-OK | N87: =VLOOKUP(L87,ПРИЦЕПЫ,2,0) -> Прицеп 2,0*1,25 м (до 750 кг.) | O87: =VLOOKUP(L87,ПРИЦЕПЫ,10,0) -> 1 ось | P87: =YEAR(VLOOKUP(L87,ПРИЦЕПЫ,7,0)) -> 2024 | Q87: =VLOOKUP(M87,матрица,16,0) -> 3150*1700*1070 | R87: =VLOOKUP(M87,матрица,17,0) -> 2000*1250*500 | S87: =VLOOKUP(O87,ОТТС!$A$2:$B$3,2,0) -> ТС KZ Е-KZ.0317.00251 от 28.02.2023 | T87: 450000 | U87: =VLOOKUP(L87,ПРИЦЕПЫ,9,0) -> Кокшетау
A88: 1250 | B88: =VLOOKUP(A88,'Реестр договоров'!$A$2:$D$298,2,0) -> 45503 | C88: =VLOOKUP(A88,Реестр_Договоров,3,0) -> Калменова | D88: =VLOOKUP(C88,Покупатели,2,0) -> Айгерим | E88: =VLOOKUP(C88,Покупатели,3,0) -> Жарылкасынкызы | F88: =VLOOKUP(C88,Покупатели,4,0) -> 050269338 | G88: =VLOOKUP(F88,Покупатели!$F$2:$N$762,2,0) -> 44305 | H88: =VLOOKUP(F88,Покупатели!$F$2:$N$762,3,0) -> МВД РК | I88: =VLOOKUP(C88,Покупатели!$C$2:$M$805,7,0) -> 901229401734 | J88: =IFERROR(__xludf.DUMMYFUNCTION("JOIN("" "", VLOOKUP(C88,Покупатели,8,0),VLOOKUP(C88,Покупатели,9,0),VLOOKUP(C88,Покупатели,10,0),VLOOKUP(C88,Покупатели,11,0))"),"г.Астана р-н Алматы ул. Куйши дина д.1, кв.77") -> г.Астана р-н Алматы ул. Куйши дина д.1, кв.77 | K88: =VLOOKUP(C88,Покупатели,12,0) -> 87711643260 | L88: =VLOOKUP(A88,Реестр_Договоров,4,0) -> MX4000002R0001660 | M88: =VLOOKUP(L88,ПРИЦЕПЫ,11,0) -> 002-2013E30Q13-OK | N88: =VLOOKUP(L88,ПРИЦЕПЫ,2,0) -> Прицеп 2,0*1,25 м (до 750 кг.) | O88: =VLOOKUP(L88,ПРИЦЕПЫ,10,0) -> 1 ось | P88: =YEAR(VLOOKUP(L88,ПРИЦЕПЫ,7,0)) -> 2024 | Q88: =VLOOKUP(M88,матрица,16,0) -> 3150*1700*900 | R88: =VLOOKUP(M88,матрица,17,0) -> 2000*1250*300 | S88: =VLOOKUP(O88,ОТТС!$A$2:$B$3,2,0) -> ТС KZ Е-KZ.0317.00251 от 28.02.2023 | T88: 430000 | U88: =VLOOKUP(L88,ПРИЦЕПЫ,9,0) -> Астана
A89: 1251 | B89: =VLOOKUP(A89,'Реестр договоров'!$A$2:$D$298,2,0) -> 45504 | C89: =VLOOKUP(A89,Реестр_Договоров,3,0) -> Махмутов | D89: =VLOOKUP(C89,Покупатели,2,0) -> Тлеукабыл | E89: =VLOOKUP(C89,Покупатели,3,0) -> Рахимбекович | F89: =VLOOKUP(C89,Покупатели,4,0) -> 016937821 | G89: =VLOOKUP(F89,Покупатели!$F$2:$N$762,2,0) -> 38296 | H89: =VLOOKUP(F89,Покупатели!$F$2:$N$762,3,0) -> МВД РК | I89: =VLOOKUP(C89,Покупатели!$C$2:$M$805,7,0) -> 580801350535 | J89: =IFERROR(__xludf.DUMMYFUNCTION("JOIN("" "", VLOOKUP(C89,Покупатели,8,0),VLOOKUP(C89,Покупатели,9,0),VLOOKUP(C89,Покупатели,10,0),VLOOKUP(C89,Покупатели,11,0))"),"Акмолинская обл, Зерендинский район, станция Чаглинка, ул. Советская 11") -> Акмолинская обл, Зерендинский район, станция Чаглинка, ул. Советская 11 | K89: =VLOOKUP(C89,Покупатели,12,0) -> 87074322039 | L89: =VLOOKUP(A89,Реестр_Договоров,4,0) -> MX4000002R0001691 | M89: =VLOOKUP(L89,ПРИЦЕПЫ,11,0) -> 002-2013E50Q13-OK | N89: =VLOOKUP(L89,ПРИЦЕПЫ,2,0) -> Прицеп 2,0*1,25 м (до 750 кг.) | O89: =VLOOKUP(L89,ПРИЦЕПЫ,10,0) -> 1 ось | P89: =YEAR(VLOOKUP(L89,ПРИЦЕПЫ,7,0)) -> 2024 | Q89: =VLOOKUP(M89,матрица,16,0) -> 3150*1700*1070 | R89: =VLOOKUP(M89,матрица,17,0) -> 2000*1250*500 | S89: =VLOOKUP(O89,ОТТС!$A$2:$B$3,2,0) -> ТС KZ Е-KZ.0317.00251 от 28.02.2023 | T89: 400000 | U89: =VLOOKUP(L89,ПРИЦЕПЫ,9,0) -> Кокшетау
A90: 1252 | B90: =VLOOKUP(A90,'Реестр договоров'!$A$2:$D$298,2,0) -> 45504 | C90: =VLOOKUP(A90,Реестр_Договоров,3,0) -> Якубов | D90: =VLOOKUP(C90,Покупатели,2,0) -> Руфат | E90: =VLOOKUP(C90,Покупатели,3,0) -> Пархатович | F90: =VLOOKUP(C90,Покупатели,4,0) -> 047059093 | G90: =VLOOKUP(F90,Покупатели!$F$2:$N$762,2,0) -> 44092 | H90: =VLOOKUP(F90,Покупатели!$F$2:$N$762,3,0) -> МВД РК | I90: =VLOOKUP(C90,Покупатели!$C$2:$M$805,7,0) -> 930815301944 | J90: =IFERROR(__xludf.DUMMYFUNCTION("JOIN("" "", VLOOKUP(C90,Покупатели,8,0),VLOOKUP(C90,Покупатели,9,0),VLOOKUP(C90,Покупатели,10,0),VLOOKUP(C90,Покупатели,11,0))"),"Алматинская обл Уйгурский р-н, с.Кыргысай ул.Розыбакиева д.6") -> Алматинская обл Уйгурский р-н, с.Кыргысай ул.Розыбакиева д.6 | K90: =VLOOKUP(C90,Покупатели,12,0) -> 87025514793 | L90: =VLOOKUP(A90,Реестр_Договоров,4,0) -> MX4000002R0001491 | M90: =VLOOKUP(L90,ПРИЦЕПЫ,11,0) -> 002-2013E30Q13-OK | N90: =VLOOKUP(L90,ПРИЦЕПЫ,2,0) -> Прицеп 2,0*1,25 м (до 750 кг.) | O90: =VLOOKUP(L90,ПРИЦЕПЫ,10,0) -> 1 ось | P90: =YEAR(VLOOKUP(L90,ПРИЦЕПЫ,7,0)) -> 2024 | Q90: =VLOOKUP(M90,матрица,16,0) -> 3150*1700*900 | R90: =VLOOKUP(M90,матрица,17,0) -> 2000*1250*300 | S90: =VLOOKUP(O90,ОТТС!$A$2:$B$3,2,0) -> ТС KZ Е-KZ.0317.00251 от 28.02.2023 | T90: 380000 | U90: =VLOOKUP(L90,ПРИЦЕПЫ,9,0) -> Алматы
A91: 1253 | B91: =VLOOKUP(A91,'Реестр договоров'!$A$2:$D$298,2,0) -> 45504 | C91: =VLOOKUP(A91,Реестр_Договоров,3,0) -> Гусевы | D91: =VLOOKUP(C91,Покупатели,2,0) -> Евгений | E91: =VLOOKUP(C91,Покупатели,3,0) -> Сергеевич | F91: =VLOOKUP(C91,Покупатели,4,0) -> 051533375 | G91: =VLOOKUP(F91,Покупатели!$F$2:$N$762,2,0) -> 44791 | H91: =VLOOKUP(F91,Покупатели!$F$2:$N$762,3,0) -> МВД РК | I91: =VLOOKUP(C91,Покупатели!$C$2:$M$805,7,0) -> 831122300643 | J91: =IFERROR(__xludf.DUMMYFUNCTION("JOIN("" "", VLOOKUP(C91,Покупатели,8,0),VLOOKUP(C91,Покупатели,9,0),VLOOKUP(C91,Покупатели,10,0),VLOOKUP(C91,Покупатели,11,0))"),"Алматинская обл. г.Каскелен ул.Кисикова д.85") -> Алматинская обл. г.Каскелен ул.Кисикова д.85 | K91: =VLOOKUP(C91,Покупатели,12,0) -> 87771880880 | L91: =VLOOKUP(A91,Реестр_Договоров,4,0) -> MX4000002R0001628 | M91: =VLOOKUP(L91,ПРИЦЕПЫ,11,0) -> 002-2513E30Q13-OK | N91: =VLOOKUP(L91,ПРИЦЕПЫ,2,0) -> Прицеп 2,5*1,25 м (до 750 кг.) | O91: =VLOOKUP(L91,ПРИЦЕПЫ,10,0) -> 1 ось | P91: =YEAR(VLOOKUP(L91,ПРИЦЕПЫ,7,0)) -> 2024 | Q91: =VLOOKUP(M91,матрица,16,0) -> 3650*1700*900 | R91: =VLOOKUP(M91,матрица,17,0) -> 2500*1250*300 | S91: =VLOOKUP(O91,ОТТС!$A$2:$B$3,2,0) -> ТС KZ Е-KZ.0317.00251 от 28.02.2023 | T91: 360000 | U91: =VLOOKUP(L91,ПРИЦЕПЫ,9,0) -> Алматы
A92: 1254 | B92: =VLOOKUP(A92,'Реестр договоров'!$A$2:$D$298,2,0) -> 45504 | C92: =VLOOKUP(A92,Реестр_Договоров,3,0) -> Сейдеметов1 | D92: =VLOOKUP(C92,Покупатели,2,0) -> Асхат | E92: =VLOOKUP(C92,Покупатели,3,0) -> Ертасович | F92: =VLOOKUP(C92,Покупатели,4,0) -> 046023523 | G92: =VLOOKUP(F92,Покупатели!$F$2:$N$762,2,0) -> 43903 | H92: =VLOOKUP(F92,Покупатели!$F$2:$N$762,3,0) -> МВД РК | I92: =VLOOKUP(C92,Покупатели!$C$2:$M$805,7,0) -> 700408301786 | J92: =IFERROR(__xludf.DUMMYFUNCTION("JOIN("" "", VLOOKUP(C92,Покупатели,8,0),VLOOKUP(C92,Покупатели,9,0),VLOOKUP(C92,Покупатели,10,0),VLOOKUP(C92,Покупатели,11,0))"),"Кызылординская обл. г.Кызылорда ул.Багаева д.4") -> Кызылординская обл. г.Кызылорда ул.Багаева д.4 | K92: =VLOOKUP(C92,Покупатели,12,0) -> 87773342870 | L92: =VLOOKUP(A92,Реестр_Договоров,4,0) -> MX4000002R0001582 | M92: =VLOOKUP(L92,ПРИЦЕПЫ,11,0) -> 002-2013E50Q13-OK30 | N92: =VLOOKUP(L92,ПРИЦЕПЫ,2,0) -> Прицеп 2,0*1,25 м (до 750 кг.) | O92: =VLOOKUP(L92,ПРИЦЕПЫ,10,0) -> 1 ось | P92: =YEAR(VLOOKUP(L92,ПРИЦЕПЫ,7,0)) -> 2024 | Q92: =VLOOKUP(M92,матрица,16,0) -> 3150*1700*1070 | R92: =VLOOKUP(M92,матрица,17,0) -> 2000*1250*500 | S92: =VLOOKUP(O92,ОТТС!$A$2:$B$3,2,0) -> ТС KZ Е-KZ.0317.00251 от 28.02.2023 | T92: 380000 | U92: =VLOOKUP(L92,ПРИЦЕПЫ,9,0) -> Алматы
A93: 1255 | B93: =VLOOKUP(A93,'Реестр договоров'!$A$2:$D$298,2,0) -> 45509 | C93: =VLOOKUP(A93,Реестр_Договоров,3,0) -> Бабенков | D93: =VLOOKUP(C93,Покупатели,2,0) -> Александр | E93: =VLOOKUP(C93,Покупатели,3,0) -> Евгеньевич | F93: =VLOOKUP(C93,Покупатели,4,0) -> 054257390 | G93: =VLOOKUP(F93,Покупатели!$F$2:$N$762,2,0) -> 44897 | H93: =VLOOKUP(F93,Покупатели!$F$2:$N$762,3,0) -> МВД РК | I93: =VLOOKUP(C93,Покупатели!$C$2:$M$805,7,0) -> 811013350702 | J93: =IFERROR(__xludf.DUMMYFUNCTION("JOIN("" "", VLOOKUP(C93,Покупатели,8,0),VLOOKUP(C93,Покупатели,9,0),VLOOKUP(C93,Покупатели,10,0),VLOOKUP(C93,Покупатели,11,0))"),"СКО, район Габита Мусрепова, с. Чистополье, ул. Космонавтов, дом 5") -> СКО, район Габита Мусрепова, с. Чистополье, ул. Космонавтов, дом 5 | K93: =VLOOKUP(C93,Покупатели,12,0) -> 87027535221 | L93: =VLOOKUP(A93,Реестр_Договоров,4,0) -> MX4000002R0001710 | M93: 002-2313E30Q13-OK | N93: Прицеп 2,0*1,25 м (до 750 кг.) | O93: =VLOOKUP(L93,ПРИЦЕПЫ,10,0) -> 1 ось | P93: =YEAR(VLOOKUP(L93,ПРИЦЕПЫ,7,0)) -> 2024 | Q93: 3150*1700*900 | R93: 2000*1250*300 | S93: =VLOOKUP(O93,ОТТС!$A$2:$B$3,2,0) -> ТС KZ Е-KZ.0317.00251 от 28.02.2023 | T93: 350000 | U93: =VLOOKUP(L93,ПРИЦЕПЫ,9,0) -> Кокшетау
A94: 1256 | B94: =VLOOKUP(A94,'Реестр договоров'!$A$2:$D$298,2,0) -> 45510 | C94: =VLOOKUP(A94,Реестр_Договоров,3,0) -> Ахатов | D94: =VLOOKUP(C94,Покупатели,2,0) -> Жасулан | E94: =VLOOKUP(C94,Покупатели,3,0) -> Болатович | F94: =VLOOKUP(C94,Покупатели,4,0) -> 053556638 | G94: =VLOOKUP(F94,Покупатели!$F$2:$N$762,2,0) -> 44784 | H94: =VLOOKUP(F94,Покупатели!$F$2:$N$762,3,0) -> МВД РК | I94: =VLOOKUP(C94,Покупатели!$C$2:$M$805,7,0) -> 950322351914 | J94: =IFERROR(__xludf.DUMMYFUNCTION("JOIN("" "", VLOOKUP(C94,Покупатели,8,0),VLOOKUP(C94,Покупатели,9,0),VLOOKUP(C94,Покупатели,10,0),VLOOKUP(C94,Покупатели,11,0))"),"г.Астана р-н Есиль ул.Сарайшык 7/1") -> г.Астана р-н Есиль ул.Сарайшык 7/1 | K94: =VLOOKUP(C94,Покупатели,12,0) -> 87058866140 | L94: =VLOOKUP(A94,Реестр_Договоров,4,0) -> MX4000002R0001490 | M94: =VLOOKUP(L94,ПРИЦЕПЫ,11,0) -> 002-2013E30Q13-OK | N94: =VLOOKUP(L94,ПРИЦЕПЫ,2,0) -> Прицеп 2,0*1,25 м (до 750 кг.) | O94: =VLOOKUP(L94,ПРИЦЕПЫ,10,0) -> 1 ось | P94: =YEAR(VLOOKUP(L94,ПРИЦЕПЫ,7,0)) -> 2024 | Q94: =VLOOKUP(M94,матрица,16,0) -> 3150*1700*900 | R94: =VLOOKUP(M94,матрица,17,0) -> 2000*1250*300 | S94: =VLOOKUP(O94,ОТТС!$A$2:$B$3,2,0) -> ТС KZ Е-KZ.0317.00251 от 28.02.2023 | T94: 380000 | U94: =VLOOKUP(L94,ПРИЦЕПЫ,9,0) -> Астана
A95: 1257 | B95: =VLOOKUP(A95,'Реестр договоров'!$A$2:$D$298,2,0) -> 45510 | C95: =VLOOKUP(A95,Реестр_Договоров,3,0) -> Легеза | D95: =VLOOKUP(C95,Покупатели,2,0) -> Вячеслав | E95: =VLOOKUP(C95,Покупатели,3,0) -> Михайлович | F95: =VLOOKUP(C95,Покупатели,4,0) -> 026891863 | G95: =VLOOKUP(F95,Покупатели!$F$2:$N$762,2,0) -> 43978 | H95: =VLOOKUP(F95,Покупатели!$F$2:$N$762,3,0) -> МВД РК | I95: =VLOOKUP(C95,Покупатели!$C$2:$M$805,7,0) -> 660923300867 | J95: =IFERROR(__xludf.DUMMYFUNCTION("JOIN("" "", VLOOKUP(C95,Покупатели,8,0),VLOOKUP(C95,Покупатели,9,0),VLOOKUP(C95,Покупатели,10,0),VLOOKUP(C95,Покупатели,11,0))"),"СКО, Айыртауский р-н, с. Куспек Озерная 26") -> СКО, Айыртауский р-н, с. Куспек Озерная 26 | K95: =VLOOKUP(C95,Покупатели,12,0) -> 87058302966 | L95: =VLOOKUP(A95,Реестр_Договоров,4,0) -> MX4000002R0001696 | M95: =VLOOKUP(L95,ПРИЦЕПЫ,11,0) -> 002-2013E50Q13-OK60 | N95: =VLOOKUP(L95,ПРИЦЕПЫ,2,0) -> Прицеп 2,0*1,25 м (до 750 кг.) | O95: =VLOOKUP(L95,ПРИЦЕПЫ,10,0) -> 1 ось | P95: =YEAR(VLOOKUP(L95,ПРИЦЕПЫ,7,0)) -> 2024 | Q95: =VLOOKUP(M95,матрица,16,0) -> 3150*1700*1070 | R95: =VLOOKUP(M95,матрица,17,0) -> 2000*1250*500 | S95: =VLOOKUP(O95,ОТТС!$A$2:$B$3,2,0) -> ТС KZ Е-KZ.0317.00251 от 28.02.2023 | T95: 360000 | U95: =VLOOKUP(L95,ПРИЦЕПЫ,9,0) -> Кокшетау
A96: 1258 | B96: =VLOOKUP(A96,'Реестр договоров'!$A$2:$D$298,2,0) -> 45511 | C96: =VLOOKUP(A96,Реестр_Договоров,3,0) -> Коптлеуов 1 | D96: =VLOOKUP(C96,Покупатели,2,0) -> Аслан | E96: =VLOOKUP(C96,Покупатели,3,0) -> Толегенович | F96: =VLOOKUP(C96,Покупатели,4,0) -> 0 | G96: =VLOOKUP(F96,Покупатели!$F$2:$N$762,2,0) -> 45497 | H96: =VLOOKUP(F96,Покупатели!$F$2:$N$762,3,0) -> МВД РК | I96: =VLOOKUP(C96,Покупатели!$C$2:$M$805,7,0) -> 780407301705 | J96: =IFERROR(__xludf.DUMMYFUNCTION("JOIN("" "", VLOOKUP(C96,Покупатели,8,0),VLOOKUP(C96,Покупатели,9,0),VLOOKUP(C96,Покупатели,10,0),VLOOKUP(C96,Покупатели,11,0))"),"0 г.Талдыкурган 0 0") -> 0 г.Талдыкурган 0 0 | K96: =VLOOKUP(C96,Покупатели,12,0) -> 0 | L96: =VLOOKUP(A96,Реестр_Договоров,4,0) -> MX4000002R0001552 | M96: =VLOOKUP(L96,ПРИЦЕПЫ,11,0) -> 002-2013E30Q13-OK | N96: =VLOOKUP(L96,ПРИЦЕПЫ,2,0) -> Прицеп 2,0*1,25 м (до 750 кг.) | O96: =VLOOKUP(L96,ПРИЦЕПЫ,10,0) -> 1 ось | P96: =YEAR(VLOOKUP(L96,ПРИЦЕПЫ,7,0)) -> 2024 | Q96: =VLOOKUP(M96,матрица,16,0) -> 3150*1700*900 | R96: =VLOOKUP(M96,матрица,17,0) -> 2000*1250*300 | S96: =VLOOKUP(O96,ОТТС!$A$2:$B$3,2,0) -> ТС KZ Е-KZ.0317.00251 от 28.02.2023 | T96: 320000 | U96: =VLOOKUP(L96,ПРИЦЕПЫ,9,0) -> Алматы
